Workbook

Sheet README
A1: Wrenfield GRC Workbook: all artifacts, one governance system
A2: Wrenfield Health (fictional) · simulated NIST SP 800-53 Rev. 5 (Release 5.2.0) assessment · synthetic data
A4: As-of (status) date | B4: 46283 | C4: <- input: all aging/overdue formulas reference this cell (use =TODAY() in a live workbook)
A6: Sheets | B6: Dashboard (live formulas) · Controls · Risks · Findings · POAM · Milestones · Evidence · AccessReview · VendorInventory · VendorAssessment · VendorFindings · Lists
A7: Why one workbook | B7: Cross-sheet formulas prove the artifacts share IDs: the Dashboard counts across sheets, so a status change anywhere updates management reporting
A8: Recalculation | B8: Built with openpyxl; Excel/Sheets/LibreOffice compute formulas on open (fullCalcOnLoad). Formula results were verified with pycel (tools/check_formulas.py)
A9: Source of truth | B9: data/*.yaml -> tools/build.py

Sheet Dashboard
A1: Executive Dashboard (live formulas)
A2: As of | B2: =README!$B$4
A4: Metric ID | B4: Metric | C4: Value | D4: Definition
A5: MET-01 | B5: Controls in scope | C5: =COUNTIF(Controls!$A$2:$A$500,"?*") | D5: Count of control rows
A6: MET-02 | B6: Controls assessed (excl. N/A) | C6: =COUNTIF(Controls!$V:$V,"Satisfied")+COUNTIF(Controls!$V:$V,"Other Than Satisfied") | D6: Result is Satisfied or Other Than Satisfied
A7: MET-03 | B7: Controls Satisfied | C7: =COUNTIF(Controls!$V:$V,"Satisfied") | D7: Result = Satisfied
A8: MET-03a | B8: % of assessed controls Satisfied | C8: =ROUND(C7/C6,2) | D8: MET-03 / MET-02
A9: MET-04a | B9: Validated: Implemented | C9: =COUNTIF(Controls!$M:$M,"Implemented") | D9: Assessor-validated status
A10: MET-04b | B10: Validated: Partially Implemented | C10: =COUNTIF(Controls!$M:$M,"Partially Implemented") | D10: Assessor-validated status
A11: MET-04c | B11: Validated: Planned or Not Implemented | C11: =COUNTIF(Controls!$M:$M,"Planned")+COUNTIF(Controls!$M:$M,"Not Implemented") | D11: Assessor-validated status
A12: MET-05 | B12: Controls where assessor changed owner-stated status | C12: =COUNTIF(Controls!$N:$N,"Yes") | D12: Owner overstatement indicator
A13: MET-06 | B13: Findings (total) | C13: =COUNTIF(Findings!$A$2:$A$500,"FIND-*") | D13: All findings
A14: MET-06a | B14: Open findings (not Closed / Risk Accepted) | C14: =C13-COUNTIF(Findings!$O:$O,"Closed")-COUNTIF(Findings!$O:$O,"Risk Accepted") | D14: Total minus Closed minus Risk Accepted
A15: MET-07 | B15: Open High/Critical findings | C15: =COUNTIFS(Findings!$C:$C,"High",Findings!$O:$O,"<>Closed")+COUNTIFS(Findings!$C:$C,"Critical",Findings!$O:$O,"<>Closed") | D15: Severity High/Critical and not Closed
A16: MET-08 | B16: Overdue POA&M items | C16: =COUNTIF(POAM!$T:$T,"Yes") | D16: Formula-driven Overdue? column
A17: MET-08a | B17: Slipped POA&M items (target changed) | C17: =COUNTIF(POAM!$U:$U,"Yes") | D17: Current target <> original target
A18: MET-09 | B18: POA&M closed and validated | C18: =COUNTIF(POAM!$Q:$Q,"Closed") | D18: Status Closed (requires validation)
A19: MET-10 | B19: Access-review exceptions (distinct) | C19: =SUM(AccessReview!$AD:$AD) | D19: Distinct AR-EX IDs (helper column counts each ID once)
A20: MET-10a | B20: Access-review exception rows | C20: =COUNTIF(AccessReview!$S:$S,"AR-EX-*") | D20: Rows carrying an exception
A21: MET-11 | B21: Vendor findings (VR) total | C21: =COUNTIF(VendorFindings!$A$2:$A$500,"VR-*") | D21: All VR items
A22: MET-11a | B22: Vendor findings Critical/High | C22: =COUNTIF(VendorFindings!$C:$C,"Critical")+COUNTIF(VendorFindings!$C:$C,"High") | D22: Severity
A23: MET-11b | B23: Tier 1-2 vendors with current assessment | C23: =COUNTIFS(VendorInventory!$K:$K,"<=2",VendorInventory!$O:$O,"Yes") | D23: Formula-driven currency
A24: MET-11c | B24: Tier 1-2 vendors total | C24: =COUNTIF(VendorInventory!$K:$K,"<=2") | D24: Tier from inherent score
A25: MET-12 | B25: Evidence completion % | C25: =ROUND((COUNTIF(Evidence!$I:$I,"Accepted")+COUNTIF(Evidence!$I:$I,"Closed"))/COUNTIF(Evidence!$A:$A,"EVID-*"),2) | D25: (Accepted + Closed) / requested
A26: MET-13a | B26: Enterprise risks rated High+ (current) | C26: =COUNTIF(Risks!$O:$O,"High")+COUNTIF(Risks!$O:$O,"Critical") | D26: Current (as tested)
A27: MET-13b | B27: Enterprise risks rated High+ (residual target) | C27: =COUNTIF(Risks!$W:$W,"High")+COUNTIF(Risks!$W:$W,"Critical") | D27: Residual target

Sheet Controls
A1: Control ID | B1: Control Family | C1: Control Name | D1: Baseline (SP 800-53B) | E1: Control Requirement Summary | F1: Applicability | G1: Applicability Rationale | H1: Control Origination | I1: System / Process | J1: Control Owner | K1: Business Requirements (REQ) | L1: Implementation Status (Owner-Stated) | M1: Implementation Status (Assessor-Validated) | N1: Status Changed by Assessor? | O1: Implementation Description | P1: Evidence Required | Q1: Evidence Available (EVID) | R1: Evidence Location | S1: Highest Evidence Level | T1: Testing Method | U1: Test Procedure / Expected vs Actual | V1: Assessment Result | W1: Gap Identified | X1: Risk Rating | Y1: Related Risk ID | Z1: Related Finding ID | AA1: Related POA&M ID | AB1: POA&M Status (as of status date) | AC1: Observations | AD1: Last Reviewed | AE1: Next Review | AF1: CSF 2.0 Function (informal) | AG1: Notes
A2: AC-1 | B2: AC - Access Control | C2: Policy and Procedures | D2: Moderate | E2: Develop, document, and disseminate an access control policy and procedures; designate an official to manage them; review and update them at a defined frequency and after defined events. | F2: Applicable | H2: Common (organization-wide) | I2: All in-scope systems | J2: Alicia Moreno (CISO) | K2: REQ-001; REQ-014; REQ-024 | L2: Implemented | M2: Implemented | N2: =IF(L2<>M2,"Yes","No") | O2: Access Control Policy ACP-002 v3.1 (approved 2025-01-15 by the CISO) covers account types, approvals, least privilege, separate admin accounts (§5.4), 24h de-provisioning (§5.3), inactivity (§5.6), and quarterly privileged recertification. It is published on the intranet and acknowledged at onboarding. JML procedure SOP-IAM-02 v2.0 implements it. | P2: Current approved policy and procedures, approval record, review history, dissemination evidence | Q2: EVID-001; EVID-002 | R2: GRC-Vault:/WCP-2026/AC/EVID-001_ACP-002_v3.1.pdf; GRC-Vault:/WCP-2026/AC/EVID-002_SOP-IAM-02_v2.0.pdf | S2: Design | T2: Examine, Interview | U2: Examined ACP-002 v3.1 and SOP-IAM-02 v2.0 against the AC family requirements, and interviewed the CISO. Expected: policy reviewed within the 12-month cycle. Actual: the last approved review was 2025-01-15, so it is 5 months overdue. Draft v3.2 has been in review since 2026-05. Content is adequate, and policy statements are specific enough to test (they drove several findings). | V2: Satisfied | W2: Annual review overdue by about 5 months (below the finding threshold: the content is current and the draft is in approval). | X2: Low | AB2: n/a | AC2: OBS-01 | AD2: 46220 | AE2: 46583 | AF2: PR | AG2: A policy existing does not prove the controls operate. AC-2/AC-6 test results show several ACP-002 requirements not operating.
A3: AC-2 | B3: AC - Access Control | C3: Account Management | D3: Moderate | E3: Define allowed account types; assign account managers; require approvals for account creation; create, modify, disable, and remove accounts per defined conditions; monitor account use; notify account managers when accounts are no longer needed; review accounts for compliance at a defined frequency. | F3: Applicable | H3: Hybrid (Okta common control + system-specific accounts) | I3: SYS-01, SYS-02, SYS-03, SYS-04, SYS-05, SYS-06, SYS-07, SYS-08, SYS-09 | J3: Nadia Rahman (IAM Engineer) | K3: REQ-001; REQ-004; REQ-013; REQ-014; REQ-023 | L3: Implemented | M3: Partially Implemented | N3: =IF(L3<>M3,"Yes","No") | O3: Okta is the identity source for SSO apps. Access requests go through Jira service desk tickets approved by the manager and the system owner. Termination tickets are raised manually by IT from HR emails. Local accounts exist outside Okta on AWS (legacy IAM users), wf-sftp-01, and the Quarrystone portal, and are managed ad hoc. There is a service-account register, but it lacked owner and rotation fields until 2026-07. | P3: Account-management procedure; user and entitlement populations from each system; HR roster; service-account register; recertification records | Q3: EVID-002; EVID-005; EVID-006; EVID-007; EVID-013; EVID-061; EVID-065 | R3: GRC-Vault:/WCP-2026/AC/EVID-002_SOP-IAM-02_v2.0.pdf; access-review/source-exports/okta_users.csv; access-review/source-exports/entitlements.csv; evidence/IA/EVID-007_aws-iam-credential-report_2026-06-30.csv; access-review/source-exports/service_accounts.csv; evidence/AC/EVID-061_terminations-and-deactivations_2026-07-01_to_09-09.csv; GRC-Vault:/WCP-2026/IA/EVID-065_service-register-v2026-09.csv | S3: Operating Effectiveness | T3: Examine, Interview, Test | U3: Full reconciliation of 106 entitlements on 9 systems against HR, the role baseline, the SoD rules, and the service register (tools/review_engine.py). Expected: every account is authorized, owned, and current. Actual: 20 exceptions across 28 entitlement rows. They include terminated users (4), a duplicate identity, inactive access, contractor term drift, service accounts without owners or rotation, and a shared vendor login. | V3: Other Than Satisfied | W3: Account lifecycle is not enforced for local (non-SSO) accounts, contractors, transfers, or service accounts. Account reviews did not catch these. | X3: High | Y3: RISK-002; RISK-004; RISK-017 | Z3: FIND-001; FIND-004; FIND-005; FIND-006 | AA3: POAM-001; POAM-004; POAM-005; POAM-006 | AB3: POAM-001: Closed; POAM-004: In Progress; POAM-005: Closed; POAM-006: Closed | AD3: 46220 | AE3: 46371 | AF3: PR | AG3: Anchor control for the access review. Individual exceptions roll up into 4 findings by root cause.
A4: AC-2(1) | B4: AC - Access Control | C4: Automated System Account Management | D4: Moderate | E4: Support management of system accounts with automated mechanisms. | F4: Applicable | H4: Common (Okta) | I4: SYS-02, SYS-06 | J4: Nadia Rahman (IAM Engineer) | K4: REQ-004; REQ-013 | L4: Implemented | M4: Partially Implemented | N4: =IF(L4<>M4,"Yes","No") | O4: Okta provisions users to GitHub and AWS IAM Identity Center with SCIM and group push. The PeopleHub-to-Okta integration syncs attributes only. Terminations and contract end dates did not trigger de-provisioning before 2026-08, and contractor accounts had no expiry dates. | P4: Integration configuration; provisioning and de-provisioning logs; evidence that HR events trigger account actions | Q4: EVID-004; EVID-005; EVID-062 | R4: evidence/AC/EVID-004_okta-deactivation-events-2026H1.csv; access-review/source-exports/okta_users.csv; evidence/AC/EVID-062_hr-okta-reconciliation-job_2026-09-10.csv | S4: Implementation | T4: Examine, Interview | U4: Examined the Okta-PeopleHub integration settings and interviewed the IAM Engineer. Expected: HR termination events automatically trigger de-provisioning. Actual: sync was attribute-only, so de-provisioning was a manual ticket. This design gap is the root cause of FIND-001. Post-remediation: a daily reconciliation job with auto-ticketing (live 2026-08-03) and Okta account-expiry dates for contractors were verified in EVID-062. | V4: Other Than Satisfied | W4: No automated de-provisioning from the authoritative HR source (fixed with compensating automation; full lifecycle-management licensing is planned for FY27). | X4: High | Y4: RISK-002 | Z4: FIND-001 | AA4: POAM-001 | AB4: POAM-001: Closed | AD4: 46220 | AE4: 46583 | AF4: PR | AG4: The reconciliation job is a detective and ticketing automation, not true HR-driven de-provisioning. The status stays Partially Implemented until lifecycle automation is licensed.
A5: AC-2(3) | B5: AC - Access Control | C5: Disable Accounts | D5: Moderate | E5: Disable accounts within a defined period when they have expired, are no longer associated with a user or function, violate policy, or have been inactive for a defined period. | F5: Applicable | H5: Hybrid | I5: SYS-01, SYS-02, SYS-03, SYS-07, SYS-09 | J5: Nadia Rahman (IAM Engineer) | K5: REQ-004; REQ-013 | L5: Implemented | M5: Partially Implemented | N5: =IF(L5<>M5,"Yes","No") | O5: ACP-002 §5.3 requires disabling within 24 hours of termination, and §5.6 requires disabling after 90 days of inactivity. IT deactivates Okta accounts from manual tickets. There was no inactivity automation and no process for local accounts. | P5: Complete population of terminations in the period; de-provisioning logs for every system; inactivity report | Q5: EVID-003; EVID-004; EVID-007; EVID-061; EVID-062; EVID-064 | R5: evidence/AC/EVID-003_peoplehub-terminations-2026H1.csv; evidence/AC/EVID-004_okta-deactivation-events-2026H1.csv; evidence/IA/EVID-007_aws-iam-credential-report_2026-06-30.csv; evidence/AC/EVID-061_terminations-and-deactivations_2026-07-01_to_09-09.csv; evidence/AC/EVID-062_hr-okta-reconciliation-job_2026-09-10.csv; evidence/IA/EVID-064_aws-iam-credential-report_2026-09-04.csv | S5: Operating Effectiveness | T5: Examine, Test | U5: Re-performed the 24h test on all 19 H1 terminations (docs/assessment/test-results/termination-deprovisioning.md). Expected: 19 of 19 within 24h, including non-SSO accounts. Actual: 16 of 19 within SLA, 1 late (209h), 2 never deactivated (one with a post-termination sign-in, which became INC-2026-0117), plus 1 active local AWS IAM user and 1 Quarrystone portal account belonging to leavers. Validation re-test (2026-09-10): 7 of 7 within SLA, and the reconciliation job reported 0 exceptions. | V5: Other Than Satisfied | W5: De-provisioning depended on manual tickets and missed local accounts. | X5: High | Y5: RISK-002 | Z5: FIND-001 | AA5: POAM-001 | AB5: POAM-001: Closed | AD5: 46275 | AE5: 46583 | AF5: PR | AG5: Remediation validated 2026-09-10. Full re-test at the FY27 assessment because the post-fix operating sample is small (7).
A6: AC-5 | B6: AC - Access Control | C6: Separation of Duties | D6: Moderate | E6: Identify and document duties that require separation, and define system access authorizations that support that separation. | F6: Applicable | H6: System-specific (Ledgerline) | I6: SYS-07 | J6: Laura Brenneman (Controller) | K6: REQ-023; REQ-024 | L6: Implemented | M6: Partially Implemented | N6: =IF(L6<>M6,"Yes","No") | O6: Ledgerline has an SoD ruleset (SOD-01 vendor master vs payment approval; SOD-02 AP entry vs approval). After the AP Specialist left in 2026-05, the Senior Accountant held both Vendor Master Maintain and Payment Approver (<= $25k). The compensating control is a monthly vendor-master change report that the Controller reviews and signs. | P6: SoD matrix; role assignments; evidence of the compensating review for each month | Q6: EVID-014; EVID-015; EVID-060 | R6: access-review/source-exports/sod_rules.csv; GRC-Vault:/WCP-2026/AC/EVID-015_vendor-master-reviews-H1.pdf; risk/risk-acceptance/RACC-001.md | S6: Operating Effectiveness | T6: Examine, Interview, Test | U6: Tested role assignments against the SoD rules (review engine) and inspected 6 of 6 monthly compensating reviews (Jan–Jun). Expected: no user holds conflicting roles, or a documented and operating compensating control exists. Actual: 1 conflict (jmercer, SOD-01). The compensating review operated 6 of 6 months (signed, dated, 2 bank-detail changes independently verified by callback). The conflict was not formally risk-accepted until RACC-001 (2026-08-12). | V6: Other Than Satisfied | W6: Conflicting duties held by one user. The compensating control operates, but it was undocumented as a risk decision. | X6: Moderate | Y6: RISK-013 | Z6: FIND-007 | AA6: POAM-007 | AB6: POAM-007: Risk Accepted | AD6: 46220 | AE6: 46477 | AF6: PR | AG6: Formally accepted (RACC-001, CFO, expires 2027-03-31). This is the project's worked example of a compensating control plus risk acceptance.
A7: AC-6 | B7: AC - Access Control | C7: Least Privilege | D7: Moderate | E7: Employ the principle of least privilege, allowing only authorized accesses necessary to accomplish assigned tasks. | F7: Applicable | H7: Hybrid | I7: SYS-01, SYS-02, SYS-03, SYS-04 | J7: Tomasz Wierzbicki (Director, Platform Engineering) | K7: REQ-001; REQ-014; REQ-023 | L7: Implemented | M7: Partially Implemented | N7: =IF(L7<>M7,"Yes","No") | O7: A role-based access baseline exists (role_access_matrix). AWS permission sets are assigned through Okta groups. Temporary grants (for migrations and troubleshooting) have no expiry mechanism. | P7: Role baseline; entitlement exports; justification for privileged grants | Q7: EVID-006; EVID-016; EVID-017; EVID-075; EVID-076 | R7: access-review/source-exports/entitlements.csv; access-review/source-exports/entitlements.csv; access-review/source-exports/entitlements.csv; GRC-Vault:/WCP-2026/AC/EVID-075_idc-assignments-2026-09-03.csv; GRC-Vault:/WCP-2026/AC/EVID-076_github-owners-2026-08-12.csv | S7: Operating Effectiveness | T7: Examine, Test | U7: Compared every privileged and PHI entitlement to the role baseline. Expected: 0 grants outside the baseline without approved justification. Actual: 8 rows outside the baseline (F-BASELINE), all confirmed on review. 6 are excessive privileged grants (2 prod AdministratorAccess, 2 GitHub owners, 1 Okta Super Admin, 1 PHI database write) under FIND-003. The other 2 are PHI read access kept after a transfer (FIND-004) and PHI access outside a contractor's SOW (FIND-006). | V7: Other Than Satisfied | W7: Temporary privileged grants never expire; access is not re-baselined when roles change. | X7: High | Y7: RISK-001; RISK-004 | Z7: FIND-003 | AA7: POAM-003 | AB7: POAM-003: In Progress | AD7: 46220 | AE7: 46331 | AF7: PR
A8: AC-6(2) | B8: AC - Access Control | C8: Non-privileged Access for Nonsecurity Functions | D8: Moderate | E8: Require users of privileged accounts or roles to use non-privileged accounts or roles when accessing nonsecurity functions. | F8: Applicable | H8: Hybrid | I8: SYS-01, SYS-02 | J8: Nadia Rahman (IAM Engineer) | K8: REQ-003; REQ-014 | L8: Implemented | M8: Partially Implemented | N8: =IF(L8<>M8,"Yes","No") | O8: ACP-002 §5.4 (since 2025-07) requires separate -adm accounts for AWS prod AdministratorAccess and Okta Super Administrator. Two admins (jkim-adm, nrahman-adm) follow it. Others still hold admin roles on email and browsing accounts. | P8: List of privileged role holders with account type | Q8: EVID-005; EVID-016; EVID-075 | R8: access-review/source-exports/okta_users.csv; access-review/source-exports/entitlements.csv; GRC-Vault:/WCP-2026/AC/EVID-075_idc-assignments-2026-09-03.csv | S8: Implementation | T8: Examine, Test | U8: Tested account type for every holder of the two covered roles. Expected: all on -adm or break-glass accounts. Actual: 6 of 10 covered assignments were not on -adm or break-glass accounts (F-DAILYADMIN): 2 legitimate SRE holders (AR-EX-10), and 4 assignments that were also excessive or orphaned (AR-EX-03/05/06/09). | V8: Other Than Satisfied | W8: Separate admin accounts are required by policy but not implemented for most admins. | X8: High | Y8: RISK-001 | Z8: FIND-003 | AA8: POAM-003 | AB8: POAM-003: In Progress | AD8: 46220 | AE8: 46331 | AF8: PR
A9: AC-6(5) | B9: AC - Access Control | C9: Privileged Accounts | D9: Moderate | E9: Restrict privileged accounts on the system to defined personnel or roles. | F9: Applicable | H9: Hybrid | I9: SYS-01, SYS-02, SYS-03 | J9: Tomasz Wierzbicki (Director, Platform Engineering) | K9: REQ-003; REQ-014; REQ-023 | L9: Implemented | M9: Partially Implemented | N9: =IF(L9<>M9,"Yes","No") | O9: Defined privileged roles are SRE (AWS admin), IAM Engineer (Okta Super Admin), and CTO plus platform (up to 3 GitHub owners). Break-glass accounts are vaulted and tested quarterly. | P9: Privileged role definitions; complete privileged-account population per system | Q9: EVID-016; EVID-017; EVID-075; EVID-076; EVID-077 | R9: access-review/source-exports/entitlements.csv; access-review/source-exports/entitlements.csv; GRC-Vault:/WCP-2026/AC/EVID-075_idc-assignments-2026-09-03.csv; GRC-Vault:/WCP-2026/AC/EVID-076_github-owners-2026-08-12.csv; GRC-Vault:/WCP-2026/AC/EVID-077_okta-admin-roles-2026-07-21.csv | S9: Operating Effectiveness | T9: Examine, Test | U9: Enumerated all 37 privileged entitlements. Expected: every holder is in a defined privileged role. Actual: AWS prod AdministratorAccess had 6 human-linked holders (including a terminated employee's local IAM user) against 3 authorized SRE roles. GitHub owners were 5 against a maximum of 3. Okta Super Admin had 1 unauthorized holder. Break-glass accounts were well controlled (last tests 2026-04-15 and 2026-05-12). | V9: Other Than Satisfied | W9: More privileged holders than the defined roles allow. | X9: High | Y9: RISK-001 | Z9: FIND-003 | AA9: POAM-003 | AB9: POAM-003: In Progress | AD9: 46220 | AE9: 46331 | AF9: PR
A10: AC-6(7) | B10: AC - Access Control | C10: Review of User Privileges | D10: Moderate | E10: Review the privileges assigned to defined roles or classes of users at a defined frequency to validate the need for them, and reassign or remove privileges as necessary. | F10: Applicable | H10: Hybrid | I10: SYS-01, SYS-02, SYS-03, SYS-04 | J10: Alicia Moreno (CISO) | K10: REQ-004; REQ-014; REQ-023 | L10: Implemented | M10: Partially Implemented | N10: =IF(L10<>M10,"Yes","No") | O10: Quarterly Okta manager certification campaigns cover app-assignment level access only. AWS permission sets, GitHub roles, database roles, and local accounts were never in scope. Before this assessment, no privileged-access review existed. | P10: Review campaign exports showing population, reviewer, decision, date, and resulting changes | Q10: EVID-008; EVID-009; EVID-074 | R10: evidence/AC/EVID-008_q1-certification-summary.md; evidence/AC/EVID-009_insufficient-screenshot-example.md; GRC-Vault:/WCP-2026/AC/EVID-074_pending | S10: Operating Effectiveness | T10: Examine, Interview, Test | U10: Examined the Q1 2026 campaign export (412 decisions by 23 reviewers). Expected: complete population, meaningful decisions, and removals actioned. Actual: 100% approved, and 17 of 23 reviewers finished in under 5 minutes. The campaign approved rgupta2 (duplicate) and cfernandes's pre-transfer access. Privileged systems were out of scope. The dashboard screenshot first provided (EVID-009) was insufficient: no population, no decisions. | V10: Other Than Satisfied | W10: Recertification is incomplete in scope and ineffective in operation (rubber-stamping). | X10: Moderate | Y10: RISK-004 | Z10: FIND-004 | AA10: POAM-004 | AB10: POAM-004: In Progress | AD10: 46220 | AE10: 46326 | AF10: PR | AG10: This assessment's access review (106 rows, 9 systems) is the first complete privileged review. The Q3 campaign (EVID-074) is the first under the new design.
A11: AC-17 | B11: AC - Access Control | C11: Remote Access | D11: Moderate | E11: Establish usage restrictions, configuration requirements, and implementation guidance for each type of remote access, and authorize each type before allowing connections. | F11: Applicable | H11: Hybrid | I11: SYS-01, SYS-10 | J11: Tomasz Wierzbicki (Director, Platform Engineering) | K11: REQ-003 | L11: Implemented | M11: Implemented | N11: =IF(L11<>M11,"Yes","No") | O11: There is no network VPN into production. Administrative access uses AWS SSM Session Manager (sessions logged to log-archive) through IAM Identity Center, gated by Okta SSO+MFA from MDM-managed devices. No public bastions. wf-sftp-01 is administered through SSM only (except the RDP rule, reported under SC-7). | P11: Remote-access standard; SSM configuration; session logging; network exposure review | Q11: EVID-018; EVID-028 | R11: GRC-Vault:/WCP-2026/AC/EVID-018_ssm-session-prefs.json; GRC-Vault:/WCP-2026/CM/EVID-028_securityhub.csv | S11: Implementation | T11: Examine, Test | U11: Examined the SSM session preferences (logging to S3 and CloudWatch enabled, KMS-encrypted) and confirmed no security groups allow SSH from the internet except the documented SFTP allowlist. Expected: remote administration only through authenticated, logged channels. Actual: met. The RDP exposure on wf-sftp-01 is an unauthorized deviation, reported under SC-7 and CM-6, not a remote-access design flaw. | V11: Satisfied | AB11: n/a | AD11: 46220 | AE11: 46583 | AF11: PR
A12: AC-18 | B12: AC - Access Control | C12: Wireless Access | D12: Moderate | E12: Establish configuration and connection requirements for wireless access and authorize it before allowing connections. | F12: Not Applicable | G12: No wireless networking exists within the WCP-PROD boundary (AWS-hosted). Office Wi-Fi is outside the boundary and has no privileged path to production; production access from any network requires Okta SSO+MFA. Re-examine if the boundary changes. | H12: n/a | I12: n/a | J12: Tomasz Wierzbicki (Director, Platform Engineering) | K12: REQ-001 | L12: Not Applicable | M12: Not Applicable | N12: =IF(L12<>M12,"Yes","No") | O12: n/a (see applicability rationale) | P12: Boundary definition confirming no wireless components | Q12: EVID-040 | R12: docs/scope/system-profile.md | S12: Design | T12: Examine | U12: Examined the boundary diagram and the AWS network inventory. No wireless components are inside the boundary. N/A determination recorded in the scope statement. | V12: Not Assessed | AB12: n/a | AD12: 46220 | AE12: 46583 | AF12: PR
A13: AT-2 | B13: AT - Awareness and Training | C13: Literacy Training and Awareness | D13: Moderate | E13: Provide security and privacy literacy training to users at onboarding and at a defined frequency after that; include practical exercises (such as phishing simulations); update content after defined events. | F13: Applicable | H13: Common (organization-wide) | I13: All workforce | J13: Denise Yamamoto (Director of People) | K13: REQ-015 | L13: Implemented | M13: Partially Implemented | N13: =IF(L13<>M13,"Yes","No") | O13: Annual HIPAA and security awareness module in the LMS, plus quarterly phishing simulations. Policy requires completion within 30 days of assignment and suspends access after 30 days overdue, but the suspension is not enforced. | P13: LMS completion report for the full workforce; phishing simulation results; escalation records | Q13: EVID-019 | R13: GRC-Vault:/WCP-2026/AT/EVID-019_lms-completion-2026-06-30.csv | S13: Operating Effectiveness | T13: Examine, Test | U13: Compared the LMS roster (347) to the Okta active population. Expected: 100% completion (or documented exceptions). Actual: 316 of 347 (91%); 31 overdue, 4 of them with PHI data-store access. Phishing simulations ran 2 of 2 quarters (click rate 6.1% to 4.3%). Post-remediation: 344 of 347 (3 on leave) is under review (EVID-070). | V13: Other Than Satisfied | W13: Completion enforcement not operating. | X13: Low | Y13: RISK-015 | Z13: FIND-019 | AA13: POAM-019 | AB13: POAM-019: Completed – Pending Validation | AD13: 46220 | AE13: 46310 | AF13: GV
A14: AT-3 | B14: AT - Awareness and Training | C14: Role-based Training | D14: Moderate | E14: Provide role-based security and privacy training to personnel with assigned roles before authorizing access, and at a defined frequency after that. | F14: Applicable | H14: Common (organization-wide) | I14: Engineering, SRE, Clinical Ops, Security | J14: Denise Yamamoto (Director of People) | K14: REQ-015 | L14: Implemented | M14: Implemented | N14: =IF(L14<>M14,"Yes","No") | O14: Secure-coding training (annual) for engineers; privileged-user training for admins; HIPAA minimum-necessary training for clinical and support staff. Tracked in the LMS by role group. | P14: Role-based curricula and completion by role group | Q14: EVID-020 | R14: GRC-Vault:/WCP-2026/AT/EVID-020_role-training.csv | S14: Operating Effectiveness | T14: Examine, Test | U14: Sampled 15 role holders (5 engineers, 5 admins, 5 support/clinical). Expected: role training complete before access, or within 30 days of the role change. Actual: 15 of 15 complete. One admin completed 9 days after receiving admin access, within the 30-day grace in the training standard. | V14: Satisfied | AB14: n/a | AD14: 46220 | AE14: 46583 | AF14: GV
A15: AU-2 | B15: AU - Audit and Accountability | C15: Event Logging | D15: Moderate | E15: Identify the event types the system can log; coordinate logging with other entities; specify the event types to be logged; review and update the selection at a defined frequency. | F15: Applicable | H15: System-specific | I15: SYS-01, SYS-02, SYS-03, SYS-04 | J15: Owen Castillo (Security Engineer) | K15: REQ-019; REQ-005 | L15: Implemented | M15: Implemented | N15: =IF(L15<>M15,"Yes","No") | O15: Logging & Monitoring Standard LMS-004 defines required events. Sources include the AWS Organizations CloudTrail trail (management and S3 data events for PHI buckets), EKS audit logs, Aurora database activity logging for PHI tables, the application audit catalog (PHI view/export/print events with user, patient ID, and timestamp), and Okta and GitHub audit logs forwarded to the SIEM. | P15: Logging standard; trail configurations; sample events for each required type | Q15: EVID-021 | R15: GRC-Vault:/WCP-2026/AU/EVID-021_logging-config-and-samples.zip | S15: Implementation | T15: Examine, Test | U15: Traced 10 required event types (for example, PHI record view, bulk export, IAM policy change, Okta admin role grant) from action to SIEM. Expected: each event recorded with who, what, when, and where. Actual: 10 of 10 found with required fields. The event catalog was last reviewed 2026-02. | V15: Satisfied | AB15: n/a | AD15: 46220 | AE15: 46583 | AF15: DE
A16: AU-6 | B16: AU - Audit and Accountability | C16: Audit Record Review, Analysis, and Reporting | D16: Moderate | E16: Review and analyze audit records at a defined frequency for signs of inappropriate or unusual activity; report findings to defined personnel; adjust review when risk changes. | F16: Applicable | H16: System-specific | I16: SYS-01, SYS-02, SYS-08 | J16: Owen Castillo (Security Engineer) | K16: REQ-019; REQ-005 | L16: Implemented | M16: Partially Implemented | N16: =IF(L16<>M16,"Yes","No") | O16: MDR monitors alerts 24x7 (SI-4). Separately, LMS-004 §6 requires a weekly human review of privileged activity (AWS admin actions, Okta admin changes, GitHub owner actions), documented in a SEC ticket. One primary reviewer, no designated backup. | P16: Weekly review tickets for the whole period with dispositions | Q16: EVID-022; EVID-072 | R16: evidence/AU/EVID-022_privileged-activity-reviews-2026H1.csv; GRC-Vault:/WCP-2026/AU/EVID-072_reviews-W27-W37.csv | S16: Operating Effectiveness | T16: Examine, Test | U16: Tested all 26 weeks (test-results/au6-log-review.md). Expected: 26 of 26 performed within 5 days with every flag dispositioned. Actual: 19 performed and 17 fully effective (65%). 7 weeks were missed (migration, PTO) and 2 reviews were marked 'reviewed' with undispositioned flags. The review scope also excluded local IAM users. | V16: Other Than Satisfied | W16: Key detective review has a single point of failure and incomplete scope. | X16: Moderate | Y16: RISK-005 | Z16: FIND-009 | AA16: POAM-009 | AB16: POAM-009: In Progress | AD16: 46220 | AE16: 46326 | AF16: DE
A17: AU-9 | B17: AU - Audit and Accountability | C17: Protection of Audit Information | D17: Moderate | E17: Protect audit information and logging tools from unauthorized access, modification, and deletion; alert on detected unauthorized access, modification, or deletion. | F17: Applicable | H17: System-specific | I17: SYS-01 | J17: Owen Castillo (Security Engineer) | K17: REQ-019 | L17: Implemented | M17: Implemented | N17: =IF(L17<>M17,"Yes","No") | O17: CloudTrail and audit logs are delivered to a dedicated log-archive account. The S3 bucket uses Object Lock in compliance mode, a bucket policy denying deletes, and an SCP blocking StopLogging and DeleteTrail for all non-break-glass principals. The SIEM admin role is limited to 1 person, plus MDR read access. | P17: Log bucket configuration; SCPs; access list for the log account | Q17: EVID-023 | R17: GRC-Vault:/WCP-2026/AU/EVID-023_log-archive-protections.json | S17: Implementation | T17: Examine, Test | U17: Examined Object Lock and the SCPs. Using the assessor's read-only role, confirmed an attempt to call cloudtrail:StopLogging returns AccessDenied (explicit SCP deny). Expected: logs are immutable to operational admins. Actual: met. | V17: Satisfied | AB17: n/a | AD17: 46220 | AE17: 46583 | AF17: DE
A18: AU-11 | B18: AU - Audit and Accountability | C18: Audit Record Retention | D18: Moderate | E18: Retain audit records for a defined period consistent with records-retention policy to support after-the-fact investigations and meet regulatory and organizational retention requirements. | F18: Applicable | H18: System-specific | I18: SYS-01, SYS-08 | J18: Owen Castillo (Security Engineer) | K18: REQ-005; REQ-019 | L18: Implemented | M18: Partially Implemented | N18: =IF(L18<>M18,"Yes","No") | O18: At assessment: SIEM hot retention 90 days; the log-archive S3 lifecycle expired CloudTrail at 180 days; CloudWatch application-audit (PHI access) logs were kept 90 days with no archive. The CSA requires 12 months (90 days searchable). | P18: Retention settings for every audit source, and confirmation that the oldest available records match the setting | Q18: EVID-024; EVID-067 | R18: evidence/AU/EVID-024_log-retention-config_2026-06-30.json; evidence/AU/EVID-067_log-retention-config_2026-09-12.json | S18: Implementation | T18: Examine, Test | U18: Examined the retention configuration for 5 sources and queried the oldest available record in each. Expected: 12 months or more for all. Actual: CloudTrail 180 days, app audit 90 days, SIEM 90 days (the oldest records matched the settings, so there was no hidden longer retention). Validation (2026-09-12): lifecycle changed to a 400-day expiry, app audit is archived to log-archive, and objects dated 2026-03-20 (182 days old) are still present, confirming the old rule no longer applies. | V18: Other Than Satisfied | W18: Retention below the contractual 12 months. | X18: Moderate | Y18: RISK-005 | Z18: FIND-008 | AA18: POAM-008 | AB18: POAM-008: Closed | AD18: 46277 | AE18: 46583 | AF18: DE | AG18: Closure rests on configuration plus an early indicator. Full 12-month retention can only be demonstrated over time, so the FY27 assessment re-tests the oldest record date.
A19: CA-2 | B19: CA - Assessment, Authorization, and Monitoring | C19: Control Assessments | D19: Moderate | E19: Select an appropriate assessor or team; develop an assessment plan; assess controls at a defined frequency; produce an assessment report; provide results to defined individuals or roles. | F19: Applicable | H19: Common (organization-wide) | I19: WCP-PROD | J19: Priya Raman (Security Compliance Manager) | K19: REQ-002; REQ-012 | L19: Implemented | M19: Implemented | N19: =IF(L19<>M19,"Yes","No") | O19: Annual SOC 2 Type II examination by an independent CPA firm, an annual external penetration test (Lanternworks Security, fictional), and this SP 800-53 assessment (SAP ASMT-SAP-001). Results are reported to the CISO, CTO, and Audit & Risk Committee. | P19: Assessment plan; prior assessment reports; distribution evidence | Q19: EVID-025 | R19: GRC-Vault:/WCP-2026/CA/EVID-025_soc2-and-pentest.pdf | S19: Operating Effectiveness | T19: Examine, Interview | U19: Examined the SOC 2 report (unqualified; 1 exception noted in change management), the 2025 pentest summary (2 High findings, retest closed), and this engagement's SAP. Expected: independent assessments at a defined frequency with results reported. Actual: met. Note: SOC 2 does not test 800-53-specific requirements, which is why this engagement exists. | V19: Satisfied | AB19: n/a | AD19: 46220 | AE19: 46583 | AF19: GV
A20: CA-3 | B20: CA - Assessment, Authorization, and Monitoring | C20: Information Exchange | D20: Moderate | E20: Approve and manage information exchanges using defined agreement types; document interface characteristics, security and privacy requirements, controls, and responsibilities in the agreements; review and update them at a defined frequency. | F20: Applicable | H20: System-specific | I20: SYS-01, SYS-05 | J20: Liam Porter (Data Engineering Manager) | K20: REQ-018; REQ-021 | L20: Implemented | M20: Implemented | N20: =IF(L20<>M20,"Yes","No") | O20: Each interconnection has an agreement (BAA plus interface or data-sharing specification). The Quarrystone Data Sharing Specification v2 documents the fields, transfer method, schedule, encryption, and contacts. Customer EHR interfaces use per-customer interface specs. | P20: Interconnection inventory and agreement for each exchange | Q20: EVID-026 | R20: GRC-Vault:/WCP-2026/CA/EVID-026_interconnection-agreements.zip | S20: Design | T20: Examine | U20: Examined agreements for Quarrystone and 3 sampled customer EHR interfaces. Expected: signed agreement with security requirements and responsibilities for each exchange. Actual: all 4 present and signed. The Quarrystone spec's contents (excess fields, no US-only clause) are covered as vendor-risk issues under SA-9 (FIND-016), not as a missing agreement. | V20: Satisfied | AB20: n/a | AD20: 46220 | AE20: 46583 | AF20: GV | AG20: The determination separates having an exchange agreement (CA-3, met) from the adequacy of the vendor's terms (SA-9, not met).
A21: CA-5 | B21: CA - Assessment, Authorization, and Monitoring | C21: Plan of Action and Milestones | D21: Moderate | E21: Develop a plan of action and milestones documenting planned remediation of weaknesses found during control assessments; update it at a defined frequency based on assessment and monitoring results. | F21: Applicable | H21: Common (organization-wide) | I21: WCP-PROD | J21: Priya Raman (Security Compliance Manager) | K21: REQ-002 | L21: Implemented | M21: Implemented | N21: =IF(L21<>M21,"Yes","No") | O21: Before 2026-08, weaknesses were tracked in a Jira "SECISSUE" project with owners and due dates (SOC 2 remediation). Since 2026-08-07, the formal POA&M (poam/poam.xlsx) has been baselined, has milestones and SLAs, is reviewed biweekly, and is reported monthly to the CISO. | P21: POA&M; update history; evidence that items come from assessments and monitoring | Q21: EVID-027 | R21: GRC-Vault:/WCP-2026/CA/EVID-027_secissue-export.csv | S21: Implementation | T21: Examine | U21: Examined the prior Jira tracking (37 items, 100% with owner and due date; 4 overdue) and the new POA&M. Expected: all assessment weaknesses tracked with milestones. Actual: met. All 19 findings are in the POA&M, including the risk-accepted item. | V21: Satisfied | AB21: n/a | AD21: 46220 | AE21: 46583 | AF21: GV
A22: CA-7 | B22: CA - Assessment, Authorization, and Monitoring | C22: Continuous Monitoring | D22: Moderate | E22: Develop a system-level continuous monitoring strategy and implement monitoring with defined metrics, frequencies, ongoing assessments, correlation and analysis, response actions, and status reporting. | F22: Applicable | H22: Common (organization-wide) | I22: WCP-PROD | J22: Alicia Moreno (CISO) | K22: REQ-002; REQ-012 | L22: Implemented | M22: Implemented | N22: =IF(L22<>M22,"Yes","No") | O22: Operational monitoring is in place (Security Hub CIS checks, weekly vulnerability scans, GuardDuty and MDR, a monthly security metrics deck to the CTO). There is no formal written ISCM strategy document, and metrics were not tied to control objectives until the dashboard built in this engagement. | P22: ISCM strategy; monitoring outputs; reporting to management | Q22: EVID-028; EVID-058 | R22: GRC-Vault:/WCP-2026/CM/EVID-028_securityhub.csv; GRC-Vault:/WCP-2026/SI/EVID-058_monitoring.zip | S22: Operating Effectiveness | T22: Examine, Interview | U22: Examined 6 monthly metric decks and the Security Hub history. Expected: defined metrics reported at a defined frequency with response actions. Actual: monitoring and reporting operate. The CSPM alert on wf-sftp-01 went untriaged for 43 days, and that failure is recorded under SC-7/FIND-012. The strategy document gap is recorded as OBS-05. | V22: Satisfied | W22: No written ISCM strategy (observation). | X22: Low | Y22: RISK-016 | AB22: n/a | AC22: OBS-05 | AD22: 46220 | AE22: 46583 | AF22: GV
A23: CM-2 | B23: CM - Configuration Management | C23: Baseline Configuration | D23: Moderate | E23: Develop, document, and maintain a current baseline configuration under configuration control; review and update it at a defined frequency and when components are installed or upgraded. | F23: Applicable | H23: System-specific | I23: SYS-01 | J23: Tomasz Wierzbicki (Director, Platform Engineering) | K23: REQ-001; REQ-023 | L23: Implemented | M23: Implemented | N23: =IF(L23<>M23,"Yes","No") | O23: Infrastructure is defined in Terraform (baseline repo, PR-reviewed). EKS nodes use a hardened AMI (CIS Level 1) rebuilt monthly. Container base images are pinned and rebuilt weekly. The legacy hosts (wf-sftp-01, legacy-reports) have no managed baseline, which is recorded under SA-22. | P23: IaC baseline; AMI build specification; drift reports | Q23: EVID-029 | R23: GRC-Vault:/WCP-2026/CM/EVID-029_baseline.zip | S23: Implementation | T23: Examine, Test | U23: Examined the Terraform baseline and the AMI pipeline. Ran a drift check on 3 sampled modules (VPC, EKS, RDS). Expected: live config matches IaC. Actual: no drift in the sampled modules. The legacy hosts are outside IaC and are covered under SA-22. | V23: Satisfied | AB23: n/a | AD23: 46220 | AE23: 46583 | AF23: PR
A24: CM-3 | B24: CM - Configuration Management | C24: Configuration Change Control | D24: Moderate | E24: Determine and document types of changes that are configuration-controlled; review, approve or disapprove, document, and implement changes; retain records; monitor and review activities. | F24: Applicable | H24: System-specific | I24: SYS-01, SYS-03, SYS-05 | J24: Tomasz Wierzbicki (Director, Platform Engineering) | K24: REQ-023 | L24: Implemented | M24: Partially Implemented | N24: =IF(L24<>M24,"Yes","No") | O24: Code and IaC changes go through GitHub PRs with required reviews and CI, then deploy through a protected environment with approvers. The change management procedure CMP-006 requires emergency changes to be retro-approved within 2 business days. Console changes have no preventive gate. | P24: Change population for the period; sample tickets with approvals, reviews, tests, and deployment timestamps | Q24: EVID-030 | R24: evidence/CM/EVID-030_change-sample-2026H1.csv | S24: Operating Effectiveness | T24: Examine, Test | U24: Random sample of 25 of 212 changes (test-results/cm3-change-sample.md). Expected: 25 of 25 approved before deployment, or retro-approved within 2 business days for emergencies. Actual: 3 exceptions. CHG-2026-0412 (emergency RDP change, never approved or reverted), CHG-2026-0288 (retro approval after 9 days), and CHG-2026-0356 (deployed 5h38m before approval). | V24: Other Than Satisfied | W24: The emergency and console change paths bypass approval. | X24: Moderate | Y24: RISK-014 | Z24: FIND-018 | AA24: POAM-018 | AB24: POAM-018: In Progress | AD24: 46220 | AE24: 46387 | AF24: PR
A25: CM-6 | B25: CM - Configuration Management | C25: Configuration Settings | D25: Moderate | E25: Establish and document configuration settings using common secure configurations; implement them; identify, document, and approve deviations; monitor and control changes to settings. | F25: Applicable | H25: System-specific | I25: SYS-01, SYS-05 | J25: Tomasz Wierzbicki (Director, Platform Engineering) | K25: REQ-001 | L25: Implemented | M25: Partially Implemented | N25: =IF(L25<>M25,"Yes","No") | O25: AWS Security Hub runs the CIS AWS Foundations benchmark across accounts (97% of controls passing at 2026-06-30). Deviations are supposed to be triaged within 7 days (High) by SRE. The SRE on-call runbook did not include Security Hub findings, so triage depended on ad-hoc review. | P25: Secure configuration baseline; CSPM results and history; deviation approvals | Q25: EVID-028; EVID-053; EVID-068 | R25: GRC-Vault:/WCP-2026/CM/EVID-028_securityhub.csv; evidence/CM/EVID-053_wf-sftp-01-security-group_2026-07-02.json; GRC-Vault:/WCP-2026/SC/EVID-068_sg-fix.zip | S25: Operating Effectiveness | T25: Examine, Test | U25: Examined the Security Hub finding history. Expected: High deviations triaged within 7 days, or approved as exceptions. Actual: 3 High findings were open more than 30 days without triage, including 'Security group allows ingress from 0.0.0.0/0 to port 3389' on wf-sftp-01 (open 43 days). Remediated 2026-07-03; the security group and Security Hub re-evaluation were validated 2026-07-10 (EVID-068). | V25: Other Than Satisfied | W25: Deviation detection works; deviation response did not. | X25: High | Y25: RISK-012; RISK-007 | Z25: FIND-012 | AA25: POAM-012 | AB25: POAM-012: Closed | AD25: 46213 | AE25: 46583 | AF25: PR
A26: CM-8 | B26: CM - Configuration Management | C26: System Component Inventory | D26: Moderate | E26: Develop and document an accurate inventory of system components at the granularity needed for tracking and reporting; review and update it at a defined frequency. | F26: Applicable | H26: System-specific | I26: SYS-01, SYS-10 | J26: Tomasz Wierzbicki (Director, Platform Engineering) | K26: REQ-001 | L26: Implemented | M26: Implemented | N26: =IF(L26<>M26,"Yes","No") | O26: AWS Config aggregator (all accounts) plus the MDM inventory for endpoints. A tag policy requires owner, environment, and data-classification tags. | P26: Inventory exports; tag compliance; reconciliation to billing and resource counts | Q26: EVID-031 | R26: GRC-Vault:/WCP-2026/CM/EVID-031_inventory.zip | S26: Implementation | T26: Examine, Test | U26: Reconciled the AWS Config resource counts to Cost Explorer resource IDs for EC2, EKS, and RDS (100% present in inventory). Expected: complete inventory with ownership. Actual: inventory complete, but 7% of EC2/EKS resources lack an owner tag, which reduces scanner scoping accuracy (OBS-02). | V26: Satisfied | W26: Owner-tag compliance at 93% (observation). | X26: Low | Y26: RISK-006 | AB26: n/a | AC26: OBS-02 | AD26: 46220 | AE26: 46583 | AF26: ID
A27: CP-2 | B27: CP - Contingency Planning | C27: Contingency Plan | D27: Moderate | E27: Develop a contingency plan that identifies essential functions, recovery objectives, restoration priorities, roles, and contacts; distribute, review, update, and protect it. | F27: Applicable | H27: System-specific | I27: SYS-01 | J27: Tomasz Wierzbicki (Director, Platform Engineering) | K27: REQ-011; REQ-017 | L27: Implemented | M27: Implemented | N27: =IF(L27<>M27,"Yes","No") | O27: BC/DR Plan BCP-003 v2.1 (2025-11). RTO 4h and RPO 1h for WCP-PROD. Restoration priorities are the auth, care-plan, and RPM ingestion services. Covers clinical downtime procedures coordinated with customers. | P27: Approved current plan with defined RTO/RPO, roles, and distribution | Q27: EVID-032 | R27: GRC-Vault:/WCP-2026/CP/EVID-032_BCP-003_v2.1.pdf | S27: Design | T27: Examine, Interview | U27: Examined BCP-003 v2.1 against CP-2 elements. Expected: current, approved, with objectives and roles. Actual: met. The plan is sound on paper; whether it works is tested under CP-4 and CP-9(1). | V27: Satisfied | AB27: n/a | AD27: 46220 | AE27: 46583 | AF27: RC
A28: CP-4 | B28: CP - Contingency Planning | C28: Contingency Plan Testing | D28: Moderate | E28: Test the contingency plan at a defined frequency using defined tests to determine effectiveness and readiness; review results and initiate corrective actions. | F28: Applicable | H28: System-specific | I28: SYS-01 | J28: Tomasz Wierzbicki (Director, Platform Engineering) | K28: REQ-011; REQ-017 | L28: Implemented | M28: Not Implemented | N28: =IF(L28<>M28,"Yes","No") | O28: The owner cited a 2024 AZ-failover exercise. BCP-003 requires an annual test (tabletop or functional). No plan-level test was performed in the 12 months before fieldwork. | P28: Test plan, test records, after-action report, and corrective actions within the last 12 months | Q28: EVID-033 | R28: GRC-Vault:/WCP-2026/CP/EVID-033_az-failover-notes-2024.md | S28: Design | T28: Examine, Interview | U28: Requested all CP test records for the past 24 months. Expected: at least 1 plan-level test in the last 12 months. Actual: only 2024-04 engineering notes on an AZ failover (not a plan-level test, with no after-action report). Evidence was marked Insufficient. A combined ransomware tabletop (IR + CP) is scheduled for 2026-10-14. | V28: Other Than Satisfied | W28: Contingency plan not tested. | X28: Moderate | Y28: RISK-008 | Z28: FIND-014 | AA28: POAM-014 | AB28: POAM-014: In Progress | AD28: 46220 | AE28: 46326 | AF28: RC
A29: CP-9 | B29: CP - Contingency Planning | C29: System Backup | D29: Moderate | E29: Conduct backups of user-level, system-level, and security-related information at a defined frequency consistent with recovery objectives; protect the confidentiality, integrity, and availability of backups. | F29: Applicable | H29: System-specific | I29: SYS-01, SYS-04 | J29: Tomasz Wierzbicki (Director, Platform Engineering) | K29: REQ-011; REQ-017 | L29: Implemented | M29: Implemented | N29: =IF(L29<>M29,"Yes","No") | O29: Aurora continuous backup (PITR, 35 days), plus daily AWS Backup copies to the wcp-dr account in us-west-2 in a vault with Vault Lock (compliance mode) and KMS encryption. S3 versioning plus cross-region replication for documents. | P29: Backup plans; job history; vault protection settings; cross-region copies | Q29: EVID-034 | R29: GRC-Vault:/WCP-2026/CP/EVID-034_backup-config.zip | S29: Operating Effectiveness | T29: Examine, Test | U29: Examined the backup plans and 30 days of job history (30 of 30 successful), and confirmed Vault Lock plus cross-account copy. Expected: backups taken per RPO and protected from deletion. Actual: met. Whether backups can actually be restored is tested separately under CP-9(1). | V29: Satisfied | AB29: n/a | AD29: 46220 | AE29: 46583 | AF29: PR
A30: CP-9(1) | B30: CP - Contingency Planning | C30: Testing for Reliability and Integrity | D30: Moderate | E30: Test backup information at a defined frequency to verify media reliability and information integrity. | F30: Applicable | H30: System-specific | I30: SYS-04 | J30: Tomasz Wierzbicki (Director, Platform Engineering) | K30: REQ-011; REQ-017 | L30: Implemented | M30: Partially Implemented | N30: =IF(L30<>M30,"Yes","No") | O30: The owner treated backup-job success notifications as testing. No restore of wcp-core-db from the DR vault had been performed or documented. | P30: Restore test records showing restore steps, time taken, data-integrity checks, and results against RTO/RPO | Q30: EVID-035; EVID-069 | R30: GRC-Vault:/WCP-2026/CP/EVID-035_backup-job-notifications.pdf; evidence/CP/EVID-069_restore-test-record_2026-08-27.md | S30: Operating Effectiveness | T30: Examine, Test | U30: Expected: an annual documented restore test with integrity validation. Actual: none; job-success logs only (EVID-035, Insufficient). Validation: the assessor observed a restore test on 2026-08-27 (EVID-069). wcp-core-db was restored from the wcp-dr vault into an isolated account in 3h41m (RTO 4h). Data loss was 11 minutes (RPO 1h). Row-count and checksum validation passed on 12 tables. | V30: Other Than Satisfied | W30: Backup recoverability had never been demonstrated. | X30: Moderate | Y30: RISK-008 | Z30: FIND-013 | AA30: POAM-013 | AB30: POAM-013: Closed | AD30: 46266 | AE30: 46583 | AF30: RC
A31: IA-2 | B31: IA - Identification and Authentication | C31: Identification and Authentication (Organizational Users) | D31: Moderate | E31: Uniquely identify and authenticate organizational users and associate that identification with processes acting on their behalf. | F31: Applicable | H31: Common (Okta) | I31: SYS-02, and all SSO-integrated systems | J31: Nadia Rahman (IAM Engineer) | K31: REQ-020 | L31: Implemented | M31: Implemented | N31: =IF(L31<>M31,"Yes","No") | O31: Every workforce user has a unique Okta identity tied to an HR worker ID. Shared human accounts are prohibited (ACP-002 §4.2). The one shared vendor login found (ironpeak-soc) is reported under AC-2 and IA-5 as FIND-005. | P31: User population with unique identifiers mapped to HR | Q31: EVID-005 | R31: access-review/source-exports/okta_users.csv | S31: Implementation | T31: Examine, Test | U31: Mapped the Okta population to HR worker IDs. Expected: unique identity per person. Actual: met for workforce identities (the duplicate rgupta2 is one person with two accounts, handled under AC-2 and FIND-004). The shared EDR vendor login is handled under FIND-005. | V31: Satisfied | AB31: n/a | AD31: 46220 | AE31: 46583 | AF31: PR
A32: IA-2(1) | B32: IA - Identification and Authentication | C32: Multi-factor Authentication to Privileged Accounts | D32: Moderate | E32: Implement multi-factor authentication for access to privileged accounts. | F32: Applicable | H32: Hybrid (Okta + AWS IAM) | I32: SYS-01, SYS-02 | J32: Nadia Rahman (IAM Engineer) | K32: REQ-003; REQ-020 | L32: Implemented | M32: Partially Implemented | N32: =IF(L32<>M32,"Yes","No") | O32: The Okta global session policy requires MFA except for members of MFA-Exempt-Legacy (a 2023 policy). AWS Identity Center access inherits Okta MFA. Legacy IAM users authenticate directly to AWS. | P32: Authentication policies; exemption groups; privileged-user MFA status; AWS credential report | Q32: EVID-007; EVID-010; EVID-011; EVID-063; EVID-064 | R32: evidence/IA/EVID-007_aws-iam-credential-report_2026-06-30.csv; evidence/IA/EVID-010_okta-authentication-policies_2026-06-30.json; evidence/IA/EVID-011_okta-mfa-exempt-group_2026-06-30.csv; evidence/IA/EVID-063_okta-authentication-policies_2026-09-04.json; evidence/IA/EVID-064_aws-iam-credential-report_2026-09-04.csv | S32: Implementation | T32: Examine, Test | U32: Expected: 100% of privileged access requires MFA. Actual: 1 Okta Super Administrator (kbrandt) was in the exemption group, and the IAM user mfeld-admin (AdministratorAccess) had a console password without MFA. Validation (2026-09-04): the exemption policy and group were deleted, admin apps require phishing-resistant factors, and only aws-breakglass (hardware MFA) remains as an IAM user. A password-only sign-in was re-performed and denied. | V32: Other Than Satisfied | W32: MFA was bypassable for some privileged access. | X32: High | Y32: RISK-003; RISK-001 | Z32: FIND-002 | AA32: POAM-002 | AB32: POAM-002: Closed | AD32: 46270 | AE32: 46583 | AF32: PR
A33: IA-2(2) | B33: IA - Identification and Authentication | C33: Multi-factor Authentication to Non-privileged Accounts | D33: Moderate | E33: Implement multi-factor authentication for access to non-privileged accounts. | F33: Applicable | H33: Common (Okta) | I33: SYS-02 | J33: Nadia Rahman (IAM Engineer) | K33: REQ-003; REQ-020 | L33: Implemented | M33: Partially Implemented | N33: =IF(L33<>M33,"Yes","No") | O33: As for IA-2(1). The exemption group held 11 accounts (9 human, 2 service), added 2023–2025 for lost phones, SMS problems, shared clinic workstations, and a scanner. | P33: Authentication policy; exemption group membership with reasons and approvals | Q33: EVID-010; EVID-011; EVID-063 | R33: evidence/IA/EVID-010_okta-authentication-policies_2026-06-30.json; evidence/IA/EVID-011_okta-mfa-exempt-group_2026-06-30.csv; evidence/IA/EVID-063_okta-authentication-policies_2026-09-04.json | S33: Implementation | T33: Examine, Test | U33: Expected: 100% MFA, or time-bound approved exceptions. Actual: 9 of 347 human accounts (2.6%) exempt, and 0 of 11 exemptions had approval or expiry (the oldest dated 2023-05). Validation: all 9 enrolled (1 with a hardware key as an accessibility accommodation), both service accounts converted to non-interactive integrations, and the group deleted. | V33: Other Than Satisfied | W33: Permanent, unapproved MFA exemptions. | X33: High | Y33: RISK-003 | Z33: FIND-002 | AA33: POAM-002 | AB33: POAM-002: Closed | AD33: 46270 | AE33: 46583 | AF33: PR
A34: IA-2(8) | B34: IA - Identification and Authentication | C34: Access to Accounts — Replay Resistant | D34: Moderate | E34: Implement replay-resistant authentication mechanisms for access to privileged and non-privileged accounts. | F34: Applicable | H34: Common (Okta) | I34: SYS-02 | J34: Nadia Rahman (IAM Engineer) | K34: REQ-020 | L34: Implemented | M34: Implemented | N34: =IF(L34<>M34,"Yes","No") | O34: All enabled authenticators are replay-resistant (Okta Verify push with number challenge, FastPass, FIDO2/WebAuthn, TOTP). SMS, voice, email, and security questions have been disabled org-wide since 2025. | P34: Authenticator configuration | Q34: EVID-012; EVID-010 | R34: GRC-Vault:/WCP-2026/IA/EVID-012_okta-authenticators.json; evidence/IA/EVID-010_okta-authentication-policies_2026-06-30.json | S34: Implementation | T34: Examine | U34: Examined the enabled authenticators. Expected: only replay-resistant factors for users who authenticate with MFA. Actual: met. The exempt users under IA-2(1)/(2) did not use weak factors; they used no second factor at all. | V34: Satisfied | AB34: n/a | AD34: 46220 | AE34: 46583 | AF34: PR
A35: IA-5 | B35: IA - Identification and Authentication | C35: Authenticator Management | D35: Moderate | E35: Manage authenticators by verifying identity before distribution, establishing initial content, ensuring strength, managing lost or compromised authenticators, changing or refreshing them at defined frequencies, and protecting their content. | F35: Applicable | H35: Hybrid | I35: SYS-01, SYS-02, SYS-05, SYS-08 | J35: Nadia Rahman (IAM Engineer) | K35: REQ-020 | L35: Implemented | M35: Partially Implemented | N35: =IF(L35<>M35,"Yes","No") | O35: Human authenticators are strong (Okta password policy plus MFA; help-desk identity verification SOP). For service credentials, the standard requires rotation within 365 days or federation. Secrets Manager auto-rotates DB credentials, and CI/CD uses OIDC with no static keys. Some legacy service credentials are outside this. | P35: Password and authenticator policies; service credential inventory with rotation dates; help-desk verification records | Q35: EVID-007; EVID-013; EVID-064; EVID-065 | R35: evidence/IA/EVID-007_aws-iam-credential-report_2026-06-30.csv; access-review/source-exports/service_accounts.csv; evidence/IA/EVID-064_aws-iam-credential-report_2026-09-04.csv; GRC-Vault:/WCP-2026/IA/EVID-065_service-register-v2026-09.csv | S35: Operating Effectiveness | T35: Examine, Test | U35: Tested credential age for all 13 registered non-human accounts. Expected: none older than 365 days unless federated. Actual: 3 stale (svc-quarrystone-sftp SSH key 811 days; svc-reporting-etl access key 539 days; svc-vulnscan password since 2023), and 1 shared vendor password (ironpeak-soc). Sampled 5 help-desk MFA resets: 5 of 5 had identity verification recorded. | V35: Other Than Satisfied | W35: Long-lived static service credentials, and a shared credential. | X35: Moderate | Y35: RISK-017 | Z35: FIND-005 | AA35: POAM-005 | AB35: POAM-005: Closed | AD35: 46277 | AE35: 46583 | AF35: PR
A36: IR-3 | B36: IR - Incident Response | C36: Incident Response Testing | D36: Moderate | E36: Test the effectiveness of the incident response capability at a defined frequency using defined tests. | F36: Applicable | H36: Common (organization-wide) | I36: WCP-PROD | J36: Owen Castillo (Security Engineer) | K36: REQ-006; REQ-016 | L36: Implemented | M36: Partially Implemented | N36: =IF(L36<>M36,"Yes","No") | O36: IRP-005 requires an annual tabletop exercise that includes the MDR, Legal/Privacy, and Customer Ops. The last tabletop was 2024-09-18 (phishing-to-BEC scenario). The 2025 exercise was deferred twice. | P36: Exercise plan, attendance, after-action report, and corrective actions within 12 months | Q36: EVID-037 | R36: GRC-Vault:/WCP-2026/IR/EVID-037_tabletop-2024-09.pdf | S36: Design | T36: Examine, Interview | U36: Expected: an IR exercise within the last 12 months with tracked corrective actions. Actual: the most recent was 21 months before fieldwork (EVID-037, Insufficient for the period). The 24-hour SHCA reporting path has never been exercised. Mitigating factor: real incidents in H1 were handled well (IR-4), which lowers but does not remove the risk. | V36: Other Than Satisfied | W36: IR capability not tested in the required period; SHCA-specific reporting path not rehearsed. | X36: Moderate | Y36: RISK-009 | Z36: FIND-014 | AA36: POAM-014 | AB36: POAM-014: In Progress | AD36: 46220 | AE36: 46326 | AF36: RS
A37: IR-4 | B37: IR - Incident Response | C37: Incident Handling | D37: Moderate | E37: Implement an incident-handling capability covering preparation, detection and analysis, containment, eradication, and recovery; coordinate with contingency planning; incorporate lessons learned. | F37: Applicable | H37: Common (organization-wide) | I37: WCP-PROD | J37: Owen Castillo (Security Engineer) | K37: REQ-016 | L37: Implemented | M37: Implemented | N37: =IF(L37<>M37,"Yes","No") | O37: 24x7 MDR triage with escalation to the on-call security engineer. IRP-005 playbooks for phishing, lost device, cloud credential misuse, privacy incidents, and malware. The Privacy Officer runs the HIPAA breach risk assessment. | P37: Incident records for the period with timeline, actions, and lessons learned | Q37: EVID-038; EVID-078 | R37: evidence/IR/EVID-038_incident-tickets-2026H1.csv; evidence/IR/EVID-078_INC-2026-0117-investigation.md | S37: Operating Effectiveness | T37: Examine, Test | U37: Tested all 6 incidents in H1 plus INC-2026-0117 (raised during the assessment). Expected: triage within SLA, containment, documentation, and a privacy assessment where PHI was involved. Actual: 7 of 7 met. INC-2026-0117 (a post-termination sign-in) was contained the same day, and a 4-factor assessment concluded low probability of compromise. | V37: Satisfied | AB37: n/a | AD37: 46220 | AE37: 46583 | AF37: RS
A38: IR-6 | B38: IR - Incident Response | C38: Incident Reporting | D38: Moderate | E38: Require personnel to report suspected incidents within a defined time; report incident information to defined authorities. | F38: Applicable | H38: Common (organization-wide) | I38: WCP-PROD | J38: Rachel Stein (HIPAA Privacy Officer) | K38: REQ-006; REQ-016; REQ-022 | L38: Implemented | M38: Implemented | N38: =IF(L38<>M38,"Yes","No") | O38: Workforce reporting through the #security-report Slack channel, the phone line, or MDR. External notification matrix covers customers (BAA, 5 business days), HHS (via covered entities), and SHCA (24h, from go-live). | P38: Reporting procedures; notification records for reportable incidents | Q38: EVID-038 | R38: evidence/IR/EVID-038_incident-tickets-2026H1.csv | S38: Operating Effectiveness | T38: Examine, Test | U38: Expected: every incident requiring notification is notified within its contractual window. Actual: 1 notifiable privacy incident (INC-2026-0077), with the customer notified in 2 business days (the BAA allows 5). The SHCA 24h path is documented but untested (see IR-3). | V38: Satisfied | AB38: n/a | AD38: 46220 | AE38: 46583 | AF38: RS
A39: IR-8 | B39: IR - Incident Response | C39: Incident Response Plan | D39: Moderate | E39: Develop an incident response plan that provides a roadmap, structure, metrics, and roles; distribute, review, and update it; protect it from unauthorized disclosure. | F39: Applicable | H39: Common (organization-wide) | I39: WCP-PROD | J39: Owen Castillo (Security Engineer) | K39: REQ-006; REQ-016 | L39: Implemented | M39: Implemented | N39: =IF(L39<>M39,"Yes","No") | O39: IRP-005 v4.0 was reviewed 2025-11 and approved by the CISO. It defines severity levels, roles, the MDR interface, communications, and breach assessment. The contact roster lists 2 departed staff (mfeld, a former Privacy Analyst). | P39: Current approved plan; review history; distribution | Q39: EVID-036 | R39: GRC-Vault:/WCP-2026/IR/EVID-036_IRP-005_v4.0.pdf | S39: Design | T39: Examine | U39: Expected: a plan reviewed within 12 months with current contacts. Actual: reviewed 2025-11 (current), but the contact roster is stale (OBS-03), which the tabletop in POAM-014 will fix. The plan does not yet include the SHCA-specific 24h notification step; that is added in POAM-014 milestone 1. | V39: Satisfied | W39: Stale contact roster (observation). | X39: Low | Y39: RISK-009 | AB39: n/a | AC39: OBS-03 | AD39: 46220 | AE39: 46583 | AF39: RS
A40: MP-6 | B40: MP - Media Protection | C40: Media Sanitization | D40: Moderate | E40: Sanitize system media before disposal, release, or reuse using defined techniques; use mechanisms with strength and integrity matching the information's classification. | F40: Applicable | H40: Hybrid (AWS-managed storage media inherited; endpoints Wrenfield) | I40: SYS-10 (endpoints); AWS storage inherited | J40: Kevin Brandt (IT Manager) | K40: REQ-021 | L40: Implemented | M40: Implemented | N40: =IF(L40<>M40,"Yes","No") | O40: Laptops are FDE-encrypted. At retirement, the MDM wipe is followed by physical destruction by Coldwater Secure Destruction (fictional ITAD), with certificates of destruction by serial number. Cloud storage media sanitization is inherited from AWS under the shared-responsibility model. | P40: Disposal records reconciled to the asset inventory; certificates of destruction | Q40: EVID-039; EVID-040 | R40: GRC-Vault:/WCP-2026/MP/EVID-039_itad-certificates.pdf; docs/scope/system-profile.md | S40: Operating Effectiveness | T40: Examine, Test | U40: Reconciled 14 laptops retired in H1 (MDM status: Retired) to Coldwater certificates by serial number. Expected: 14 of 14 certificates. Actual: 14 of 14. | V40: Satisfied | Y40: RISK-018 | AB40: n/a | AD40: 46220 | AE40: 46583 | AF40: PR
A41: PE-3 | B41: PE - Physical and Environmental Protection | C41: Physical Access Control | D41: Moderate | E41: Enforce physical access authorizations at entry and exit points to facilities where the system resides; maintain audit logs; control visitor access; secure keys and combinations. | F41: Applicable | H41: Common (inherited from AWS) | I41: AWS data centers (inherited) | J41: Priya Raman (Security Compliance Manager), who verifies the inheritance | K41: REQ-001 | L41: Implemented | M41: Implemented | N41: =IF(L41<>M41,"Yes","No") | O41: Inherited. WCP-PROD runs entirely in AWS data centers, and physical security is the provider's responsibility under the shared-responsibility model. Wrenfield's responsibility is to keep the inheritance record current and review the provider's attestations annually. The HQ office holds no system components. | P41: Inheritance record; evidence of annual review of the provider's attestation documentation | Q41: EVID-040 | R41: docs/scope/system-profile.md | S41: Design | T41: Examine | U41: Examined the inheritance record and confirmed the provider attestation review was logged in 2026-03 by the GRC Manager. Expected: current inheritance record and annual review. Actual: met. The provider's own controls were not tested (out of scope). No statement is made about any real provider's controls. | V41: Satisfied | AB41: n/a | AD41: 46220 | AE41: 46583 | AF41: PR
A42: PL-2 | B42: PL - Planning | C42: System Security and Privacy Plans | D42: Moderate | E42: Develop security and privacy plans that describe the system, boundary, categorization, threats, controls, and relationships; distribute, review, update, and protect them. | F42: Applicable | H42: System-specific | I42: WCP-PROD | J42: Priya Raman (Security Compliance Manager) | K42: REQ-001; REQ-002 | L42: Implemented | M42: Partially Implemented | N42: =IF(L42<>M42,"Yes","No") | O42: SSP v1.3 dated 2025-02. It predates the EKS migration (2025-Q3), the Quarrystone SFTP data flow, and the log-archive account, and states a higher implementation status than testing supports for 27 of the 61 in-scope controls (the 'owner-stated' column in the matrix). It was written for SOC 2 narrative purposes and is not organized by 800-53 control. | P42: Current SSP reflecting the boundary, inventory, data flows, and control implementations | Q42: EVID-041 | R42: GRC-Vault:/WCP-2026/PL/EVID-041_SSP_v1.3.pdf | S42: Design | T42: Examine | U42: Compared the SSP to the as-found environment (system profile). Expected: SSP current within 12 months and accurate. Actual: 19 months old, 3 major architecture changes missing, and 27 of 61 controls described at a higher implementation status than testing supports. | V42: Other Than Satisfied | W42: Outdated SSP that overstates controls. | X42: Low | Y42: RISK-016 | Z42: FIND-017 | AA42: POAM-017 | AB42: POAM-017: In Progress | AD42: 46220 | AE42: 46371 | AF42: GV | AG42: The SSP rewrite is scoped to SP 800-18 Rev. 2 (June 2026), which covers security, privacy, and C-SCRM plans together.
A43: PM-9 | B43: PM - Program Management | C43: Risk Management Strategy | D43: Org-level (PM family is not allocated to baselines) | E43: Develop an organization-wide strategy for managing security and privacy risk, including risk tolerance; implement it consistently; review and update it at a defined frequency. | F43: Applicable | H43: Common (organization-wide) | I43: Organization-wide | J43: Alicia Moreno (CISO) | K43: REQ-024; REQ-012 | L43: Implemented | M43: Implemented | N43: =IF(L43<>M43,"Yes","No") | O43: Risk Management Strategy RMS-001 and a Board-approved Risk Appetite Statement (2025-10-21) define appetite by rating, acceptance authority, and escalation. The risk-scoring methodology (RSK-MTH-001) operationalizes them. | P43: Approved strategy and appetite; evidence of use in decisions | Q43: EVID-042; EVID-060 | R43: GRC-Vault:/WCP-2026/PM/EVID-042_RMS-001_and_appetite.pdf; risk/risk-acceptance/RACC-001.md | S43: Operating Effectiveness | T43: Examine, Interview | U43: Expected: an approved strategy with defined tolerance, applied in decisions. Actual: met. RACC-001 followed the acceptance authority matrix, and VR-001 (Critical) was escalated to the CEO within 5 business days as the strategy requires. | V43: Satisfied | AB43: n/a | AC43: OBS-06 | AD43: 46220 | AE43: 46583 | AF43: GV
A44: PS-3 | B44: PS - Personnel Security | C44: Personnel Screening | D44: Moderate | E44: Screen individuals before authorizing access to the system; rescreen according to defined conditions and frequency. | F44: Applicable | H44: Hybrid (employees Wrenfield; contractors screened by staffing firm under contract) | I44: All workforce | J44: Denise Yamamoto (Director of People) | K44: REQ-014 | L44: Implemented | M44: Implemented | N44: =IF(L44<>M44,"Yes","No") | O44: Background checks are required before system access for all employees. Contractors are screened by Northgate under MSA §8 (attestation per placement). | P44: Screening completion before the access-grant date for a sample of new hires and contractors | Q44: EVID-043 | R44: GRC-Vault:/WCP-2026/PS/EVID-043_screening-sample.pdf | S44: Operating Effectiveness | T44: Examine, Test | U44: Sampled 15 H1 new hires and contractors, comparing screening completion dates to the Okta account creation date. Expected: 15 of 15 screened before access. Actual: 15 of 15 (contractors by Northgate attestation). | V44: Satisfied | AB44: n/a | AD44: 46220 | AE44: 46583 | AF44: GV
A45: PS-4 | B45: PS - Personnel Security | C45: Personnel Termination | D45: Moderate | E45: Upon termination, disable system access within a defined period, terminate or revoke authenticators, conduct exit interviews as needed, retrieve organizational property, and retain access to organizational information. | F45: Applicable | H45: Hybrid (HR + IT) | I45: All workforce | J45: Denise Yamamoto (Director of People) | K45: REQ-004; REQ-013 | L45: Implemented | M45: Partially Implemented | N45: =IF(L45<>M45,"Yes","No") | O45: HR processes terminations in PeopleHub and emails IT. Asset return is tracked by IT. Access removal depends on IT creating a ticket (see AC-2(3)). | P45: Termination population; access removal timing; asset-return records | Q45: EVID-003; EVID-004; EVID-061 | R45: evidence/AC/EVID-003_peoplehub-terminations-2026H1.csv; evidence/AC/EVID-004_okta-deactivation-events-2026H1.csv; evidence/AC/EVID-061_terminations-and-deactivations_2026-07-01_to_09-09.csv | S45: Operating Effectiveness | T45: Examine, Test | U45: Same population as AC-2(3). Asset return: 19 of 19 laptops recovered or wiped. Access removal: 16 of 19 within 24h. The HR-to-IT handoff failed for 2 of 19 terminations (the AP team turnover and a staffing-vendor end date). | V45: Other Than Satisfied | W45: The HR-to-IT handoff is unreliable. | X45: High | Y45: RISK-002 | Z45: FIND-001 | AA45: POAM-001 | AB45: POAM-001: Closed | AD45: 46275 | AE45: 46583 | AF45: GV
A46: PS-5 | B46: PS - Personnel Security | C46: Personnel Transfer | D46: Moderate | E46: Review and confirm the ongoing operational need for current access when individuals are reassigned or transferred; initiate defined transfer actions within a defined period. | F46: Applicable | H46: Hybrid (HR + IT) | I46: All workforce | J46: Denise Yamamoto (Director of People) | K46: REQ-014 | L46: Implemented | M46: Partially Implemented | N46: =IF(L46<>M46,"Yes","No") | O46: Transfers are updated in PeopleHub. New access is requested through tickets. There is no step to remove the prior role's access. | P46: Transfer population; access before and after transfer | Q46: EVID-044 | R46: GRC-Vault:/WCP-2026/PS/EVID-044_transfers.csv | S46: Operating Effectiveness | T46: Examine, Test | U46: Tested all 6 H1 transfers. Expected: prior-role access removed within 5 business days of the transfer. Actual: 5 of 6 transfers had no prior-role privileged or PHI access to remove. In 1 of 6 (cfernandes), PHI support access was retained for 5 months and used after the transfer. | V46: Other Than Satisfied | W46: No access re-baselining on transfer. | X46: Moderate | Y46: RISK-004 | Z46: FIND-004 | AA46: POAM-004 | AB46: POAM-004: In Progress | AD46: 46220 | AE46: 46371 | AF46: GV
A47: PS-7 | B47: PS - Personnel Security | C47: External Personnel Security | D47: Moderate | E47: Establish personnel security requirements for external providers; require them to comply with policies; document the requirements; require notification of transfers and terminations within a defined time; monitor compliance. | F47: Applicable | H47: Hybrid | I47: Contractors (Northgate), vendor personnel (Ironpeak) | J47: Sofia Ricci (Engineering Manager, contractor sponsor) | K47: REQ-004; REQ-008; REQ-013 | L47: Implemented | M47: Partially Implemented | N47: =IF(L47<>M47,"Yes","No") | O47: The Northgate MSA requires screening and 2-business-day notice of contractor departures. Contractor end dates are entered in PeopleHub but not enforced in Okta. Contractor access is approved by the sponsor with no link to the SOW scope. | P47: Contractor roster with SOW dates; notices of departure; access vs SOW scope | Q47: EVID-045; EVID-066 | R47: GRC-Vault:/WCP-2026/PS/EVID-045_contractor-sow-register.xlsx; GRC-Vault:/WCP-2026/PS/EVID-066_contractor-expiry.csv | S47: Operating Effectiveness | T47: Examine, Test | U47: Tested all 5 contractors active in H1 against SOW dates and scope. Expected: access ends at the contract end date and matches SOW scope. Actual: 1 contractor ended without de-provisioning (reported under FIND-001). 1 was active past the recorded end date with the extension undocumented (AR-EX-15). 1 had PHI production access outside the QA SOW scope (AR-EX-16). | V47: Other Than Satisfied | W47: Contractor access is not bound to the engagement term and scope. | X47: Moderate | Y47: RISK-002; RISK-004 | Z47: FIND-006; FIND-001 | AA47: POAM-006; POAM-001 | AB47: POAM-006: Closed; POAM-001: Closed | AD47: 46275 | AE47: 46583 | AF47: GV
A48: RA-2 | B48: RA - Risk Assessment | C48: Security Categorization | D48: Moderate | E48: Categorize the system and information it processes, stores, and transmits; document results in the security plan; have the authorizing official or designee review and approve the categorization. | F48: Applicable | H48: System-specific | I48: WCP-PROD | J48: Samir Haddad (CTO, system owner) | K48: REQ-001; REQ-012 | L48: Implemented | M48: Implemented | N48: =IF(L48<>M48,"Yes","No") | O48: FIPS 199 categorization worksheet (2025-06) rates WCP-PROD Moderate. It was re-validated during this engagement (system profile §4), including a challenge on integrity for RPM data, with review triggers documented. | P48: Categorization with rationale and approval | Q48: EVID-046 | R48: docs/scope/system-profile.md | S48: Design | T48: Examine, Interview | U48: Expected: a documented, approved categorization consistent with the data and mission. Actual: met. The assessor independently reached the same result (Moderate) and recorded a trigger to re-categorize if real-time clinical alerting is added. | V48: Satisfied | AB48: n/a | AD48: 46220 | AE48: 46583 | AF48: ID
A49: RA-3 | B49: RA - Risk Assessment | C49: Risk Assessment | D49: Moderate | E49: Conduct risk assessments identifying threats, vulnerabilities, likelihood, and impact; integrate results with organization-level determinations; document, review, disseminate, and update them. | F49: Applicable | H49: Common (organization-wide) | I49: WCP-PROD | J49: Priya Raman (Security Compliance Manager) | K49: REQ-012 | L49: Implemented | M49: Implemented | N49: =IF(L49<>M49,"Yes","No") | O49: Annual HIPAA risk analysis (2025-09 report) using an SP 800-30-style method. As of 2026-08, it is superseded by the enterprise risk register in this engagement (18 risks, scored with RSK-MTH-001). | P49: Current risk assessment; methodology; evidence of update and dissemination | Q49: EVID-047 | R49: GRC-Vault:/WCP-2026/RA/EVID-047_risk-analysis-2025.pdf | S49: Design | T49: Examine | U49: Expected: a risk assessment within 12 months covering threats, vulnerabilities, likelihood, and impact. Actual: 2025-09 analysis present and adequate. It did not identify the vendor offshore-access or retention gaps; the new register adds them. | V49: Satisfied | AB49: n/a | AD49: 46220 | AE49: 46583 | AF49: ID
A50: RA-5 | B50: RA - Risk Assessment | C50: Vulnerability Monitoring and Scanning | D50: Moderate | E50: Monitor and scan for vulnerabilities at a defined frequency and when new vulnerabilities are reported; use interoperable tools; analyze reports; remediate per risk; share information; use tools that can update the vulnerabilities scanned. | F50: Applicable | H50: System-specific | I50: SYS-01, SYS-05 | J50: Owen Castillo (Security Engineer) | K50: REQ-009 | L50: Implemented | M50: Implemented | N50: =IF(L50<>M50,"Yes","No") | O50: Weekly authenticated scanning of EC2 and EKS nodes (agent-based), container image scanning in CI and in the registry, and a weekly external scan of internet-facing endpoints. Scan scope is driven by owner tags. | P50: Scan configuration and coverage; scan history; findings export | Q50: EVID-048; EVID-031 | R50: evidence/RA/EVID-048_vuln-remediation-aging-2026H1.csv; GRC-Vault:/WCP-2026/CM/EVID-031_inventory.zip | S50: Operating Effectiveness | T50: Examine, Test | U50: Compared scan coverage to the CM-8 inventory. Expected: all production assets scanned weekly. Actual: 100% of tagged assets scanned. Untagged resources (7%) were caught by the external and registry scans but missed by host scans for 1–3 weeks (OBS-02). Remediation timeliness is assessed under SI-2. | V50: Satisfied | W50: Tag-driven scoping leaves a coverage lag for untagged resources (observation). | X50: Low | Y50: RISK-006 | AB50: n/a | AC50: OBS-02 | AD50: 46220 | AE50: 46583 | AF50: ID
A51: RA-7 | B51: RA - Risk Assessment | C51: Risk Response | D51: Moderate | E51: Respond to findings from security and privacy assessments, monitoring, and audits in accordance with organizational risk tolerance. | F51: Applicable | H51: Common (organization-wide) | I51: WCP-PROD | J51: Alicia Moreno (CISO) | K51: REQ-012; REQ-024 | L51: Implemented | M51: Implemented | N51: =IF(L51<>M51,"Yes","No") | O51: Findings receive a treatment decision (mitigate, accept, transfer, or avoid) per RSK-MTH-001, with acceptance authority by rating. Decisions are recorded in the risk register and the POA&M. Formal acceptances use RACC forms. | P51: Treatment decisions for findings; acceptance records signed by the correct authority | Q51: EVID-027; EVID-060 | R51: GRC-Vault:/WCP-2026/CA/EVID-027_secissue-export.csv; risk/risk-acceptance/RACC-001.md | S51: Implementation | T51: Examine | U51: Expected: every finding has a treatment consistent with appetite, and acceptances are signed at the right level. Actual: 19 of 19 findings have treatments. The 1 acceptance (RACC-001, Moderate) was signed by the CFO as risk owner with CISO concurrence, as the matrix requires. | V51: Satisfied | AB51: n/a | AD51: 46220 | AE51: 46583 | AF51: GV
A52: SA-9 | B52: SA - System and Services Acquisition | C52: External System Services | D52: Moderate | E52: Require external service providers to comply with organizational security and privacy requirements and employ defined controls; define oversight roles and responsibilities; monitor provider compliance on an ongoing basis. | F52: Applicable | H52: Common (vendor-management program) | I52: Vendors (14 Tier 1–2) | J52: Beth Kowalski (Vendor Management Lead) | K52: REQ-007; REQ-008; REQ-018 | L52: Implemented | M52: Partially Implemented | N52: =IF(L52<>M52,"Yes","No") | O52: The Third-Party Risk Management Standard TPRM-007 requires tiering, due diligence before contract, security terms (BAA, notification, data return), and reassessment (Tier 1 annually, Tier 2 every 2 years). Standard contract templates were updated in 2025 but not applied to older contracts. | P52: Vendor inventory with tiers; assessment records; contract security terms for Tier 1–2 vendors | Q52: EVID-049; EVID-026; EVID-050; EVID-051; EVID-073 | R52: vendor-risk/vendor-assessment.xlsx; GRC-Vault:/WCP-2026/CA/EVID-026_interconnection-agreements.zip; evidence/SR/EVID-050_quarrystone-soc2-review-workpaper.md; GRC-Vault:/WCP-2026/SR/EVID-051_pending; GRC-Vault:/WCP-2026/SR/EVID-073_quarrystone-amendment-v3.pdf | S52: Operating Effectiveness | T52: Examine, Interview, Test | U52: Tested all 14 Tier 1–2 vendors for a current assessment and adequate contract terms, plus a deep assessment of Quarrystone. Expected: 14 of 14 current, with notification and data-return terms. Actual: 9 of 14 current. Quarrystone's terms allow 30-day breach notice, include no US-only restriction, and do not define data return. Offshore subcontractor access to PHI was confirmed. | V52: Other Than Satisfied | W52: Provider oversight is not operating consistently; the highest-risk vendor has material contractual and access gaps. | X52: High | Y52: RISK-010; RISK-011 | Z52: FIND-015; FIND-016 | AA52: POAM-015; POAM-016 | AB52: POAM-015: In Progress; POAM-016: In Progress | AD52: 46220 | AE52: 46398 | AF52: GV
A53: SA-22 | B53: SA - System and Services Acquisition | C53: Unsupported System Components | D53: Moderate | E53: Replace system components when support is no longer available from the developer, vendor, or manufacturer; or provide options for alternative sources of continued support. | F53: Applicable | H53: System-specific | I53: SYS-05, legacy-reports, notify-worker | J53: Tomasz Wierzbicki (Director, Platform Engineering) | K53: REQ-010 | L53: Partially Implemented | M53: Partially Implemented | N53: =IF(L53<>M53,"Yes","No") | O53: Most components are current. Three are unsupported: wf-sftp-01 (Windows Server 2012 R2; extended support ended 2023-10-10; no ESU enrollment), legacy-reports (PostgreSQL 11; community support ended 2023-11-09), and the notify-worker container (Node.js 16; end of life 2023-09-11). Compensating controls on wf-sftp-01 are EDR, an SFTP source allowlist, and weekly scanning. | P53: Software inventory with support status; replacement plans; compensating-control documentation | Q53: EVID-052; EVID-048 | R53: GRC-Vault:/WCP-2026/SA/EVID-052_eol-inventory.csv; evidence/RA/EVID-048_vuln-remediation-aging-2026H1.csv | S53: Implementation | T53: Examine, Test | U53: Compared the OS, database, and runtime inventory to vendor lifecycle dates. Expected: 0 unsupported components, or SHCA-approved compensating controls. Actual: 3 unsupported components, 2 of them handling PHI. They account for 4 of the 6 open past-SLA vulnerabilities. No SHCA-approved exception exists (CSA §7.4). | V53: Other Than Satisfied | W53: Unsupported components in the PHI data path. | X53: High | Y53: RISK-007 | Z53: FIND-011 | AA53: POAM-011 | AB53: POAM-011: Delayed | AD53: 46220 | AE53: 46356 | AF53: PR
A54: SC-7 | B54: SC - System and Communications Protection | C54: Boundary Protection | D54: Moderate | E54: Monitor and control communications at the external and key internal boundaries; implement subnetworks for publicly accessible components; connect to external networks only through managed interfaces. | F54: Applicable | H54: System-specific | I54: SYS-01, SYS-05 | J54: Tomasz Wierzbicki (Director, Platform Engineering) | K54: REQ-001; REQ-021 | L54: Implemented | M54: Partially Implemented | N54: =IF(L54<>M54,"Yes","No") | O54: Public traffic enters through CloudFront and WAF to internal ALBs. Workloads sit in private subnets with VPC endpoints for AWS services. There is an egress allowlist for EKS. wf-sftp-01 sits in a public subnet with an SFTP (22) allowlist of 6 partner CIDRs. | P54: Network architecture; security group and NACL exports; exposure scans | Q54: EVID-053; EVID-028; EVID-068 | R54: evidence/CM/EVID-053_wf-sftp-01-security-group_2026-07-02.json; GRC-Vault:/WCP-2026/CM/EVID-028_securityhub.csv; GRC-Vault:/WCP-2026/SC/EVID-068_sg-fix.zip | S54: Implementation | T54: Examine, Test | U54: Enumerated all security groups with 0.0.0.0/0 ingress. Expected: only CloudFront/ALB listeners on 443. Actual: wf-sftp-01 allowed TCP 3389 (RDP) from 0.0.0.0/0, added under emergency change CHG-2026-0412 on 2026-05-19 and never reverted (43 days exposed at discovery). No evidence of successful RDP logons from external addresses (reviewed Windows Security log 4624 type 10 for the period). Fixed within 24h of discovery; validated 2026-07-10. | V54: Other Than Satisfied | W54: Internet-exposed administrative service on an unsupported host. | X54: High | Y54: RISK-012; RISK-007 | Z54: FIND-012 | AA54: POAM-012 | AB54: POAM-012: Closed | AD54: 46213 | AE54: 46583 | AF54: PR
A55: SC-8 | B55: SC - System and Communications Protection | C55: Transmission Confidentiality and Integrity | D55: Moderate | E55: Protect the confidentiality and integrity of transmitted information. | F55: Applicable | H55: System-specific | I55: SYS-01, SYS-04, SYS-05 | J55: Tomasz Wierzbicki (Director, Platform Engineering) | K55: REQ-021 | L55: Implemented | M55: Implemented | N55: =IF(L55<>M55,"Yes","No") | O55: TLS 1.2+ only (the CloudFront and ALB security policies disable TLS 1.0/1.1). The database enforces SSL (rds.force_ssl=1). SFTP to partners uses SSH. HL7/FHIR interfaces run over TLS or VPN. | P55: TLS policies; database SSL enforcement; external TLS scan | Q55: EVID-054 | R55: GRC-Vault:/WCP-2026/SC/EVID-054_tls.zip | S55: Implementation | T55: Examine, Test | U55: Scanned the 4 public endpoints with a TLS scanner (TLS 1.2/1.3 only, no weak ciphers) and confirmed rds.force_ssl=1 in the parameter group. Expected: encryption for all PHI in transit. Actual: met. | V55: Satisfied | AB55: n/a | AD55: 46220 | AE55: 46583 | AF55: PR
A56: SC-12 | B56: SC - System and Communications Protection | C56: Cryptographic Key Establishment and Management | D56: Moderate | E56: Establish and manage cryptographic keys when cryptography is employed, per defined requirements for key generation, distribution, storage, access, and destruction. | F56: Applicable | H56: Hybrid (cloud key-management service; Wrenfield key policies) | I56: SYS-01, SYS-04 | J56: Tomasz Wierzbicki (Director, Platform Engineering) | K56: REQ-021 | L56: Implemented | M56: Implemented | N56: =IF(L56<>M56,"Yes","No") | O56: Customer-managed KMS keys for Aurora, S3 PHI buckets, EBS, and backups, with annual automatic rotation enabled. Key policies separate key administrators (SRE) from key users (service roles). No key material leaves KMS. | P56: Key inventory; rotation settings; key policies | Q56: EVID-055 | R56: GRC-Vault:/WCP-2026/SC/EVID-055_kms.json | S56: Implementation | T56: Examine | U56: Examined 9 customer-managed keys. Expected: rotation enabled and separation of admin and usage duties. Actual: 9 of 9 with rotation enabled; key policies separate administration from use. | V56: Satisfied | AB56: n/a | AD56: 46220 | AE56: 46583 | AF56: PR
A57: SC-28 | B57: SC - System and Communications Protection | C57: Protection of Information at Rest | D57: Moderate | E57: Protect the confidentiality and integrity of defined information at rest. | F57: Applicable | H57: Hybrid | I57: SYS-01, SYS-04, SYS-10 | J57: Tomasz Wierzbicki (Director, Platform Engineering) | K57: REQ-021 | L57: Implemented | M57: Implemented | N57: =IF(L57<>M57,"Yes","No") | O57: Aurora storage encryption (KMS CMK), S3 default encryption with bucket keys, EBS encryption-by-default at the account level, and backup vault encryption. Laptops use FileVault or BitLocker, enforced by MDM. | P57: Encryption settings for every PHI data store; endpoint encryption compliance | Q57: EVID-056 | R57: GRC-Vault:/WCP-2026/SC/EVID-056_encryption.zip | S57: Implementation | T57: Examine, Test | U57: Queried the encryption status of every RDS, S3, and EBS resource in wcp-prod (100% encrypted) and the MDM encryption compliance (362 of 362 endpoints). Expected: all PHI at rest encrypted. Actual: met. wf-sftp-01 volumes are encrypted (EBS default). | V57: Satisfied | Y57: RISK-018 | AB57: n/a | AD57: 46220 | AE57: 46583 | AF57: PR
A58: SI-2 | B58: SI - System and Information Integrity | C58: Flaw Remediation | D58: Moderate | E58: Identify, report, and correct system flaws; test updates before installation; install security-relevant updates within a defined time; incorporate flaw remediation into configuration management. | F58: Applicable | H58: System-specific | I58: SYS-01, SYS-05 | J58: Grace Lindqvist (VP Engineering) | K58: REQ-009 | L58: Implemented | M58: Partially Implemented | N58: =IF(L58<>M58,"Yes","No") | O58: VM-003 sets SLAs of Critical 15 days, High 30, and Moderate 90. Findings are auto-ticketed to the owning team. Container fixes ship through base-image rebuilds. Risk exceptions require a CISO-approved form (VM-003 §7). | P58: Complete population of Critical/High findings with detection and remediation dates; exception approvals | Q58: EVID-048 | R58: evidence/RA/EVID-048_vuln-remediation-aging-2026H1.csv | S58: Operating Effectiveness | T58: Examine, Test | U58: Full population test (test-results/si2-vuln-sla.md). Expected: 100% remediated within SLA, or approved exception. Actual: 14 of 61 (23%) breached SLA; 6 remain open past SLA (2 Critical), and 0 exceptions were filed. Engineering disputes the 2 Critical findings as unreachable. Assessor position: the SLA applies until an exception with reachability analysis is approved. | V58: Other Than Satisfied | W58: Remediation timeliness below SLA; exception process unused. | X58: High | Y58: RISK-006 | Z58: FIND-010 | AA58: POAM-010 | AB58: POAM-010: In Progress | AC58: OBS-04 | AD58: 46220 | AE58: 46331 | AF58: PR
A59: SI-3 | B59: SI - System and Information Integrity | C59: Malicious Code Protection | D59: Moderate | E59: Implement signature- and/or non-signature-based malicious code protection at entry and exit points; update it; scan periodically and in real time; take defined actions on detection. | F59: Applicable | H59: Hybrid | I59: SYS-01, SYS-05, SYS-10 | J59: Owen Castillo (Security Engineer) | K59: REQ-016 | L59: Implemented | M59: Implemented | N59: =IF(L59<>M59,"Yes","No") | O59: EDR on endpoints and EC2 hosts (including wf-sftp-01), runtime protection on EKS nodes (DaemonSet), and email security filtering. Detections auto-contain and escalate to MDR. | P59: Coverage report reconciled to inventory; policy settings; detection records | Q59: EVID-057; EVID-038 | R59: GRC-Vault:/WCP-2026/SI/EVID-057_edr-coverage.csv; evidence/IR/EVID-038_incident-tickets-2026H1.csv | S59: Operating Effectiveness | T59: Examine, Test | U59: Reconciled EDR sensors to the MDM and AWS inventory: 358 of 362 endpoints (4 were new devices under 72h old, within the provisioning standard), 100% of EC2 hosts and EKS nodes. INC-2026-0095 shows detection and containment operating. | V59: Satisfied | AB59: n/a | AD59: 46220 | AE59: 46583 | AF59: PR
A60: SI-4 | B60: SI - System and Information Integrity | C60: System Monitoring | D60: Moderate | E60: Monitor the system to detect attacks and indicators of attacks and unauthorized connections; identify unauthorized use; deploy monitoring devices strategically; analyze events; adjust monitoring when risk changes. | F60: Applicable | H60: Hybrid (MDR provider + Wrenfield) | I60: SYS-01, SYS-02, SYS-08 | J60: Owen Castillo (Security Engineer) | K60: REQ-019; REQ-016 | L60: Implemented | M60: Implemented | N60: =IF(L60<>M60,"Yes","No") | O60: GuardDuty (all accounts), SIEM correlation rules (Okta anomalies, impossible travel, privilege escalation), and 24x7 MDR triage with a 30-minute SLA for High alerts. | P60: Detection inventory; alert triage metrics; sample alert records | Q60: EVID-058 | R60: GRC-Vault:/WCP-2026/SI/EVID-058_monitoring.zip | S60: Operating Effectiveness | T60: Examine, Test | U60: Examined the detection inventory (41 rules) and MDR metrics for H1 (High alerts triaged within 30 minutes: 97%). Sampled 10 alerts, all dispositioned. Expected: continuous monitoring with timely triage. Actual: met. The weekly human privileged-activity review is a separate AU-6 control. | V60: Satisfied | AB60: n/a | AD60: 46220 | AE60: 46583 | AF60: DE
A61: SR-2 | B61: SR - Supply Chain Risk Management | C61: Supply Chain Risk Management Plan | D61: Moderate | E61: Develop a plan for managing supply chain risks associated with the research, development, design, manufacturing, acquisition, delivery, integration, operations, maintenance, and disposal of the system; review, update, and protect it. | F61: Applicable | H61: Common (organization-wide) | I61: Organization-wide | J61: Beth Kowalski (Vendor Management Lead) | K61: REQ-008; REQ-001 | L61: Planned | M61: Planned | N61: =IF(L61<>M61,"Yes","No") | O61: No C-SCRM plan exists. TPRM-007 covers vendor due diligence but not software supply chain (dependencies, CI/CD, SBOM) or fourth-party mapping. A draft outline was produced in 2026-06. | P61: Approved C-SCRM plan | Q61: EVID-059 | R61: GRC-Vault:/WCP-2026/SR/EVID-059_cscrm-outline.docx | S61: Design | T61: Examine, Interview | U61: Expected: an approved C-SCRM plan. Actual: an outline only (EVID-059, Insufficient). The plan is scheduled for Q4 2026, aligned to SP 800-161 Rev. 1 Update 1 and the new SP 800-18 Rev. 2 C-SCRM plan structure. | V61: Other Than Satisfied | W61: No C-SCRM plan. | X61: Moderate | Y61: RISK-011 | Z61: FIND-015 | AA61: POAM-015 | AB61: POAM-015: In Progress | AD61: 46220 | AE61: 46421 | AF61: GV
A62: SR-6 | B62: SR - Supply Chain Risk Management | C62: Supplier Assessments and Reviews | D62: Moderate | E62: Assess and review the supply chain-related risks associated with suppliers or contractors and the systems, components, or services they provide, at a defined frequency. | F62: Applicable | H62: Common (vendor-management program) | I62: Vendors (14 Tier 1–2) | J62: Beth Kowalski (Vendor Management Lead) | K62: REQ-008; REQ-018 | L62: Implemented | M62: Partially Implemented | N62: =IF(L62<>M62,"Yes","No") | O62: Tier-based reassessment (Tier 1 annually) using a questionnaire plus attestation review (SOC 2 and pentest summaries). There is no fourth-party inventory. Assessments are tracked in a spreadsheet. | P62: Assessment records per vendor, within the frequency for its tier | Q62: EVID-049; EVID-050; EVID-051 | R62: vendor-risk/vendor-assessment.xlsx; evidence/SR/EVID-050_quarrystone-soc2-review-workpaper.md; GRC-Vault:/WCP-2026/SR/EVID-051_pending | S62: Operating Effectiveness | T62: Examine, Test | U62: Expected: all Tier 1–2 vendors assessed within frequency. Actual: 5 of 14 overdue or never assessed (including Tier 1 Pulsewire and Ironpeak). The Quarrystone deep assessment found 12 vendor-risk issues (1 Critical, contained 2026-07-24). The vendor's pentest report and retest evidence are still outstanding (EVID-051). | V62: Other Than Satisfied | W62: Supplier reviews are overdue, and no fourth-party visibility exists. | X62: High | Y62: RISK-010; RISK-011 | Z62: FIND-015; FIND-016 | AA62: POAM-015; POAM-016 | AB62: POAM-015: In Progress; POAM-016: In Progress | AD62: 46220 | AE62: 46398 | AF62: GV

Sheet Risks
A1: Risk ID | B1: Risk Title | C1: Risk Description | D1: Asset / Process | E1: Threat | F1: Vulnerability | G1: Existing Controls | H1: Inherent Likelihood | I1: Inherent Impact | J1: Inherent Score | K1: Inherent Risk | L1: Current Likelihood | M1: Current Impact | N1: Current Score | O1: Current Risk | P1: Treatment Strategy | Q1: Planned Mitigation | R1: Risk Owner | S1: Target Date | T1: Residual Likelihood | U1: Residual Impact | V1: Residual Score | W1: Residual Risk | X1: Status | Y1: Related NIST Controls | Z1: Related Findings | AA1: Related POA&M | AB1: Review Date | AC1: Rationale: Inherent | AD1: Rationale: Current | AE1: Rationale: Residual
A2: RISK-001 | B2: Privileged cloud or identity admin account misused or compromised | C2: An attacker phishes or steals the session of a user holding production AdministratorAccess, Okta Super Admin, or GitHub owner, then exfiltrates PHI or destroys infrastructure. | D2: AWS wcp-prod admin plane, Okta tenant, GitHub org | E2: External actor (phishing, session-token theft) or malicious/negligent insider | F2: Excess admin grants; admin performed from daily-use accounts; no JIT elevation | G2: Okta SSO+MFA for most users; CloudTrail and GuardDuty; MDR 24x7; Vault Lock on backups | H2: 4 | I2: 5 | J2: =H2*I2 | K2: =IF(J2="","",IF(J2>=20,"Critical",IF(J2>=10,"High",IF(J2>=5,"Moderate","Low")))) | L2: 3 | M2: 5 | N2: =L2*M2 | O2: =IF(N2="","",IF(N2>=20,"Critical",IF(N2>=10,"High",IF(N2>=5,"Moderate","Low")))) | P2: Mitigate | Q2: Remove excess grants; -adm accounts; JIT elevation; GitHub owner cap (POAM-003) | R2: Samir Haddad (CTO) | S2: 46331 | T2: 2 | U2: 4 | V2: =T2*U2 | W2: =IF(V2="","",IF(V2>=20,"Critical",IF(V2>=10,"High",IF(V2>=5,"Moderate","Low")))) | X2: Treatment in progress | Y2: AC-6; AC-6(2); AC-6(5); IA-2(1) | Z2: FIND-003 | AA2: POAM-003 | AB2: 46283 | AC2: L4: identity-based intrusion is the dominant cloud attack path. I5: admin reaches all PHI (>50k records) and can cause an outage over 24h. | AD2: L3: MFA and monitoring raise attacker effort, but 6 unjustified or daily-account admin assignments existed. I5 unchanged: any admin can still reach everything. | AE2: L2: -adm accounts with phishing-resistant MFA plus approval-gated JIT elevation. I4: time-boxed sessions and Vault Lock limit destructive impact and dwell time, but exfiltration during a session is still possible.
A3: RISK-002 | B3: Unauthorized access by former employees or contractors | C3: A departed worker's still-active account is used, by them or by an attacker, to access PHI or financial systems. | D3: All in-scope systems, including Ledgerline and the vendor portal | E3: Former workforce member (disgruntled or careless), or an attacker using an orphaned account | F3: Manual de-provisioning; local accounts outside SSO; contractor end dates not enforced | G3: Okta deactivation by IT ticket; asset recovery at exit | H3: 4 | I3: 4 | J3: =H3*I3 | K3: =IF(J3="","",IF(J3>=20,"Critical",IF(J3>=10,"High",IF(J3>=5,"Moderate","Low")))) | L3: 4 | M3: 4 | N3: =L3*M3 | O3: =IF(N3="","",IF(N3>=20,"Critical",IF(N3>=10,"High",IF(N3>=5,"Moderate","Low")))) | P3: Mitigate | Q3: HR-to-Okta reconciliation with auto-ticketing; contractor expiry; local-account cleanup (POAM-001, POAM-006) | R3: Alicia Moreno (CISO) | S3: 46275 | T3: 2 | U3: 4 | V3: =T3*U3 | W3: =IF(V3="","",IF(V3>=20,"Critical",IF(V3>=10,"High",IF(V3>=5,"Moderate","Low")))) | X3: Treated (residual achieved; monitoring) | Y3: AC-2; AC-2(1); AC-2(3); PS-4; PS-7 | Z3: FIND-001; FIND-006 | AA3: POAM-001; POAM-006 | AB3: 46283 | AC3: L4: turnover of about 38/year plus contractors, and orphaned accounts are a well-known misuse path. I4: AWS admin or PHI DB access affects 500–50,000+ records; limited by role mix. | AD3: L4 unchanged: the control failed testing (2 of 19 not disabled, 1 post-termination sign-in, local admin account active 95 days) and earns no credit. I4. | AE3: L2: daily reconciliation job, contractor account expiry, and a local-account inventory, validated 7 of 7. I4 unchanged: a missed account could still reach sensitive data.
A4: RISK-003 | B4: Account takeover through MFA gaps | C4: An attacker obtains the password of an MFA-exempt account and signs in directly, inheriting that user's access, including identity administration. | D4: Okta and all federated systems | E4: Credential phishing, password spraying, reuse of breached credentials | F4: MFA exemption group (9 humans incl. an Okta Super Admin); IAM user without MFA | G4: Global MFA policy for 97% of users; replay-resistant authenticators; Okta ThreatInsight | H4: 4 | I4: 5 | J4: =H4*I4 | K4: =IF(J4="","",IF(J4>=20,"Critical",IF(J4>=10,"High",IF(J4>=5,"Moderate","Low")))) | L4: 3 | M4: 5 | N4: =L4*M4 | O4: =IF(N4="","",IF(N4>=20,"Critical",IF(N4>=10,"High",IF(N4>=5,"Moderate","Low")))) | P4: Mitigate | Q4: Delete the exemption policy; enroll all users; phishing-resistant admin MFA; exception workflow (POAM-002) | R4: Alicia Moreno (CISO) | S4: 46270 | T4: 2 | U4: 4 | V4: =T4*U4 | W4: =IF(V4="","",IF(V4>=20,"Critical",IF(V4>=10,"High",IF(V4>=5,"Moderate","Low")))) | X4: Treated (residual achieved; monitoring) | Y4: IA-2(1); IA-2(2); IA-2(8) | Z4: FIND-002 | AA4: POAM-002 | AB4: 46283 | AC4: L4: phishing is the leading initial-access vector. I5: federation reaches AWS prod and PHI. | AD4: L3: MFA covers 97%, a partial control. I5: an exempt Okta Super Admin could reach everything. | AE4: L2: no exemptions; phishing-resistant MFA for admins; token theft still possible. I4: least-privilege work narrows what one account reaches.
A5: RISK-004 | B5: Access creep from ineffective recertification | C5: Users accumulate access beyond need over time, increasing the blast radius of any compromise or misuse. | D5: Privileged and PHI entitlements across 9 systems | E5: Insider misuse; attacker leveraging over-privileged accounts | F5: Rubber-stamp reviews; privileged systems out of review scope; no re-baseline on transfer | G5: Quarterly Okta app certification (limited scope) | H5: 4 | I5: 3 | J5: =H5*I5 | K5: =IF(J5="","",IF(J5>=20,"Critical",IF(J5>=10,"High",IF(J5>=5,"Moderate","Low")))) | L5: 4 | M5: 3 | N5: =L5*M5 | O5: =IF(N5="","",IF(N5>=20,"Critical",IF(N5>=10,"High",IF(N5>=5,"Moderate","Low")))) | P5: Mitigate | Q5: Redesign certifications; transfer-triggered review (POAM-004) | R5: Alicia Moreno (CISO) | S5: 46326 | T5: 2 | U5: 3 | V5: =T5*U5 | W5: =IF(V5="","",IF(V5>=20,"Critical",IF(V5>=10,"High",IF(V5>=5,"Moderate","Low")))) | X5: Treatment in progress | Y5: AC-6(7); AC-2; PS-5 | Z5: FIND-004; FIND-006 | AA5: POAM-004 | AB5: 46283 | AC5: L4: fast growth, transfers, and contractors make creep near-certain without review. I3: creep usually adds read access; worst credible case is fewer than 500 records. | AD5: L4: the review operated but was ineffective (100% approval, key systems excluded), so no credit. I3. | AE5: L2: full-scope campaigns with usage data and flagged items needing rationale. I3.
A6: RISK-005 | B6: Inability to detect or investigate PHI access | C6: Misuse goes unnoticed, or a breach found months later cannot be scoped, forcing presumptive notification of large patient populations. | D6: Audit logs (CloudTrail, application PHI-access audit, SIEM) | E6: Undetected insider or attacker activity; late-discovered breach | F6: 90–180-day retention; inconsistent privileged-activity review | G6: Comprehensive event logging (AU-2); immutable log archive (AU-9); MDR alerting (SI-4) | H6: 3 | I6: 4 | J6: =H6*I6 | K6: =IF(J6="","",IF(J6>=20,"Critical",IF(J6>=10,"High",IF(J6>=5,"Moderate","Low")))) | L6: 3 | M6: 4 | N6: =L6*M6 | O6: =IF(N6="","",IF(N6>=20,"Critical",IF(N6>=10,"High",IF(N6>=5,"Moderate","Low")))) | P6: Mitigate | Q6: Extend retention (POAM-008, done); backup reviewer and escalation (POAM-009) | R6: Alicia Moreno (CISO) | S6: 46326 | T6: 2 | U6: 3 | V6: =T6*U6 | W6: =IF(V6="","",IF(V6>=20,"Critical",IF(V6>=10,"High",IF(V6>=5,"Moderate","Low")))) | X6: Treatment in progress | Y6: AU-6; AU-11; AU-2; AU-9 | Z6: FIND-008; FIND-009 | AA6: POAM-008; POAM-009 | AB6: 46283 | AC6: L3: breaches are often discovered after 90+ days. I4: inability to scope means broad notification plus contract breach. | AD6: L3: logging is strong, but retention is short and 35% of weekly reviews were missed or incomplete. I4. | AE6: L2: 400-day retention plus a backup reviewer. I3: records now exist to scope and limit notification.
A7: RISK-006 | B7: Exploitation of unremediated vulnerabilities | C7: An attacker exploits a known, unpatched flaw in a production service or host to gain a foothold. | D7: Internet-facing services and container workloads | E7: Opportunistic exploitation of known CVEs; ransomware affiliates | F7: 23% SLA misses; end-of-life runtimes; exception process unused | G7: WAF; weekly authenticated scanning; container image scanning; EDR; MDR | H7: 4 | I7: 5 | J7: =H7*I7 | K7: =IF(J7="","",IF(J7>=20,"Critical",IF(J7>=10,"High",IF(J7>=5,"Moderate","Low")))) | L7: 3 | M7: 4 | N7: =L7*M7 | O7: =IF(N7="","",IF(N7>=20,"Critical",IF(N7>=10,"High",IF(N7>=5,"Moderate","Low")))) | P7: Mitigate | Q7: Upgrade EOL runtimes; exception process; SLA reporting; tag enforcement (POAM-010) | R7: Grace Lindqvist (VP Engineering) | S7: 46331 | T7: 2 | U7: 4 | V7: =T7*U7 | W7: =IF(V7="","",IF(V7>=20,"Critical",IF(V7>=10,"High",IF(V7>=5,"Moderate","Low")))) | X7: Treatment in progress | Y7: RA-5; SI-2; CM-8 | Z7: FIND-010 | AA7: POAM-010 | AB7: 46283 | AC7: L4: exploitation of known vulnerabilities is a top initial-access vector. I5: PHI platform compromise. | AD7: L3: scanning, WAF, and EDR are effective layers, but 6 items are open past SLA. I4: segmentation (private subnets) limits the blast radius from most workloads. | AE7: L2: SLA adherence with governed exceptions. I4: same architecture.
A8: RISK-007 | B8: Compromise of unsupported legacy components in the PHI path | C8: An attacker exploits an unpatchable flaw on the legacy SFTP host, which holds the nightly full-PHI extract, and pivots or exfiltrates. | D8: wf-sftp-01 (Windows 2012 R2), legacy-reports (PostgreSQL 11), notify-worker (Node 16) | E8: Exploitation of unpatchable flaws; ransomware | F8: No vendor patches; host previously exposed via internet-facing RDP | G8: EDR; SFTP source allowlist; weekly scanning; SSM-only admin (after FIND-012 fix) | H8: 4 | I8: 4 | J8: =H8*I8 | K8: =IF(J8="","",IF(J8>=20,"Critical",IF(J8>=10,"High",IF(J8>=5,"Moderate","Low")))) | L8: 3 | M8: 4 | N8: =L8*M8 | O8: =IF(N8="","",IF(N8>=20,"Critical",IF(N8>=10,"High",IF(N8>=5,"Moderate","Low")))) | P8: Avoid | Q8: Decommission wf-sftp-01 and legacy-reports; upgrade notify-worker (POAM-011) | R8: Samir Haddad (CTO) | S8: 46371 | T8: 1 | U8: 4 | V8: =T8*U8 | W8: =IF(V8="","",IF(V8>=20,"Critical",IF(V8>=10,"High",IF(V8>=5,"Moderate","Low")))) | X8: Treatment in progress (delayed) | Y8: SA-22; SC-7; CM-6; SI-2 | Z8: FIND-011; FIND-012 | AA8: POAM-011; POAM-012 | AB8: 46283 | AC8: L4: unsupported, internet-reachable Windows host. I4: a full-PHI extract sits there transiently (worst credible case is one night's file, bounded). | AD8: L3: RDP closed, allowlist and EDR in place, but no patches. I4. | AE8: L1: components decommissioned (Avoid). I4 kept, because the managed-transfer replacement still moves the same data.
A9: RISK-008 | B9: Failed or slow recovery from ransomware or data corruption | C9: A destructive event forces recovery, and recovery takes longer than RTO or loses data because the process was never exercised. | D9: wcp-core-db and WCP services | E9: Ransomware; destructive insider; data corruption | F9: Restore never tested (at fieldwork); contingency plan untested | G9: PITR (35 days); cross-region, cross-account backups with Vault Lock; BC/DR plan | H9: 3 | I9: 5 | J9: =H9*I9 | K9: =IF(J9="","",IF(J9>=20,"Critical",IF(J9>=10,"High",IF(J9>=5,"Moderate","Low")))) | L9: 2 | M9: 5 | N9: =L9*M9 | O9: =IF(N9="","",IF(N9>=20,"Critical",IF(N9>=10,"High",IF(N9>=5,"Moderate","Low")))) | P9: Mitigate | Q9: Semi-annual restore tests (POAM-013, done); CP exercise (POAM-014) | R9: Samir Haddad (CTO) | S9: 46341 | T9: 2 | U9: 4 | V9: =T9*U9 | W9: =IF(V9="","",IF(V9>=20,"Critical",IF(V9>=10,"High",IF(V9>=5,"Moderate","Low")))) | X9: Treatment in progress | Y9: CP-2; CP-4; CP-9; CP-9(1) | Z9: FIND-013; FIND-014 | AA9: POAM-013; POAM-014 | AB9: 46283 | AC9: L3: healthcare ransomware frequency. I5: outage over 24h for clinical workflows. | AD9: L2: strong, immutable backups reduce the chance of an unrecoverable event. I5: recovery time was unproven. | AE9: L2. I4: restore proven at 3h41m (within the 4h RTO); a full contingency exercise is pending (POAM-014).
A10: RISK-009 | B10: Delayed or ineffective response to a major incident | C10: During a major incident, unclear roles or notification steps delay containment or cause a missed contractual or regulatory notification deadline. | D10: Incident response capability and notification obligations | E10: Major incident (ransomware, large PHI breach) stressing untested processes | F10: No IR exercise in 21 months; SHCA 24h path never rehearsed | G10: IRP-005 (current); 24x7 MDR; incidents in H1 handled well (IR-4 satisfied) | H10: 3 | I10: 4 | J10: =H10*I10 | K10: =IF(J10="","",IF(J10>=20,"Critical",IF(J10>=10,"High",IF(J10>=5,"Moderate","Low")))) | L10: 3 | M10: 4 | N10: =L10*M10 | O10: =IF(N10="","",IF(N10>=20,"Critical",IF(N10>=10,"High",IF(N10>=5,"Moderate","Low")))) | P10: Mitigate | Q10: Ransomware tabletop and plan update (POAM-014) | R10: Alicia Moreno (CISO) | S10: 46341 | T10: 2 | U10: 3 | V10: =T10*U10 | W10: =IF(V10="","",IF(V10>=20,"Critical",IF(V10>=10,"High",IF(V10>=5,"Moderate","Low")))) | X10: Treatment in progress | Y10: IR-3; IR-4; IR-6; IR-8 | Z10: FIND-014 | AA10: POAM-014 | AB10: 46283 | AC10: L3: at least one significant incident per year is plausible. I4: missed notification means a contract breach and regulatory scrutiny. | AD10: L3: good day-to-day handling, but major-incident paths are untested. I4. | AE10: L2: rehearsed plan with the SHCA step. I3: faster, coordinated response limits impact.
A11: RISK-010 | B11: PHI exposure through the analytics vendor (Quarrystone) | C11: A breach at Quarrystone or its offshore subcontractor exposes Wrenfield PHI, and notice arrives too late for Wrenfield to meet 24h or 5-day obligations. | D11: Nightly full-PHI extract (about 410k patients) processed by Quarrystone and its subcontractors | E11: Vendor or subcontractor breach; unauthorized offshore access; delayed breach notice | F11: Offshore subcontractor access; 30-day notice term; excess data fields; stale pentest | G11: BAA; SOC 2 Type II (unqualified); encryption in transit and at rest; interim suspension of offshore access (2026-07-24) | H11: 4 | I11: 5 | J11: =H11*I11 | K11: =IF(J11="","",IF(J11>=20,"Critical",IF(J11>=10,"High",IF(J11>=5,"Moderate","Low")))) | L11: 3 | M11: 5 | N11: =L11*M11 | O11: =IF(N11="","",IF(N11>=20,"Critical",IF(N11>=10,"High",IF(N11>=5,"Moderate","Low")))) | P11: Mitigate | Q11: Contract amendment; data minimization; pentest and retest; monitoring plan (POAM-016). Transfer (partial) through cyber insurance and vendor indemnity. | R11: Dr. Miriam Castell (VP Clinical Analytics) | S11: 46331 | T11: 2 | U11: 4 | V11: =T11*U11 | W11: =IF(V11="","",IF(V11>=20,"Critical",IF(V11>=10,"High",IF(V11>=5,"Moderate","Low")))) | X11: Treatment in progress | Y11: SA-9; SR-6; CA-3 | Z11: FIND-016; FIND-015 | AA11: POAM-016; POAM-015 | AB11: 46283 | AC11: L4: third-party breaches are frequent in healthcare, and an undisclosed offshore party was present. I5: >50k records plus SHCA contract loss. | AD11: L3: vendor controls are generally mature (SOC 2, encryption) and offshore access is suspended, but the contract terms are unchanged. I5. | AE11: L2: contractual US-only with technical enforcement, 24h notice, and current pentest. I4: minimized extract (no contact details or free text) reduces the records and sensitivity exposed.
A12: RISK-011 | B12: Software or vendor supply-chain compromise | C12: A compromised dependency or vendor integration introduces malicious code or access into WCP. | D12: CI/CD pipeline, open-source dependencies, vendor integrations | E12: Malicious dependency or compromised vendor update or integration | F12: No C-SCRM plan; no fourth-party inventory; 5 vendors overdue for review | G12: Dependency scanning; branch protection and required review; OIDC deploy (no static keys); pinned base images | H12: 3 | I12: 5 | J12: =H12*I12 | K12: =IF(J12="","",IF(J12>=20,"Critical",IF(J12>=10,"High",IF(J12>=5,"Moderate","Low")))) | L12: 3 | M12: 4 | N12: =L12*M12 | O12: =IF(N12="","",IF(N12>=20,"Critical",IF(N12>=10,"High",IF(N12>=5,"Moderate","Low")))) | P12: Mitigate | Q12: C-SCRM plan; clear the vendor backlog; fourth-party inventory (POAM-015) | R12: Beth Kowalski (Vendor Management Lead) | S12: 46421 | T12: 2 | U12: 4 | V12: =T12*U12 | W12: =IF(V12="","",IF(V12>=20,"Critical",IF(V12>=10,"High",IF(V12>=5,"Moderate","Low")))) | X12: Treatment in progress | Y12: SR-2; SR-6; SA-9 | Z12: FIND-015 | AA12: POAM-015 | AB12: 46283 | AC12: L3: supply-chain attacks are increasing. I5: code execution in the PHI platform. | AD12: L3: good pipeline hygiene, but no program-level supply chain risk management. I4: OIDC and least-privilege deploy roles limit what a compromised pipeline can reach. | AE12: L2: C-SCRM plan, current vendor reviews, fourth-party visibility. I4.
A13: RISK-012 | B13: Cloud misconfiguration exposing PHI or admin services | C13: A manual misconfiguration (an open port, a public resource) exposes PHI or an admin interface to the internet. | D13: AWS wcp-prod network and storage configuration | E13: Opportunistic internet scanning; misconfiguration exploited by attackers | F13: Console changes bypass IaC; CSPM findings not routed to on-call | G13: Org-wide S3 Block Public Access (SCP); encryption by default; Security Hub CIS checks; IaC for most resources | H13: 4 | I13: 5 | J13: =H13*I13 | K13: =IF(J13="","",IF(J13>=20,"Critical",IF(J13>=10,"High",IF(J13>=5,"Moderate","Low")))) | L13: 2 | M13: 5 | N13: =L13*M13 | O13: =IF(N13="","",IF(N13>=20,"Critical",IF(N13>=10,"High",IF(N13>=5,"Moderate","Low")))) | P13: Mitigate | Q13: Route CSPM to on-call; admin-port guardrail; emergency change auto-revert (POAM-012, POAM-018) | R13: Tomasz Wierzbicki (Director, Platform Engineering) | S13: 46276 | T13: 2 | U13: 4 | V13: =T13*U13 | W13: =IF(V13="","",IF(V13>=20,"Critical",IF(V13>=10,"High",IF(V13>=5,"Moderate","Low")))) | X13: Treatment in progress | Y13: CM-2; CM-6; SC-7; SC-28 | Z13: FIND-012 | AA13: POAM-012 | AB13: 46283 | AC13: L4: misconfiguration is a leading cloud breach cause. I5: public PHI exposure. | AD13: L2: strong preventive guardrails for data stores (block public access, encryption). The observed exposure was an admin port, not data. I5: remains the worst credible case. | AE13: L2: CSPM routed to on-call plus SCP guardrails on admin ports. I4: guardrails prevent the most severe (data-store) exposures.
... A18: RISK-017 | B18: Service-account credential theft | C18: A stolen long-lived service credential grants quiet, unmonitored access to PHI extracts. | D18: Non-human accounts with static credentials (SFTP push, reporting ETL, vendor logins) | E18: Credential theft from hosts or repositories; vendor-side compromise | F18: Keys 1.5–3 years old; no owners; a shared vendor login | G18: Secrets Manager rotation for DB credentials; OIDC for CI/CD | H18: 3 | I18: 4 | J18: =H18*I18 | K18: =IF(J18="","",IF(J18>=20,"Critical",IF(J18>=10,"High",IF(J18>=5,"Moderate","Low")))) | L18: 3 | M18: 4 | N18: =L18*M18 | O18: =IF(N18="","",IF(N18>=20,"Critical",IF(N18>=10,"High",IF(N18>=5,"Moderate","Low")))) | P18: Mitigate | Q18: Owners, rotation or federation, and named vendor accounts (POAM-005) | R18: Alicia Moreno (CISO) | S18: 46277 | T18: 1 | U18: 4 | V18: =T18*U18 | W18: =IF(V18="","",IF(V18>=20,"Critical",IF(V18>=10,"High",IF(V18>=5,"Moderate","Low")))) | X18: Treated (residual achieved; monitoring) | Y18: IA-5; AC-2 | Z18: FIND-005 | AA18: POAM-005 | AB18: 46283 | AC18: L3: static keys leak through repositories, hosts, and backups. I4: PHI extract access. | AD18: L3: modern patterns exist, but the legacy exceptions carry the risk. I4. | AE18: L1: federation and rotation with owners and quarterly attestation. I4: a compromised service identity would still reach the same data.
A19: RISK-018 | B19: Loss or theft of an endpoint containing PHI | C19: A lost or stolen laptop exposes PHI stored locally. | D19: About 362 workforce laptops | E19: Theft, loss in transit | F19: Mobile workforce (60% remote) | G19: Full-disk encryption (100%); MDM remote wipe; policy against storing PHI locally, with DLP; EDR | H19: 4 | I19: 3 | J19: =H19*I19 | K19: =IF(J19="","",IF(J19>=20,"Critical",IF(J19>=10,"High",IF(J19>=5,"Moderate","Low")))) | L19: 2 | M19: 2 | N19: =L19*M19 | O19: =IF(N19="","",IF(N19>=20,"Critical",IF(N19>=10,"High",IF(N19>=5,"Moderate","Low")))) | P19: Accept | Q19: None beyond current controls; annual review | R19: Kevin Brandt (IT Manager) | S19: 46583 | T19: 2 | U19: 2 | V19: =T19*U19 | W19: =IF(V19="","",IF(V19>=20,"Critical",IF(V19>=10,"High",IF(V19>=5,"Moderate","Low")))) | X19: Accepted within appetite (Low) | Y19: SC-28; MP-6 | AB19: 46283 | AC19: L4: several devices are lost each year. I3: a local PHI cache could hold under 500 records. | AD19: L2: devices are still lost (INC-2026-0063), but FDE means a lost encrypted device is not a breach of unsecured PHI. I2: exposure is internal-only and non-reportable when encryption is verified. | AE19: Unchanged; within appetite.

Sheet Findings
A1: Finding ID | B1: Title | C1: Severity | D1: Likelihood | E1: Impact | F1: Score | G1: Primary Control | H1: Related Controls | I1: Related Risks | J1: POA&M ID | K1: Source | L1: Related Items (AR-EX / VR / EVID) | M1: Date Identified | N1: Owner | O1: Status | P1: Condition | Q1: Criteria | R1: Cause | S1: Effect | T1: Recommendation | U1: Management Response | V1: Challenge Record
A2: FIND-001 | B2: Terminated workforce retained active access | C2: =IF(F2="","",IF(F2>=20,"Critical",IF(F2>=10,"High",IF(F2>=5,"Moderate","Low")))) | D2: 4 | E2: 4 | F2: =D2*E2 | G2: AC-2(3) | H2: AC-2(3); AC-2; AC-2(1); PS-4; PS-7 | I2: RISK-002 | J2: POAM-001 | K2: Control test + access review | L2: AR-EX-01; AR-EX-02; AR-EX-03; AR-EX-04; VR-007; EVID-003; EVID-004; EVID-007; EVID-078 | M2: 46209 | N2: Nadia Rahman (IAM Engineer) | O2: Closed | P2: 2 of 19 workers terminated in H1 2026 were still enabled in Okta at the 2026-06-30 snapshot, and 1 more was disabled 9 days late. A terminated contractor signed in 4 days after the contract ended (INC-2026-0117). A local AWS IAM user with AdministratorAccess belonging to an employee terminated 2026-03-27 was still active 95 days later. A former employee still had a Quarrystone portal account (local authentication). | Q2: SHCA CSA §3.3 and ACP-002 §5.3 require disabling within 24 hours. HIPAA 164.308(a)(3)(ii)(C) requires termination procedures. The vendor SOC 2 CUEC requires Wrenfield to manage its portal users. | R2: De-provisioning depended on IT manually creating a ticket from an HR email, with no automated HR trigger (AC-2(1)). The offboarding checklist covered only Okta, not local accounts (AWS IAM users, wf-sftp-01, the vendor portal). Contract end dates were not enforced. | S2: Former workers could reach PHI systems (AWS admin) or financial systems (Ledgerline AP) after separation. One post-termination sign-in required a HIPAA breach risk assessment (outcome, low probability of compromise). | T2: Automate HR-driven de-provisioning or daily reconciliation with auto-ticketing. Eliminate or register all local accounts. Set expiry dates on contractor accounts. Add vendor portals to the JML checklist and pursue SSO for them. | U2: Agree. The CISO committed to automated reconciliation by 2026-08-21 and local-account cleanup by 2026-07-10.
A3: FIND-002 | B3: MFA not enforced for all workforce and privileged accounts | C3: =IF(F3="","",IF(F3>=20,"Critical",IF(F3>=10,"High",IF(F3>=5,"Moderate","Low")))) | D3: 4 | E3: 4 | F3: =D3*E3 | G3: IA-2(1) | H3: IA-2(1); IA-2(2) | I3: RISK-003 | J3: POAM-002 | K3: Control test + access review | L3: AR-EX-11; EVID-010; EVID-011; EVID-007; EVID-063; EVID-064 | M3: 46203 | N3: Nadia Rahman (IAM Engineer) | O3: Closed | P3: An Okta policy created in 2023 as a "temporary" workaround exempted the MFA-Exempt-Legacy group (11 accounts, 9 human) from MFA. One member was an Okta Super Administrator. None of the exemptions had approval or an expiry date. In AWS, the IAM user mfeld-admin (AdministratorAccess) had a console password and no MFA. | Q3: SHCA CSA §3.2 requires MFA for all privileged and remote access. HIPAA 164.312(d) requires person or entity authentication. ACP-002 §6.1 limits exceptions to 30 days with CISO approval. | R3: Exceptions were granted by help desk and IT without a workflow, an expiry, or review. Legacy IAM users bypass the Okta policy entirely. | S3: Password-only access to an identity administrator account put every downstream system at risk from a single phished password. This is the exact MFA concern raised in the Lakemont review. | T3: Remove the exemption policy and group. Enroll all members, with accommodation alternatives such as hardware keys. Convert service users to non-interactive integrations. Require phishing-resistant MFA for admin apps. Remove IAM users other than break-glass. Implement a time-bound exception workflow. | U3: Agree. Target 2026-09-05.
A4: FIND-003 | B4: Excessive privileged access and administration from daily-use accounts | C4: =IF(F4="","",IF(F4>=20,"Critical",IF(F4>=10,"High",IF(F4>=5,"Moderate","Low")))) | D4: 3 | E4: 5 | F4: =D4*E4 | G4: AC-6(5) | H4: AC-6(5); AC-6; AC-6(2) | I4: RISK-001 | J4: POAM-003 | K4: Access review | L4: AR-EX-05; AR-EX-06; AR-EX-07; AR-EX-08; AR-EX-09; AR-EX-10; EVID-016; EVID-017; EVID-071; EVID-075; EVID-076; EVID-077 | M4: 46213 | N4: Tomasz Wierzbicki (Director, Platform Engineering) | O4: In Progress | P4: Production AWS AdministratorAccess was held by 2 engineers outside the SRE role, including a 2024 'temporary' migration grant. GitHub had 5 organization owners against an approved maximum of 3. An IT Manager held Okta Super Administrator. A Data Engineer had write access to the PHI primary database. 2 of 3 authorized SRE admins used their email and browsing accounts for production administration, contrary to ACP-002 §5.4. | Q4: AC-6 and AC-6(5) least privilege. ACP-002 §5.4 separate admin accounts. SOC 2 CC6.3 commitment. | R4: Privileged grants have no expiry, and no privileged-access review existed before this assessment. The separate-admin-account policy (2025-07) was never rolled out. | S4: A compromised daily account, which is exposed to phishing and browsing, could immediately act as a production administrator over all PHI. | T4: Remove excess grants. Issue -adm accounts with phishing-resistant MFA. Introduce just-in-time (JIT), approval-gated elevation with automatic expiry for AWS admin. Enforce the GitHub owner cap. | U4: Agree. Engineering initially disputed the Data Engineer's need; resolved with time-boxed elevation. Target 2026-11-05.
A5: FIND-004 | B5: Access recertification incomplete and ineffective (access creep) | C5: =IF(F5="","",IF(F5>=20,"Critical",IF(F5>=10,"High",IF(F5>=5,"Moderate","Low")))) | D5: 3 | E5: 3 | F5: =D5*E5 | G5: AC-6(7) | H5: AC-6(7); AC-2; PS-5 | I5: RISK-004 | J5: POAM-004 | K5: Control test + access review | L5: AR-EX-12; AR-EX-13; AR-EX-14; EVID-008; EVID-009; EVID-044; EVID-074 | M5: 46213 | N5: Alicia Moreno (CISO) | O5: In Progress | P5: Quarterly Okta certifications cover app assignments only. AWS, GitHub, database, and local accounts were never reviewed. In the Q1 campaign, 412 of 412 items were approved and 17 of 23 reviewers finished in under 5 minutes. The campaign approved a duplicate account (rgupta2) and a transferred user's prior-role PHI access, which that user used after the transfer. One user kept production access unused for 240 days. | Q5: SHCA CSA §3.3 requires quarterly privileged recertification. HIPAA 164.308(a)(4)(ii)(C). AC-6(7). PS-5. | R5: Campaign scope is limited to what the Okta certification feature can see. Reviewers get no usage data or risk flags. Transfers do not trigger an access re-baseline. | S5: Access accumulates beyond need, which undermines least privilege and raises insider and compromise impact. | T5: Expand campaigns to all privileged and PHI entitlements across the 9 systems. Give reviewers last-used dates and role-baseline deviations (the review engine output). Require a rationale for approving flagged items. Add a transfer-triggered re-certification. | U5: Agree. The Q3 campaign is being run on the new design; its results are due 2026-09-30.
A6: FIND-005 | B6: Service and shared accounts lack ownership, credential rotation, and individual accountability | C6: =IF(F6="","",IF(F6>=20,"Critical",IF(F6>=10,"High",IF(F6>=5,"Moderate","Low")))) | D6: 3 | E6: 3 | F6: =D6*E6 | G6: IA-5 | H6: IA-5; AC-2 | I6: RISK-017 | J6: POAM-005 | K6: Access review | L6: AR-EX-18; AR-EX-19; AR-EX-20; EVID-013; EVID-065 | M6: 46212 | N6: Nadia Rahman (IAM Engineer) | O6: Closed | P6: Of 13 non-human accounts: 2 had no documented owner (svc-quarrystone-sftp, whose SSH key was 811 days old and which pushes the nightly PHI extract; svc-reporting-etl, an IAM user with a 539-day static access key created by a now-terminated employee). The MDR vendor used a single shared login to the EDR console, so containment actions could not be attributed to individual analysts. | Q6: IA-5 (refresh authenticators; the Wrenfield standard is 365 days). AC-2 (account managers for every account). ACP-002 §4.2 (no shared accounts). | R6: The service-account register had no owner or rotation fields. Vendor access was set up for convenience during MDR onboarding. | S6: Long-lived secrets increase the chance of undetected credential theft, and orphaned accounts are not monitored by anyone. | T6: Assign owners. Rotate or federate credentials (IAM roles, OIDC). Replace the shared vendor login with named federated accounts. Add owner and rotation fields and quarterly attestation to the register. | U6: Agree. Target 2026-09-12.
A7: FIND-006 | B7: Contractor access not bound to engagement term and scope | C7: =IF(F7="","",IF(F7>=20,"Critical",IF(F7>=10,"High",IF(F7>=5,"Moderate","Low")))) | D7: 2 | E7: 4 | F7: =D7*E7 | G7: PS-7 | H7: PS-7; AC-2 | I7: RISK-002; RISK-004 | J7: POAM-006 | K7: Access review | L7: AR-EX-15; AR-EX-16; EVID-045; EVID-066 | M7: 46211 | N7: Sofia Ricci (Engineering Manager) | O7: Closed | P7: One contractor remained active 22 days past the recorded contract end date while working under an extension that had not been documented. The same contractor had PHI production database access that the QA SOW did not require (QA uses staging with synthetic data). | Q7: PS-7 (external personnel requirements and monitoring). ACP-002 §5.3 (contractor end dates enforced). Minimum necessary (HIPAA 164.502(b)). | R7: Contractor end dates were not enforced in Okta, and access requests were not checked against SOW scope. | S7: Contractor access can outlive or exceed the engagement, which increases PHI exposure through third-party personnel. | T7: Set Okta account expiry equal to the SOW end date. Require SOW scope on contractor access requests. Send a monthly contractor roster to sponsors. | U7: Agree. Target 2026-09-10.
A8: FIND-007 | B8: Segregation-of-duties conflict in vendor payment process | C8: =IF(F8="","",IF(F8>=20,"Critical",IF(F8>=10,"High",IF(F8>=5,"Moderate","Low")))) | D8: 2 | E8: 3 | F8: =D8*E8 | G8: AC-5 | H8: AC-5 | I8: RISK-013 | J8: POAM-007 | K8: Access review | L8: AR-EX-17; EVID-014; EVID-015; EVID-060 | M8: 46213 | N8: Laura Brenneman (Controller) | O8: Risk Accepted | P8: The Senior Accountant can both maintain vendor master data (including bank details) and approve payments up to $25,000 (SOD-01). A compensating control, a monthly vendor-master change report reviewed by the Controller, operated 6 of 6 months, but it was never formally documented as a risk decision. | Q8: AC-5. Wrenfield internal-control policy (Board-approved) on payment SoD. | R8: The finance team shrank to three people after the AP Specialist left in 2026-05. Duties were consolidated temporarily. | S8: A single person could create or alter a vendor and approve payment to it, up to $25,000 per transaction. | T8: Formally accept the risk with the compensating control and an expiry date, and redesign roles when the AP role is backfilled. Keep the callback verification of bank-detail changes. | U8: Agree. RACC-001 signed by the CFO (risk owner) with CISO concurrence on 2026-08-12, expiring 2027-03-31.
A9: FIND-008 | B9: Audit log retention below the 12-month contractual requirement | C9: =IF(F9="","",IF(F9>=20,"Critical",IF(F9>=10,"High",IF(F9>=5,"Moderate","Low")))) | D9: 3 | E9: 3 | F9: =D9*E9 | G9: AU-11 | H9: AU-11 | I9: RISK-005 | J9: POAM-008 | K9: Control test | L9: EVID-024; EVID-067 | M9: 46198 | N9: Owen Castillo (Security Engineer) | O9: Closed | P9: CloudTrail logs expired after 180 days. Application audit logs recording PHI access (who viewed which patient) were kept 90 days. SIEM hot retention was 90 days. | Q9: SHCA CSA §4.1 requires 12 months (90 days searchable). HIPAA 164.312(b) audit controls. Customers' breach investigations need historical PHI-access records. | R9: Retention was set in 2022 for cost reasons, before contractual requirements existed, and was never revisited. | S9: If a breach were discovered late, which is common, Wrenfield could not show which patients' records were accessed. That could force broader breach notifications than necessary and would breach the SHCA contract. | T9: Extend retention to 400 days via lifecycle tiering. Archive application audit logs to the log-archive account. Keep 90 days searchable in the SIEM. Add a quarterly oldest-record check. | U9: Agree. Target 2026-09-15.
A10: FIND-009 | B10: Privileged-activity log reviews not consistently performed or documented | C10: =IF(F10="","",IF(F10>=20,"Critical",IF(F10>=10,"High",IF(F10>=5,"Moderate","Low")))) | D10: 3 | E10: 3 | F10: =D10*E10 | G10: AU-6 | H10: AU-6 | I10: RISK-005 | J10: POAM-009 | K10: Control test | L10: EVID-022; EVID-072 | M10: 46199 | N10: Owen Castillo (Security Engineer) | O10: In Progress | P10: The weekly privileged-activity review was performed in 19 of 26 weeks and fully effective in 17 of 26 (65%). Missed weeks coincided with a SIEM migration and reviewer PTO. Two reviews were marked "Reviewed" with flagged items left undispositioned. The review scope excluded local AWS IAM users. | Q10: AU-6. LMS-004 §6 weekly review. HIPAA 164.308(a)(1)(ii)(D) information system activity review. | R10: The review depends on one person with no backup reviewer, no escalation when a week is missed, and a report scope defined before local IAM users were known. | S10: Misuse of privileged access, such as an admin creating a backdoor account, could go unnoticed for weeks. | T10: Name a backup reviewer (the MDR under an SOW change). Auto-create the weekly ticket with escalation after 5 business days. Expand scope to all privileged principals. Require a disposition per flagged item. | U10: Agree. Committed 2026-09-15; the MDR SOW change was delayed in procurement.
A11: FIND-010 | B11: Vulnerability remediation exceeds contractual SLAs | C11: =IF(F11="","",IF(F11>=20,"Critical",IF(F11>=10,"High",IF(F11>=5,"Moderate","Low")))) | D11: 3 | E11: 4 | F11: =D11*E11 | G11: SI-2 | H11: SI-2 | I11: RISK-006 | J11: POAM-010 | K11: Control test | L11: EVID-048; OBS-02; OBS-04 | M11: 46202 | N11: Grace Lindqvist (VP Engineering) | O11: In Progress | P11: 14 of 61 (23%) Critical and High vulnerabilities in H1 exceeded SLA. 6 remained open past SLA at 2026-06-30, including 2 Critical in the notify-worker container (end-of-life Node.js 16 and OpenSSL 1.1.1). 4 of the 6 are on unsupported hosts where no patch exists. No risk exceptions were filed. Engineering asserts the 2 Critical items are unreachable. | Q11: SHCA CSA §7.1 (Critical 15 days, High 30 days). VM-003 §5 SLAs and §7 exception process. | R11: End-of-life runtimes block patching, and the exception process is not used. Remediation work competes with feature work without SLA visibility. 7% of resources are untagged, which delays scan scoping. | S11: Known exploitable weaknesses stay open longer than allowed, which increases the chance of compromise and breaches the contract. | T11: Upgrade the notify-worker runtime. File documented exceptions with reachability analysis where they are justified. Add SLA dashboards to engineering planning. Enforce tag policy. Consider SI-2(7) root-cause analysis (new in Release 5.2.0) for repeat SLA misses. | U11: Partially agree. Engineering disputes the 2 Critical ratings (no network-reachable path) but agrees the exception process must be used. Target 2026-11-05. | V11: Assessor position: exploitability may justify an exception, but only through the documented VM-003 §7 process with evidence (reachability analysis, compensating controls, CISO approval, and an expiry). An assertion in a meeting is not evidence. The determination stands. Management accepted this approach, and an exception request with reachability analysis is milestone M1.
A12: FIND-011 | B12: Unsupported software components in the PHI data path | C12: =IF(F12="","",IF(F12>=20,"Critical",IF(F12>=10,"High",IF(F12>=5,"Moderate","Low")))) | D12: 3 | E12: 4 | F12: =D12*E12 | G12: SA-22 | H12: SA-22 | I12: RISK-007 | J12: POAM-011 | K12: Control test | L12: EVID-052; EVID-048; VR-012 | M12: 46199 | N12: Tomasz Wierzbicki (Director, Platform Engineering) | O12: Delayed | P12: Three components are past vendor or community support: wf-sftp-01 (Windows Server 2012 R2, which pushes the nightly full-PHI extract to Quarrystone and receives 4 customer file drops), legacy-reports (PostgreSQL 11, which holds a PHI extract for monthly outcome reports), and notify-worker (Node.js 16). No SHCA-approved exception exists. | Q12: SHCA CSA §7.4 (supported software only). SA-22. | R12: Legacy integration components were never included in the platform modernization, and there is no lifecycle review of non-IaC assets. | S12: Security flaws in these components will never be patched. They account for 4 of the 6 open past-SLA vulnerabilities. | T12: Avoid the risk: replace wf-sftp-01 with a managed transfer service (encrypted, IaC-managed), migrate legacy-reports to the supported Aurora replica, and upgrade notify-worker. Keep compensating controls until then (EDR, allowlist, weekly scans, SSM-only admin). | U12: Agree. Target 2026-11-05. Milestone 2 (SFTP migration) slipped from 2026-09-15 because 2 of 4 customers had not completed partner-side key exchange. Revised target 2026-12-15, approved by the CTO on 2026-09-12.
A13: FIND-012 | B13: Internet-exposed RDP on legacy host; CSPM alert not triaged | C13: =IF(F13="","",IF(F13>=20,"Critical",IF(F13>=10,"High",IF(F13>=5,"Moderate","Low")))) | D13: 4 | E13: 4 | F13: =D13*E13 | G13: SC-7 | H13: SC-7; CM-6 | I13: RISK-012; RISK-007 | J13: POAM-012 | K13: Control test | L13: EVID-053; EVID-028; EVID-068; EVID-030 | M13: 46205 | N13: Tomasz Wierzbicki (Director, Platform Engineering) | O13: Closed | P13: The security group for wf-sftp-01 allowed RDP (TCP 3389) from 0.0.0.0/0 for 43 days. It was added under emergency change CHG-2026-0412 for a vendor support session, never approved, and never reverted. AWS Security Hub flagged it as High the next day, but no one triaged it. No successful external RDP logons were found (Windows event 4624 logon type 10 reviewed). | Q13: SC-7 boundary protection. CM-6 deviation approval. CMP-006 emergency change rules. The Security Hub triage standard (High within 7 days). | R13: The console change path bypasses IaC and approvals. Security Hub findings were not routed to the SRE on-call queue. | S13: An unsupported Windows server holding PHI extracts was exposed to internet-wide RDP brute-force and exploitation. | T13: Remove the rule (done within 24h). Route Security Hub High findings to on-call with an SLA. Add an SCP or guardrail that blocks 0.0.0.0/0 on admin ports. Tie emergency changes to automatic revert. | U13: Agree. Remediated 2026-07-03 and validated 2026-07-10.
A14: FIND-013 | B14: Backup restoration never tested | C14: =IF(F14="","",IF(F14>=20,"Critical",IF(F14>=10,"High",IF(F14>=5,"Moderate","Low")))) | D14: 2 | E14: 4 | F14: =D14*E14 | G14: CP-9(1) | H14: CP-9(1) | I14: RISK-008 | J14: POAM-013 | K14: Control test | L14: EVID-035; EVID-069 | M14: 46199 | N14: Tomasz Wierzbicki (Director, Platform Engineering) | O14: Closed | P14: Backups are taken, protected, and copied cross-region (CP-9 satisfied), but no restore of the PHI database had ever been performed or documented. Backup job success was treated as proof of recoverability. | Q14: CP-9(1). SHCA CSA §8.1 (tested restoration annually). HIPAA 164.308(a)(7)(ii)(D). | R14: Recovery was assumed rather than tested. There was no scheduled restore exercise in the BC/DR plan. | S14: In a ransomware or corruption event, recovery time and completeness were unknown. RTO and RPO were promises, not demonstrated capabilities. | T14: Perform and document a restore from the DR vault into an isolated account, with timings and integrity checks. Schedule it semi-annually. | U14: Agree. Target 2026-09-01.
A15: FIND-014 | B15: Incident response and contingency plans not tested within 12 months | C15: =IF(F15="","",IF(F15>=20,"Critical",IF(F15>=10,"High",IF(F15>=5,"Moderate","Low")))) | D15: 3 | E15: 3 | F15: =D15*E15 | G15: IR-3 | H15: IR-3; CP-4 | I15: RISK-009; RISK-008 | J15: POAM-014 | K15: Control test | L15: EVID-033; EVID-037; OBS-03 | M15: 46199 | N15: Owen Castillo (Security Engineer) | O15: In Progress | P15: The last IR tabletop was 2024-09-18, 21 months before fieldwork. There has been no plan-level contingency test (only 2024 engineering failover notes). The SHCA 24-hour incident-reporting path and the IR contact roster (2 departed staff) have never been exercised or validated. | Q15: IR-3, CP-4, IRP-005 and BCP-003 (annual testing), SHCA CSA §5.2 and §8.1. | R15: Exercises were deferred twice for delivery priorities, with no escalation. | S15: Roles, decision rights, and notification timelines are untested. Real incidents were handled well (IR-4), but a major ransomware event would test untested paths. | T15: Run a combined ransomware tabletop (IR + CP) including MDR, Legal/Privacy, Customer Ops, and executives. Update IRP-005 with the SHCA 24h step and the current roster. Track after-action items in the POA&M. | U15: Agree. Tabletop scheduled 2026-10-14. Target 2026-11-15.
A16: FIND-015 | B16: Third-party risk monitoring incomplete; no C-SCRM plan | C16: =IF(F16="","",IF(F16>=20,"Critical",IF(F16>=10,"High",IF(F16>=5,"Moderate","Low")))) | D16: 3 | E16: 3 | F16: =D16*E16 | G16: SR-6 | H16: SR-6; SA-9; SR-2 | I16: RISK-011; RISK-010 | J16: POAM-015 | K16: Control test (vendor program) | L16: EVID-049; EVID-059 | M16: 46220 | N16: Beth Kowalski (Vendor Management Lead) | O16: In Progress | P16: 5 of 14 Tier 1–2 vendors (36%) lack a current assessment, including Tier 1 Pulsewire Connect (last 2024-08) and Ironpeak MDR (never assessed after onboarding). No fourth-party (subcontractor) inventory exists. There is no supply chain risk management plan (outline only). 3 older contracts lack breach-notification timelines. | Q16: SA-9, SR-6 (reassess at tier frequency), SR-2, TPRM-007, SHCA CSA §6.3 subcontractor inventory. | R16: Vendor management is one person, part time. Reassessment is spreadsheet-tracked with no reminders, and the program was not resourced as the vendor count grew. | S16: Vendor risks can drift unnoticed, as the Quarrystone offshore access (FIND-016) shows. | T16: Clear the overdue assessments (Tier 1 first). Build a fourth-party inventory from vendor questionnaires. Approve a C-SCRM plan aligned to SP 800-161r1-upd1 and SP 800-18r2. Add contract-renewal triggers. | U16: Agree. Target 2027-02-03 (Moderate SLA), with Tier 1 vendors by 2026-11-30.
A17: FIND-016 | B17: Quarrystone Analytics: offshore PHI access, inadequate breach-notification terms, and excessive data sharing | C17: =IF(F17="","",IF(F17>=20,"Critical",IF(F17>=10,"High",IF(F17>=5,"Moderate","Low")))) | D17: 3 | E17: 5 | F17: =D17*E17 | G17: SA-9 | H17: SA-9; SR-6 | I17: RISK-010 | J17: POAM-016 | K17: Vendor assessment | L17: VR-001; VR-002; VR-003; VR-004; VR-005; VR-008; VR-010; EVID-050; EVID-051; EVID-073 | M17: 46220 | N17: Dr. Miriam Castell (VP Clinical Analytics, business owner) | O17: In Progress | P17: Quarrystone receives a nightly full-PHI extract (about 410k patients). (1) An undisclosed offshore subcontractor (Pune, India) had production access to Wrenfield PHI (VR-001, rated Critical, escalated to the CEO 2026-07-17; interim suspension confirmed 2026-07-24). (2) The BAA allows 30-day breach notice, against Wrenfield's 24h SHCA and 5-business-day customer obligations (VR-002). (3) The extract includes fields not needed for scoring: full address, phone, email, free-text notes (VR-003). Supporting issues: pentest evidence stale, data return undefined, secondary-use ambiguity. | Q17: SHCA CSA §6.1 (US-only) and §6.3 (flow-down). HIPAA 164.502(b) minimum necessary and 164.314(a). 2 customer BAAs prohibit offshore access. SA-9. | R17: The contract was signed in 2023 on the vendor's paper before TPRM-007 existed. The questionnaire relied on self-attestation. Data minimization was never designed into the extract. | S17: Potential breach of 2 current customer BAAs and a blocking condition for SHCA. A breach at the vendor could go unreported to Wrenfield for up to 30 days. | T17: Conditional continuation (Mitigate + Transfer): execute the amendment (US-only access with technical enforcement, 24h notification, subcontractor approval, data return and destruction within 30 days with a certificate, log cooperation). Minimize the extract to scoring-required fields with tokenized identifiers. Obtain a current pentest and retest. Do not send SHCA data until the conditions are met. | U17: Agree. The CEO approved conditional continuation on 2026-07-22. The amendment is in redline v3. Target 2026-11-05.
A18: FIND-017 | B18: System security plan outdated and overstates control implementation | C18: =IF(F18="","",IF(F18>=20,"Critical",IF(F18>=10,"High",IF(F18>=5,"Moderate","Low")))) | D18: 2 | E18: 2 | F18: =D18*E18 | G18: PL-2 | H18: PL-2 | I18: RISK-016 | J18: POAM-017 | K18: Control test | L18: EVID-041; OBS-01 | M18: 46217 | N18: Priya Raman (Security Compliance Manager) | O18: In Progress | P18: SSP v1.3 (2025-02) predates the EKS migration, the log-archive account, and the Quarrystone SFTP flow, and it states a higher implementation status than testing supports for 27 of the 61 in-scope controls. | Q18: PL-2. SHCA CSA §2.1 (current SSP expected with the assessment package). | R18: The SSP was maintained as a SOC 2 narrative, with no update trigger tied to architecture changes. | S18: SHCA and customers would receive an inaccurate description of the system, a credibility and contractual risk rather than a direct technical one. | T18: Rewrite the SSP in control-by-control form using this matrix as the source. Adopt the SP 800-18 Rev. 2 structure. Add architecture-change triggers to the change process. | U18: Agree. Target 2026-12-15.
A19: FIND-018 | B19: Emergency and console changes bypass approval | C19: =IF(F19="","",IF(F19>=20,"Critical",IF(F19>=10,"High",IF(F19>=5,"Moderate","Low")))) | D19: 3 | E19: 3 | F19: =D19*E19 | G19: CM-3 | H19: CM-3 | I19: RISK-014 | J19: POAM-018 | K19: Control test | L19: EVID-030 | M19: 46202 | N19: Tomasz Wierzbicki (Director, Platform Engineering) | O19: In Progress | P19: 3 of 25 sampled changes failed. CHG-2026-0412 (emergency, no approval, never reverted, which caused FIND-012). CHG-2026-0288 (retro approval after 9 business days against a standard of 2). CHG-2026-0356 (deployed 5h38m before approval was recorded). 2 of the 3 emergency changes in the sample failed. | Q19: CM-3. CMP-006 §4.3. SOC 2 CC8.1 commitment. | R19: The code pipeline enforces review, but the console and emergency paths rely on people remembering. No report flags emergency changes awaiting retro approval. | S19: Unreviewed changes can introduce outages or security regressions, as FIND-012 shows. | T19: Auto-open a retro-approval task on every emergency change with a 2-day escalation. Alert on console changes to security groups and IAM (CloudTrail + EventBridge). Require approval before the deploy job runs. | U19: Agree. Committed 2026-09-11. Milestone 1 is done; milestones 2 and 3 are waiting on an SRE backlog slot.
A20: FIND-019 | B20: Security awareness training completion below 100% | C20: =IF(F20="","",IF(F20>=20,"Critical",IF(F20>=10,"High",IF(F20>=5,"Moderate","Low")))) | D20: 2 | E20: 2 | F20: =D20*E20 | G20: AT-2 | H20: AT-2 | I20: RISK-015 | J20: POAM-019 | K20: Control test | L20: EVID-019; EVID-070 | M20: 46199 | N20: Denise Yamamoto (Director of People) | O20: Completed – Pending Validation | P20: 316 of 347 workforce members (91%) completed annual training. 31 were overdue, 4 of them with PHI data-store access. The policy's access-suspension step for users more than 30 days overdue was not enforced. | Q20: AT-2. HIPAA 164.308(a)(5)(i). Training policy HR-011. | R20: Overdue reminders went to users only, with no manager escalation or enforcement. | S20: A small increase in phishing and data-handling risk. Mainly a compliance gap. | T20: Enforce the suspension step via an Okta group rule. Escalate to managers at 14 days. Report completion monthly. | U20: Agree. Enforcement live 2026-08-20; 344 of 347 complete as of 2026-09-12, with 3 on leave.

Sheet POAM
A1: POA&M ID | B1: Related Finding | C1: Related Control | D1: Related Risk | E1: Weakness | F1: Root Cause | G1: Severity | H1: Corrective Action | I1: Milestones | J1: Owner | K1: Resources Required | L1: Open Date | M1: SLA Date | N1: Original Target Date | O1: Current Target Date | P1: Target Change Reason | Q1: Current Status | R1: Percent Complete | S1: Days Open | T1: Overdue? | U1: Slipped? | V1: Target Within SLA? | W1: Dependencies | X1: Validation Method | Y1: Closure Evidence | Z1: Validated By | AA1: Closure Date | AB1: Residual Risk | AC1: Notes
A2: POAM-001 | B2: FIND-001 | C2: AC-2(3); AC-2; AC-2(1); PS-4; PS-7 | D2: RISK-002 | E2: Terminated workforce retained active access (SSO, local AWS IAM, vendor portal) | F2: Manual HR-email-to-IT ticketing with no automated trigger; local accounts not in offboarding checklist; contractor end dates not enforced | G2: High | H2: Disable identified accounts; implement daily HR-to-Okta/AWS/portal reconciliation with auto-ticketing; update SOP-IAM-02 with a local-account checklist and 24h SLA | I2: M1 Disable 4 identified accounts (AR-EX-01..04); investigate post-termination sign-in (INC-2026-0117) (due 2026-07-10; Done) | M2 Deploy daily HR-to-Okta/AWS IAM/portal reconciliation job with auto-ticketing (due 2026-08-21; Done) | M3 Update SOP-IAM-02 (24h SLA, local-account checklist, vendor portals); train IT (due 2026-08-28; Done) | M4 Assessor validation: re-perform termination test on all terminations since 2026-07-01 + 5 job runs (due 2026-09-11; Done) | J2: Nadia Rahman (IAM Engineer) | K2: IAM Engineer (about 60h); Okta Workflows (existing license); HR ops (4h) | L2: 46241 | M2: =L2+IF(G2="Critical",30,IF(G2="High",90,IF(G2="Moderate",180,365))) | N2: 46276 | O2: 46276 | Q2: Closed | R2: =IFERROR(COUNTIFS(Milestones!$A:$A,A2,Milestones!$E:$E,"Done")/COUNTIF(Milestones!$A:$A,A2),0) | S2: =IF(Q2="Closed",AA2-L2,README!$B$4-L2) | T2: =IF(AND(Q2<>"Closed",Q2<>"Risk Accepted",O2<README!$B$4),"Yes","No") | U2: =IF(O2<>N2,"Yes","No") | V2: =IF(Q2="Risk Accepted","n/a (acceptance expiry)",IF(O2<=M2,"Yes","No")) | W2: Okta Workflows connector to PeopleHub | X2: Re-performance: tools/assessment_tests.py termination-validation (7 of 7 within 24h, 0 job exceptions); inspection of IAM credential report (break-glass only) | Y2: EVID-061; EVID-062; EVID-064; EVID-078 | Z2: Lead assessor | AA2: 46275 | AB2: Moderate (RISK-002 residual L2 x I4 = 8) | AC2: Operating sample is small (7); full re-test scheduled for FY27.
A3: POAM-002 | B3: FIND-002 | C3: IA-2(1); IA-2(2) | D3: RISK-003 | E3: MFA exemption group and AWS IAM user without MFA | F3: Exceptions granted without workflow, expiry, or review; legacy IAM users bypass Okta policy | G3: High | H3: Delete exemption policy and group; enroll all members (hardware key accommodation); convert service users to integrations; require phishing-resistant MFA for admin apps; delete non-break-glass IAM users; add time-bound exception workflow | I3: M1 Enroll 9 human members in MFA (accommodation for 1) (due 2026-08-28; Done) | M2 Convert svc-vulnscan and svc-confroom to non-interactive integrations (due 2026-08-28; Done) | M3 Delete Legacy Exemption Policy and group; phishing-resistant policy on admin apps (CHG-2026-0731) (due 2026-09-01; Done) | M4 Assessor validation: policy export, group lookup, password-only sign-in attempt, IAM credential report (due 2026-09-05; Done) | J3: Nadia Rahman (IAM Engineer) | K3: IAM Engineer (about 30h); 12 FIDO2 keys (about $600) | L3: 46241 | M3: =L3+IF(G3="Critical",30,IF(G3="High",90,IF(G3="Moderate",180,365))) | N3: 46270 | O3: 46270 | Q3: Closed | R3: =IFERROR(COUNTIFS(Milestones!$A:$A,A3,Milestones!$E:$E,"Done")/COUNTIF(Milestones!$A:$A,A3),0) | S3: =IF(Q3="Closed",AA3-L3,README!$B$4-L3) | T3: =IF(AND(Q3<>"Closed",Q3<>"Risk Accepted",O3<README!$B$4),"Yes","No") | U3: =IF(O3<>N3,"Yes","No") | V3: =IF(Q3="Risk Accepted","n/a (acceptance expiry)",IF(O3<=M3,"Yes","No")) | W3: Hardware key delivery for accessibility accommodation | X3: Inspection of Okta policy export and IAM credential report; re-performance of password-only sign-in with a test account (denied) | Y3: EVID-063; EVID-064 | Z3: Lead assessor | AA3: 46270 | AB3: Moderate (RISK-003 residual L2 x I4 = 8)
A4: POAM-003 | B4: FIND-003 | C4: AC-6(5); AC-6; AC-6(2) | D4: RISK-001 | E4: Excessive privileged access; administration from daily-use accounts | F4: Privileged grants without expiry; no privileged-access review before 2026; separate-admin policy never rolled out | G4: High | H4: Remove excess grants; issue -adm accounts with phishing-resistant MFA; implement approval-gated JIT elevation for AWS admin; enforce GitHub owner cap | I4: M1 Remove excess grants: AR-EX-05/06/07/08/09 (due 2026-08-21; Done) | M2 Issue -adm accounts for remaining admins; remove admin from daily accounts (AR-EX-10) (due 2026-09-30; In Progress) | M3 Implement JIT elevation (approval + 4h auto-expiry) for AWS AdministratorAccess (due 2026-10-23; In Progress) | M4 Assessor validation: assignment export + live elevation record with CloudTrail evidence (due 2026-11-05; Not Started) | J4: Tomasz Wierzbicki (Director, Platform Engineering) | K4: SRE (about 80h); IAM Engineer (about 20h) | L4: 46241 | M4: =L4+IF(G4="Critical",30,IF(G4="High",90,IF(G4="Moderate",180,365))) | N4: 46331 | O4: 46331 | Q4: In Progress | R4: =IFERROR(COUNTIFS(Milestones!$A:$A,A4,Milestones!$E:$E,"Done")/COUNTIF(Milestones!$A:$A,A4),0) | S4: =IF(Q4="Closed",AA4-L4,README!$B$4-L4) | T4: =IF(AND(Q4<>"Closed",Q4<>"Risk Accepted",O4<README!$B$4),"Yes","No") | U4: =IF(O4<>N4,"Yes","No") | V4: =IF(Q4="Risk Accepted","n/a (acceptance expiry)",IF(O4<=M4,"Yes","No")) | W4: IAM Identity Center permission-set redesign; EVID-071 returned as Rework Required (design-only evidence) | X4: Inspection of Identity Center/GitHub/Okta admin exports; re-performance: request and observe a JIT elevation, confirm auto-expiry in CloudTrail | Y4: EVID-075; EVID-076; EVID-077; EVID-071 | AB4: Moderate target (RISK-001 residual L2 x I4 = 8); currently High | AC4: Evidence EVID-071 rejected: a screenshot of an approval screen shows the design, not that elevation operates.
A5: POAM-004 | B5: FIND-004 | C5: AC-6(7); AC-2; PS-5 | D5: RISK-004 | E5: Access recertification incomplete in scope and ineffective in operation | F5: Campaign scope limited to Okta app assignments; no usage data or risk flags for reviewers; no transfer trigger | G5: Moderate | H5: Redesign certification to cover all privileged and PHI entitlements on 9 systems with usage and baseline flags; require rationale for approving flagged items; transfer-triggered re-certification | I5: M1 Revoke duplicate, transferred, and inactive access (AR-EX-12/13/14) (due 2026-07-17; Done) | M2 Add transfer trigger to SOP-IAM-02 (re-baseline access within 5 business days) (due 2026-08-28; Done) | M3 Run Q3 privileged certification on new design (EVID-074) (due 2026-09-30; In Progress) | M4 Assessor validation: review Q3 campaign decisions for flagged items and rationale quality (due 2026-10-31; Not Started) | J5: Alicia Moreno (CISO) | K5: GRC Manager (about 40h); IAM Engineer (about 30h); review_engine.py reused as the flagging logic | L5: 46241 | M5: =L5+IF(G5="Critical",30,IF(G5="High",90,IF(G5="Moderate",180,365))) | N5: 46326 | O5: 46326 | Q5: In Progress | R5: =IFERROR(COUNTIFS(Milestones!$A:$A,A5,Milestones!$E:$E,"Done")/COUNTIF(Milestones!$A:$A,A5),0) | S5: =IF(Q5="Closed",AA5-L5,README!$B$4-L5) | T5: =IF(AND(Q5<>"Closed",Q5<>"Risk Accepted",O5<README!$B$4),"Yes","No") | U5: =IF(O5<>N5,"Yes","No") | V5: =IF(Q5="Risk Accepted","n/a (acceptance expiry)",IF(O5<=M5,"Yes","No")) | W5: Q3 campaign completion by reviewers | X5: Inspection of campaign export (population completeness vs entitlement exports; % flagged items with rationale; removals actioned) | Y5: EVID-061; EVID-074 | AB5: Moderate (RISK-004 residual L2 x I3 = 6)
A6: POAM-005 | B6: FIND-005 | C6: IA-5; AC-2 | D6: RISK-017 | E6: Service/shared accounts without owners, stale credentials, shared vendor login | F6: Service register lacked owner/rotation fields; vendor access set up for convenience | G6: Moderate | H6: Assign owners; rotate or federate stale credentials; named federated accounts for MDR analysts; add owner/rotation fields and quarterly attestation to the register | I6: M1 Assign owners to all 13 non-human accounts; add fields to register (due 2026-08-21; Done) | M2 Rotate svc-quarrystone-sftp key (AR-EX-18) (due 2026-08-28; Done) | M3 Replace ironpeak-soc shared login with 6 named federated accounts (AR-EX-20) (due 2026-09-04; Done) | M4 Migrate svc-reporting-etl to IAM role; delete IAM user (AR-EX-19) (due 2026-09-11; Done) | M5 Assessor validation: register re-test (owner + credential age) and IAM credential report (due 2026-09-12; Done) | J6: Nadia Rahman (IAM Engineer) | K6: IAM Engineer (about 20h); SRE (about 16h) | L6: 46241 | M6: =L6+IF(G6="Critical",30,IF(G6="High",90,IF(G6="Moderate",180,365))) | N6: 46277 | O6: 46277 | Q6: Closed | R6: =IFERROR(COUNTIFS(Milestones!$A:$A,A6,Milestones!$E:$E,"Done")/COUNTIF(Milestones!$A:$A,A6),0) | S6: =IF(Q6="Closed",AA6-L6,README!$B$4-L6) | T6: =IF(AND(Q6<>"Closed",Q6<>"Risk Accepted",O6<README!$B$4),"Yes","No") | U6: =IF(O6<>N6,"Yes","No") | V6: =IF(Q6="Risk Accepted","n/a (acceptance expiry)",IF(O6<=M6,"Yes","No")) | W6: Ironpeak MDR SSO onboarding | X6: Re-performance of the review engine's service-account checks on the updated register; inspection of EDR console user list (no shared logins) | Y6: EVID-065; EVID-064 | Z6: Lead assessor | AA6: 46277 | AB6: Low (RISK-017 residual L1 x I4 = 4)
A7: POAM-006 | B7: FIND-006 | C7: PS-7; AC-2 | D7: RISK-002; RISK-004 | E7: Contractor access not bound to engagement term and scope | F7: Contract end dates not enforced in Okta; access requests not checked against SOW scope | G7: Moderate | H7: Okta account expiry = SOW end date for all contractors; SOW scope required on contractor access requests; monthly contractor roster to sponsors | I7: M1 Execute SOW amendment for awu; revoke out-of-scope PHI access (AR-EX-15/16) (due 2026-07-24; Done) | M2 Set Okta expiry for all contractor accounts; add SOW-scope field to access request form (due 2026-08-28; Done) | M3 Assessor validation: expiry report vs SOW register (due 2026-09-10; Done) | J7: Sofia Ricci (Engineering Manager) | K7: IAM Engineer (about 8h); Vendor Mgmt (about 4h) | L7: 46241 | M7: =L7+IF(G7="Critical",30,IF(G7="High",90,IF(G7="Moderate",180,365))) | N7: 46275 | O7: 46275 | Q7: Closed | R7: =IFERROR(COUNTIFS(Milestones!$A:$A,A7,Milestones!$E:$E,"Done")/COUNTIF(Milestones!$A:$A,A7),0) | S7: =IF(Q7="Closed",AA7-L7,README!$B$4-L7) | T7: =IF(AND(Q7<>"Closed",Q7<>"Risk Accepted",O7<README!$B$4),"Yes","No") | U7: =IF(O7<>N7,"Yes","No") | V7: =IF(Q7="Risk Accepted","n/a (acceptance expiry)",IF(O7<=M7,"Yes","No")) | X7: Inspection: Okta expiry dates reconciled to SOW register for all active contractors (29 of 29) | Y7: EVID-066 | Z7: Lead assessor | AA7: 46275 | AB7: Moderate (RISK-002 residual)
A8: POAM-007 | B8: FIND-007 | C8: AC-5 | D8: RISK-013 | E8: SoD conflict (vendor master + payment approval) | F8: Finance team reduced to 3 after AP departure | G8: Moderate | H8: Formal risk acceptance (RACC-001) with compensating monthly independent review; split roles when AP role is backfilled | I8: M1 Sign RACC-001 (CFO as risk owner; CISO concurrence) (due 2026-08-14; Done) | M2 Continue monthly compensating review (evidence each month to GRC) (due 2027-03-31; In Progress) | M3 Split roles at AP backfill (requisition open) (due 2027-03-31; Not Started) | J8: Laura Brenneman (Controller) | K8: Controller (2h/month for compensating review) | L8: 46241 | M8: =L8+IF(G8="Critical",30,IF(G8="High",90,IF(G8="Moderate",180,365))) | N8: 46477 | O8: 46477 | Q8: Risk Accepted | R8: =IFERROR(COUNTIFS(Milestones!$A:$A,A8,Milestones!$E:$E,"Done")/COUNTIF(Milestones!$A:$A,A8),0) | S8: =IF(Q8="Closed",AA8-L8,README!$B$4-L8) | T8: =IF(AND(Q8<>"Closed",Q8<>"Risk Accepted",O8<README!$B$4),"Yes","No") | U8: =IF(O8<>N8,"Yes","No") | V8: =IF(Q8="Risk Accepted","n/a (acceptance expiry)",IF(O8<=M8,"Yes","No")) | W8: AP Specialist hire | X8: Monthly: GRC inspects signed vendor-master change report; at expiry: re-test role assignments | Y8: EVID-060; EVID-015 | AB8: Moderate, accepted (RISK-013 residual L2 x I3 = 6) | AC8: Accepted risks stay on the POA&M until expiry so they are re-decided, not forgotten.
A9: POAM-008 | B9: FIND-008 | C9: AU-11 | D9: RISK-005 | E9: Audit log retention below 12-month requirement | F9: 2022 cost-driven retention settings never revisited after contractual requirements emerged | G9: Moderate | H9: 400-day lifecycle with tiering (hot 90d searchable); archive application audit logs to log-archive; quarterly oldest-record check | I9: M1 Change S3 lifecycle to 400-day expiry with Glacier IR after 90d (CHG-2026-0702) (due 2026-08-21; Done) | M2 Subscribe app-audit CloudWatch logs to log-archive (Firehose) (due 2026-08-28; Done) | M3 Assessor validation: config inspection + oldest-object query (due 2026-09-15; Done) | J9: Owen Castillo (Security Engineer) | K9: Security Engineer (about 16h); storage cost about $180/month | L9: 46241 | M9: =L9+IF(G9="Critical",30,IF(G9="High",90,IF(G9="Moderate",180,365))) | N9: 46280 | O9: 46280 | Q9: Closed | R9: =IFERROR(COUNTIFS(Milestones!$A:$A,A9,Milestones!$E:$E,"Done")/COUNTIF(Milestones!$A:$A,A9),0) | S9: =IF(Q9="Closed",AA9-L9,README!$B$4-L9) | T9: =IF(AND(Q9<>"Closed",Q9<>"Risk Accepted",O9<README!$B$4),"Yes","No") | U9: =IF(O9<>N9,"Yes","No") | V9: =IF(Q9="Risk Accepted","n/a (acceptance expiry)",IF(O9<=M9,"Yes","No")) | X9: Inspection of lifecycle/subscription config; test: oldest CloudTrail object (2026-03-20, 182 days) still present after old 180-day rule would have expired it | Y9: EVID-067 | Z9: Lead assessor | AA9: 46280 | AB9: Moderate (RISK-005 residual after POAM-009) | AC9: Full 12-month retention can only be demonstrated over time; FY27 assessment re-tests.
A10: POAM-009 | B10: FIND-009 | C10: AU-6 | D10: RISK-005 | E10: Weekly privileged-activity review missed 7 of 26 weeks; 2 incomplete | F10: Single reviewer; no escalation; scope excluded local IAM users | G10: Moderate | H10: Backup reviewer (MDR under SOW change); auto-created weekly ticket with 5-day escalation; expand scope to all privileged principals; disposition required per flag | I10: M1 Expand SIEM report scope to all privileged principals incl. IAM users (due 2026-08-21; Done) | M2 Auto-create weekly review ticket with escalation to CISO at 5 business days (due 2026-08-28; Done) | M3 Execute MDR SOW change for backup reviewer (due 2026-09-11; Delayed) | M4 Assessor validation: W27–W37 reviews (EVID-072) (due 2026-09-15; Not Started) | J10: Owen Castillo (Security Engineer) | K10: MDR SOW change (about $1,500/month); Security Engineer (about 12h) | L10: 46241 | M10: =L10+IF(G10="Critical",30,IF(G10="High",90,IF(G10="Moderate",180,365))) | N10: 46280 | O10: 46280 | Q10: In Progress | R10: =IFERROR(COUNTIFS(Milestones!$A:$A,A10,Milestones!$E:$E,"Done")/COUNTIF(Milestones!$A:$A,A10),0) | S10: =IF(Q10="Closed",AA10-L10,README!$B$4-L10) | T10: =IF(AND(Q10<>"Closed",Q10<>"Risk Accepted",O10<README!$B$4),"Yes","No") | U10: =IF(O10<>N10,"Yes","No") | V10: =IF(Q10="Risk Accepted","n/a (acceptance expiry)",IF(O10<=M10,"Yes","No")) | W10: Procurement approval of MDR SOW change (pending CFO signature) | X10: Test: all weeks since change performed within 5 days with dispositions; inspect escalation config | Y10: EVID-072 | AB10: Moderate (RISK-005 residual L2 x I3 = 6) | AC10: Overdue since 2026-09-15; escalated to CISO 2026-09-16.
A11: POAM-010 | B11: FIND-010 | C11: SI-2 | D11: RISK-006 | E11: 23% of Critical/High vulnerabilities exceeded SLA; exception process unused | F11: End-of-life runtimes block patching; no exception discipline; SLA not visible in engineering planning; 7% untagged assets | G11: High | H11: Upgrade notify-worker runtime; file exceptions with reachability analysis where justified; SLA dashboard in sprint planning; tag-policy SCP | I11: M1 Submit VM-003 §7 exception for 2 notify-worker criticals with reachability analysis (CISO decision) (due 2026-08-21; Done) | M2 Upgrade notify-worker to supported Node.js LTS + current base image (due 2026-09-30; In Progress) | M3 SLA-breach dashboard reviewed in weekly engineering leads meeting (due 2026-09-15; Done) | M4 Tag-policy SCP denying untagged EC2/EKS launches (OBS-02) (due 2026-10-15; Not Started) | M5 Assessor validation: re-run SLA test on Q3 population (due 2026-11-05; Not Started) | J11: Grace Lindqvist (VP Engineering) | K11: Engineering (about 3 sprint-weeks); Security Engineer (about 16h) | L11: 46241 | M11: =L11+IF(G11="Critical",30,IF(G11="High",90,IF(G11="Moderate",180,365))) | N11: 46331 | O11: 46331 | Q11: In Progress | R11: =IFERROR(COUNTIFS(Milestones!$A:$A,A11,Milestones!$E:$E,"Done")/COUNTIF(Milestones!$A:$A,A11),0) | S11: =IF(Q11="Closed",AA11-L11,README!$B$4-L11) | T11: =IF(AND(Q11<>"Closed",Q11<>"Risk Accepted",O11<README!$B$4),"Yes","No") | U11: =IF(O11<>N11,"Yes","No") | V11: =IF(Q11="Risk Accepted","n/a (acceptance expiry)",IF(O11<=M11,"Yes","No")) | W11: FIND-011 (4 open breaches resolve only when legacy hosts are decommissioned) | X11: Re-performance: tools/assessment_tests.py vulnsla on Q3 export (target: >= 95% within SLA, 0 open Critical past SLA without exception) | AB11: Moderate (RISK-006 residual L2 x I4 = 8) | AC11: CISO approved a 30-day exception for the 2 criticals (expires 2026-09-30) contingent on M2; consider SI-2(7) root cause analysis (OBS-04).
A12: POAM-011 | B12: FIND-011 | C12: SA-22 | D12: RISK-007 | E12: Unsupported components (Windows 2012 R2 SFTP host, PostgreSQL 11, Node.js 16) in PHI path | F12: Legacy integrations excluded from modernization; no lifecycle review for non-IaC assets | G12: High | H12: Avoid: replace wf-sftp-01 with managed transfer (IaC, PGP + SFTP, vendor/customer keys); migrate legacy-reports to supported Aurora replica; upgrade notify-worker (with POAM-010); maintain compensating controls until then | I12: M1 Stand up managed transfer service (IaC) and test with Quarrystone (due 2026-08-28; Done) | M2 Cut over Quarrystone + 4 customers; decommission wf-sftp-01 (due 2026-09-15; Delayed) | M3 Migrate legacy-reports to Aurora read replica; decommission EC2 host (due 2026-10-30; In Progress) | M4 Assessor validation: inventory shows 0 unsupported components; hosts terminated (due 2026-12-15; Not Started) | J12: Tomasz Wierzbicki (Director, Platform Engineering) | K12: SRE (about 120h); Customer Ops coordination with 4 customers + Quarrystone; managed transfer service about $400/month | L12: 46241 | M12: =L12+IF(G12="Critical",30,IF(G12="High",90,IF(G12="Moderate",180,365))) | N12: 46331 | O12: 46371 | P12: M2 slipped: 2 of 4 customers have not completed partner key exchange. SLA extension approved by CTO and CISO 2026-09-12 with compensating controls (EDR, allowlist, SSM-only admin, weekly scans); still ahead of SHCA go-live 2027-01-11. | Q12: Delayed | R12: =IFERROR(COUNTIFS(Milestones!$A:$A,A12,Milestones!$E:$E,"Done")/COUNTIF(Milestones!$A:$A,A12),0) | S12: =IF(Q12="Closed",AA12-L12,README!$B$4-L12) | T12: =IF(AND(Q12<>"Closed",Q12<>"Risk Accepted",O12<README!$B$4),"Yes","No") | U12: =IF(O12<>N12,"Yes","No") | V12: =IF(Q12="Risk Accepted","n/a (acceptance expiry)",IF(O12<=M12,"Yes","No")) | W12: Customer partner-side key exchange (2 of 4 pending); POAM-010 M2 for notify-worker | X12: Inspection of EOL inventory and AWS Config (instances terminated); re-run vulnsla to confirm legacy-host findings closed | AB12: Low target (RISK-007 residual L1 x I4 = 4); currently High | AC12: Treatment is Avoid (decommission) rather than patching, which is not possible.
A13: POAM-012 | B13: FIND-012 | C13: SC-7; CM-6 | D13: RISK-012; RISK-007 | E13: RDP open to 0.0.0.0/0 on wf-sftp-01; CSPM High finding untriaged 43 days | F13: Console change path bypasses IaC/approval; Security Hub findings not routed to on-call | G13: High | H13: Remove rule; route Security Hub High findings to on-call with 7-day SLA; SCP guardrail blocking 0.0.0.0/0 on admin ports | I13: M1 Remove 3389 ingress rule; confirm SSM-only admin (CHG-2026-0521); review Windows 4624 type-10 logons (due 2026-07-03; Done) | M2 Route Security Hub High findings to SRE on-call queue (due 2026-07-08; Done) | M3 Deploy SCP guardrail for admin ports from 0.0.0.0/0 (due 2026-07-10; Done) | M4 Assessor validation: SG export, Security Hub PASSED, guardrail test (due 2026-07-10; Done) | J13: Tomasz Wierzbicki (Director, Platform Engineering) | K13: SRE (about 12h) | L13: 46205 | M13: =L13+IF(G13="Critical",30,IF(G13="High",90,IF(G13="Moderate",180,365))) | N13: 46213 | O13: 46213 | Q13: Closed | R13: =IFERROR(COUNTIFS(Milestones!$A:$A,A13,Milestones!$E:$E,"Done")/COUNTIF(Milestones!$A:$A,A13),0) | S13: =IF(Q13="Closed",AA13-L13,README!$B$4-L13) | T13: =IF(AND(Q13<>"Closed",Q13<>"Risk Accepted",O13<README!$B$4),"Yes","No") | U13: =IF(O13<>N13,"Yes","No") | V13: =IF(Q13="Risk Accepted","n/a (acceptance expiry)",IF(O13<=M13,"Yes","No")) | X13: Inspection of SG and Security Hub status; re-performance: attempted to add 0.0.0.0/0:3389 rule in a sandbox OU account (denied by SCP) | Y13: EVID-068; EVID-053 | Z13: Lead assessor | AA13: 46213 | AB13: Moderate (RISK-012 residual L2 x I4 = 8) | AC13: Remediated during fieldwork. Still reported as a finding because the control failed during the period.
A14: POAM-013 | B14: FIND-013 | C14: CP-9(1) | D14: RISK-008 | E14: Backup restoration never tested | F14: Recoverability assumed from job success; no scheduled restore test | G14: Moderate | H14: Documented restore from DR vault into isolated account with timing and integrity checks; semi-annual schedule in BCP-003 | I14: M1 Write restore runbook and integrity-check queries (due 2026-08-21; Done) | M2 Perform restore test (assessor observes) (due 2026-08-28; Done) | M3 Add semi-annual restore test to BCP-003 calendar; assessor validation (due 2026-09-01; Done) | J14: Tomasz Wierzbicki (Director, Platform Engineering) | K14: SRE (about 16h); isolated recovery account | L14: 46241 | M14: =L14+IF(G14="Critical",30,IF(G14="High",90,IF(G14="Moderate",180,365))) | N14: 46266 | O14: 46266 | Q14: Closed | R14: =IFERROR(COUNTIFS(Milestones!$A:$A,A14,Milestones!$E:$E,"Done")/COUNTIF(Milestones!$A:$A,A14),0) | S14: =IF(Q14="Closed",AA14-L14,README!$B$4-L14) | T14: =IF(AND(Q14<>"Closed",Q14<>"Risk Accepted",O14<README!$B$4),"Yes","No") | U14: =IF(O14<>N14,"Yes","No") | V14: =IF(Q14="Risk Accepted","n/a (acceptance expiry)",IF(O14<=M14,"Yes","No")) | X14: Observation of restore test; inspection of timings vs RTO/RPO and integrity check output | Y14: EVID-069 | Z14: Lead assessor | AA14: 46266 | AB14: Moderate (RISK-008 residual L2 x I4 = 8, pending POAM-014)
A15: POAM-014 | B15: FIND-014 | C15: IR-3; CP-4 | D15: RISK-009; RISK-008 | E15: IR and contingency plans not tested in 12+ months; SHCA 24h path unrehearsed | F15: Exercises deferred twice without escalation | G15: Moderate | H15: Combined ransomware tabletop (IR + CP) with MDR, Legal/Privacy, Customer Ops, execs; update IRP-005 (SHCA 24h step, roster); track after-action items | I15: M1 Update IRP-005: SHCA 24h notification step + current roster (OBS-03) (due 2026-09-15; Done) | M2 Conduct ransomware tabletop (IR + CP) (due 2026-10-14; Not Started) | M3 Publish after-action report; add corrective actions to POA&M (due 2026-10-30; Not Started) | M4 Assessor validation (due 2026-11-15; Not Started) | J15: Owen Castillo (Security Engineer) | K15: Facilitator (MDR-provided, in contract); 3h of 12 participants | L15: 46241 | M15: =L15+IF(G15="Critical",30,IF(G15="High",90,IF(G15="Moderate",180,365))) | N15: 46341 | O15: 46341 | Q15: In Progress | R15: =IFERROR(COUNTIFS(Milestones!$A:$A,A15,Milestones!$E:$E,"Done")/COUNTIF(Milestones!$A:$A,A15),0) | S15: =IF(Q15="Closed",AA15-L15,README!$B$4-L15) | T15: =IF(AND(Q15<>"Closed",Q15<>"Risk Accepted",O15<README!$B$4),"Yes","No") | U15: =IF(O15<>N15,"Yes","No") | V15: =IF(Q15="Risk Accepted","n/a (acceptance expiry)",IF(O15<=M15,"Yes","No")) | W15: Executive calendar availability | X15: Inspection of exercise materials, attendance, after-action report; verify corrective actions are tracked | AB15: Moderate (RISK-009 residual L2 x I3 = 6)
A16: POAM-015 | B16: FIND-015 | C16: SR-6; SA-9; SR-2 | D16: RISK-011; RISK-010 | E16: 5 of 14 Tier 1–2 vendors overdue; no fourth-party inventory; no C-SCRM plan | F16: Under-resourced vendor program; spreadsheet tracking without reminders | G16: Moderate | H16: Clear overdue assessments (Tier 1 first); build fourth-party inventory; approve C-SCRM plan aligned to SP 800-161r1-upd1 / SP 800-18r2; renewal triggers | I16: M1 Assess Tier 1 overdue vendors (Pulsewire, Ironpeak) (due 2026-11-30; In Progress) | M2 Fourth-party inventory from updated questionnaires (all Tier 1) (due 2026-12-15; Not Started) | M3 Approve C-SCRM plan (due 2027-01-15; Not Started) | M4 Assess remaining Tier 2 overdue vendors; assessor validation (due 2027-02-03; Not Started) | J16: Beth Kowalski (Vendor Management Lead) | K16: Vendor Mgmt (about 0.5 FTE for 4 months); GRC Manager support | L16: 46241 | M16: =L16+IF(G16="Critical",30,IF(G16="High",90,IF(G16="Moderate",180,365))) | N16: 46421 | O16: 46421 | Q16: In Progress | R16: =IFERROR(COUNTIFS(Milestones!$A:$A,A16,Milestones!$E:$E,"Done")/COUNTIF(Milestones!$A:$A,A16),0) | S16: =IF(Q16="Closed",AA16-L16,README!$B$4-L16) | T16: =IF(AND(Q16<>"Closed",Q16<>"Risk Accepted",O16<README!$B$4),"Yes","No") | U16: =IF(O16<>N16,"Yes","No") | V16: =IF(Q16="Risk Accepted","n/a (acceptance expiry)",IF(O16<=M16,"Yes","No")) | W16: Vendor responsiveness | X16: Inspection of vendor register (100% Tier 1–2 within frequency) and approved C-SCRM plan | AB16: Moderate (RISK-011 residual L2 x I4 = 8)
A17: POAM-016 | B17: FIND-016 | C17: SA-9; SR-6 | D17: RISK-010 | E17: Quarrystone: offshore PHI access, 30-day breach notice, excessive data fields, stale pentest | F17: 2023 contract on vendor paper before TPRM-007; self-attestation relied on; extract not designed for minimum necessary | G17: High | H17: Contract amendment (US-only + technical enforcement, 24h notice, subcontractor approval, data return/destruction 30 days with certificate, log cooperation); minimize extract to scoring-required fields with tokenized IDs; obtain current pentest + retest; SHCA data blocked until conditions met | I17: M1 Interim: vendor suspends offshore access to Wrenfield data (letter) (due 2026-07-24; Done) | M2 Execute contract amendment (redline v3 in negotiation) (due 2026-09-30; In Progress) | M3 Deploy minimized, tokenized extract (drop address, phone, email, free text) (due 2026-10-16; In Progress) | M4 Receive current pentest report + retest letter (EVID-051) (due 2026-10-30; Not Started) | M5 Assessor validation + vendor risk re-score (due 2026-11-05; Not Started) | J17: Dr. Miriam Castell (VP Clinical Analytics) | K17: General Counsel (about 20h); Data Engineering (about 60h for extract redesign); Vendor Mgmt | L17: 46241 | M17: =L17+IF(G17="Critical",30,IF(G17="High",90,IF(G17="Moderate",180,365))) | N17: 46331 | O17: 46331 | Q17: In Progress | R17: =IFERROR(COUNTIFS(Milestones!$A:$A,A17,Milestones!$E:$E,"Done")/COUNTIF(Milestones!$A:$A,A17),0) | S17: =IF(Q17="Closed",AA17-L17,README!$B$4-L17) | T17: =IF(AND(Q17<>"Closed",Q17<>"Risk Accepted",O17<README!$B$4),"Yes","No") | U17: =IF(O17<>N17,"Yes","No") | V17: =IF(Q17="Risk Accepted","n/a (acceptance expiry)",IF(O17<=M17,"Yes","No")) | W17: Vendor negotiation; Quarrystone model retraining on minimized fields | X17: Inspection of executed amendment; test: sample extract file schema vs approved minimum field list; inspection of pentest/retest; vendor attestation of US-only access with access-log sample | Y17: EVID-073; EVID-051 | AB17: Moderate target (RISK-010 residual L2 x I4 = 8); currently High | AC17: VR-001 (Critical) escalated to CEO 2026-07-17 per risk appetite; CEO approved conditional continuation 2026-07-22.
A18: POAM-017 | B18: FIND-017 | C18: PL-2 | D18: RISK-016 | E18: SSP outdated; overstates implementation of 27 of 61 controls | F18: SSP maintained as SOC 2 narrative; no update trigger on architecture change | G18: Low | H18: Rewrite SSP control-by-control from the validated matrix (SP 800-18 Rev. 2 structure); add architecture-change trigger in CMP-006 | I18: M1 SSP outline on SP 800-18r2 structure; boundary + data flows updated (due 2026-09-30; In Progress) | M2 Control implementation statements (61 controls) reviewed by owners (due 2026-11-30; Not Started) | M3 Approval by CTO (system owner); assessor validation (due 2026-12-15; Not Started) | J18: Priya Raman (Security Compliance Manager) | K18: GRC Manager (about 80h); control owner reviews | L18: 46241 | M18: =L18+IF(G18="Critical",30,IF(G18="High",90,IF(G18="Moderate",180,365))) | N18: 46371 | O18: 46371 | Q18: In Progress | R18: =IFERROR(COUNTIFS(Milestones!$A:$A,A18,Milestones!$E:$E,"Done")/COUNTIF(Milestones!$A:$A,A18),0) | S18: =IF(Q18="Closed",AA18-L18,README!$B$4-L18) | T18: =IF(AND(Q18<>"Closed",Q18<>"Risk Accepted",O18<README!$B$4),"Yes","No") | U18: =IF(O18<>N18,"Yes","No") | V18: =IF(Q18="Risk Accepted","n/a (acceptance expiry)",IF(O18<=M18,"Yes","No")) | W18: Control owners' review time | X18: Inspection: SSP statements traced to matrix determinations (sample 15 controls) | AB18: Low (RISK-016 residual)
A19: POAM-018 | B19: FIND-018 | C19: CM-3 | D19: RISK-014 | E19: Emergency and console changes bypass approval (3 of 25 sampled) | F19: Console/emergency paths rely on memory; no retro-approval tracking | G19: Moderate | H19: Auto-open retro-approval task on every emergency change with 2-day escalation; CloudTrail/EventBridge alerts on console changes to security groups and IAM; approval gate before deploy job | I19: M1 Retro-approval task automation for emergency changes (due 2026-08-28; Done) | M2 EventBridge alerts on console SG/IAM changes to on-call (due 2026-09-04; Not Started) | M3 Assessor validation: sample of emergency changes since M1 + alert test (due 2026-09-11; Not Started) | J19: Tomasz Wierzbicki (Director, Platform Engineering) | K19: SRE (about 24h) | L19: 46241 | M19: =L19+IF(G19="Critical",30,IF(G19="High",90,IF(G19="Moderate",180,365))) | N19: 46276 | O19: 46276 | Q19: In Progress | R19: =IFERROR(COUNTIFS(Milestones!$A:$A,A19,Milestones!$E:$E,"Done")/COUNTIF(Milestones!$A:$A,A19),0) | S19: =IF(Q19="Closed",AA19-L19,README!$B$4-L19) | T19: =IF(AND(Q19<>"Closed",Q19<>"Risk Accepted",O19<README!$B$4),"Yes","No") | U19: =IF(O19<>N19,"Yes","No") | V19: =IF(Q19="Risk Accepted","n/a (acceptance expiry)",IF(O19<=M19,"Yes","No")) | W19: SRE backlog capacity (competing with POAM-011) | X19: Test: all emergency changes since 2026-08-28 retro-approved within 2 business days; trigger a test SG change and confirm alert | AB19: Moderate (RISK-014 residual L2 x I3 = 6) | AC19: Overdue since 2026-09-11; needs CTO prioritization decision against POAM-011 (same SRE team).
A20: POAM-019 | B20: FIND-019 | C20: AT-2 | D20: RISK-015 | E20: Security awareness training completion 91%; suspension not enforced | F20: Reminders to users only; no manager escalation or enforcement | G20: Low | H20: Okta group rule enforcing suspension at 30 days overdue; manager escalation at 14 days; monthly completion reporting | I20: M1 Manager escalation at 14 days; enforcement group rule live (due 2026-08-21; Done) | M2 Reach >= 99% (documented leave exceptions) (due 2026-09-15; Done) | M3 Assessor validation of EVID-070 (leave records for 3 exceptions) (due 2026-09-30; In Progress) | J20: Denise Yamamoto (Director of People) | K20: People Ops (about 8h); IAM Engineer (about 4h) | L20: 46241 | M20: =L20+IF(G20="Critical",30,IF(G20="High",90,IF(G20="Moderate",180,365))) | N20: 46295 | O20: 46295 | Q20: Completed – Pending Validation | R20: =IFERROR(COUNTIFS(Milestones!$A:$A,A20,Milestones!$E:$E,"Done")/COUNTIF(Milestones!$A:$A,A20),0) | S20: =IF(Q20="Closed",AA20-L20,README!$B$4-L20) | T20: =IF(AND(Q20<>"Closed",Q20<>"Risk Accepted",O20<README!$B$4),"Yes","No") | U20: =IF(O20<>N20,"Yes","No") | V20: =IF(Q20="Risk Accepted","n/a (acceptance expiry)",IF(O20<=M20,"Yes","No")) | X20: Inspection: LMS roster reconciled to Okta active population; leave exceptions verified in PeopleHub | Y20: EVID-070 | AB20: Moderate, accepted (RISK-015 residual L3 x I3 = 9)

Sheet Milestones
A1: POA&M ID | B1: Milestone | C1: Description | D1: Due Date | E1: Status | F1: Completed Date | G1: Late?
A2: POAM-001 | B2: M1 | C2: Disable 4 identified accounts (AR-EX-01..04); investigate post-termination sign-in (INC-2026-0117) | D2: 46213 | E2: Done | F2: 46212 | G2: =IF(AND(E2<>"Done",D2<README!$B$4),"Yes","No")
A3: POAM-001 | B3: M2 | C3: Deploy daily HR-to-Okta/AWS IAM/portal reconciliation job with auto-ticketing | D3: 46255 | E3: Done | F3: 46237 | G3: =IF(AND(E3<>"Done",D3<README!$B$4),"Yes","No")
A4: POAM-001 | B4: M3 | C4: Update SOP-IAM-02 (24h SLA, local-account checklist, vendor portals); train IT | D4: 46262 | E4: Done | F4: 46260 | G4: =IF(AND(E4<>"Done",D4<README!$B$4),"Yes","No")
A5: POAM-001 | B5: M4 | C5: Assessor validation: re-perform termination test on all terminations since 2026-07-01 + 5 job runs | D5: 46276 | E5: Done | F5: 46275 | G5: =IF(AND(E5<>"Done",D5<README!$B$4),"Yes","No")
A6: POAM-002 | B6: M1 | C6: Enroll 9 human members in MFA (accommodation for 1) | D6: 46262 | E6: Done | F6: 46261 | G6: =IF(AND(E6<>"Done",D6<README!$B$4),"Yes","No")
A7: POAM-002 | B7: M2 | C7: Convert svc-vulnscan and svc-confroom to non-interactive integrations | D7: 46262 | E7: Done | F7: 46261 | G7: =IF(AND(E7<>"Done",D7<README!$B$4),"Yes","No")
A8: POAM-002 | B8: M3 | C8: Delete Legacy Exemption Policy and group; phishing-resistant policy on admin apps (CHG-2026-0731) | D8: 46266 | E8: Done | F8: 46262 | G8: =IF(AND(E8<>"Done",D8<README!$B$4),"Yes","No")
A9: POAM-002 | B9: M4 | C9: Assessor validation: policy export, group lookup, password-only sign-in attempt, IAM credential report | D9: 46270 | E9: Done | F9: 46270 | G9: =IF(AND(E9<>"Done",D9<README!$B$4),"Yes","No")
A10: POAM-003 | B10: M1 | C10: Remove excess grants: AR-EX-05/06/07/08/09 | D10: 46255 | E10: Done | F10: 46254 | G10: =IF(AND(E10<>"Done",D10<README!$B$4),"Yes","No")
A11: POAM-003 | B11: M2 | C11: Issue -adm accounts for remaining admins; remove admin from daily accounts (AR-EX-10) | D11: 46295 | E11: In Progress | G11: =IF(AND(E11<>"Done",D11<README!$B$4),"Yes","No")
A12: POAM-003 | B12: M3 | C12: Implement JIT elevation (approval + 4h auto-expiry) for AWS AdministratorAccess | D12: 46318 | E12: In Progress | G12: =IF(AND(E12<>"Done",D12<README!$B$4),"Yes","No")
A13: POAM-003 | B13: M4 | C13: Assessor validation: assignment export + live elevation record with CloudTrail evidence | D13: 46331 | E13: Not Started | G13: =IF(AND(E13<>"Done",D13<README!$B$4),"Yes","No")
A14: POAM-004 | B14: M1 | C14: Revoke duplicate, transferred, and inactive access (AR-EX-12/13/14) | D14: 46220 | E14: Done | F14: 46217 | G14: =IF(AND(E14<>"Done",D14<README!$B$4),"Yes","No")
A15: POAM-004 | B15: M2 | C15: Add transfer trigger to SOP-IAM-02 (re-baseline access within 5 business days) | D15: 46262 | E15: Done | F15: 46259 | G15: =IF(AND(E15<>"Done",D15<README!$B$4),"Yes","No")
A16: POAM-004 | B16: M3 | C16: Run Q3 privileged certification on new design (EVID-074) | D16: 46295 | E16: In Progress | G16: =IF(AND(E16<>"Done",D16<README!$B$4),"Yes","No")
A17: POAM-004 | B17: M4 | C17: Assessor validation: review Q3 campaign decisions for flagged items and rationale quality | D17: 46326 | E17: Not Started | G17: =IF(AND(E17<>"Done",D17<README!$B$4),"Yes","No")
A18: POAM-005 | B18: M1 | C18: Assign owners to all 13 non-human accounts; add fields to register | D18: 46255 | E18: Done | F18: 46252 | G18: =IF(AND(E18<>"Done",D18<README!$B$4),"Yes","No")
A19: POAM-005 | B19: M2 | C19: Rotate svc-quarrystone-sftp key (AR-EX-18) | D19: 46262 | E19: Done | F19: 46259 | G19: =IF(AND(E19<>"Done",D19<README!$B$4),"Yes","No")
A20: POAM-005 | B20: M3 | C20: Replace ironpeak-soc shared login with 6 named federated accounts (AR-EX-20) | D20: 46269 | E20: Done | F20: 46265 | G20: =IF(AND(E20<>"Done",D20<README!$B$4),"Yes","No")
A21: POAM-005 | B21: M4 | C21: Migrate svc-reporting-etl to IAM role; delete IAM user (AR-EX-19) | D21: 46276 | E21: Done | F21: 46268 | G21: =IF(AND(E21<>"Done",D21<README!$B$4),"Yes","No")
A22: POAM-005 | B22: M5 | C22: Assessor validation: register re-test (owner + credential age) and IAM credential report | D22: 46277 | E22: Done | F22: 46277 | G22: =IF(AND(E22<>"Done",D22<README!$B$4),"Yes","No")
A23: POAM-006 | B23: M1 | C23: Execute SOW amendment for awu; revoke out-of-scope PHI access (AR-EX-15/16) | D23: 46227 | E23: Done | F23: 46225 | G23: =IF(AND(E23<>"Done",D23<README!$B$4),"Yes","No")
A24: POAM-006 | B24: M2 | C24: Set Okta expiry for all contractor accounts; add SOW-scope field to access request form | D24: 46262 | E24: Done | F24: 46258 | G24: =IF(AND(E24<>"Done",D24<README!$B$4),"Yes","No")
A25: POAM-006 | B25: M3 | C25: Assessor validation: expiry report vs SOW register | D25: 46275 | E25: Done | F25: 46273 | G25: =IF(AND(E25<>"Done",D25<README!$B$4),"Yes","No")
A26: POAM-007 | B26: M1 | C26: Sign RACC-001 (CFO as risk owner; CISO concurrence) | D26: 46248 | E26: Done | F26: 46246 | G26: =IF(AND(E26<>"Done",D26<README!$B$4),"Yes","No")
A27: POAM-007 | B27: M2 | C27: Continue monthly compensating review (evidence each month to GRC) | D27: 46477 | E27: In Progress | G27: =IF(AND(E27<>"Done",D27<README!$B$4),"Yes","No")
A28: POAM-007 | B28: M3 | C28: Split roles at AP backfill (requisition open) | D28: 46477 | E28: Not Started | G28: =IF(AND(E28<>"Done",D28<README!$B$4),"Yes","No")
A29: POAM-008 | B29: M1 | C29: Change S3 lifecycle to 400-day expiry with Glacier IR after 90d (CHG-2026-0702) | D29: 46255 | E29: Done | F29: 46253 | G29: =IF(AND(E29<>"Done",D29<README!$B$4),"Yes","No")
A30: POAM-008 | B30: M2 | C30: Subscribe app-audit CloudWatch logs to log-archive (Firehose) | D30: 46262 | E30: Done | F30: 46261 | G30: =IF(AND(E30<>"Done",D30<README!$B$4),"Yes","No")
A31: POAM-008 | B31: M3 | C31: Assessor validation: config inspection + oldest-object query | D31: 46280 | E31: Done | F31: 46277 | G31: =IF(AND(E31<>"Done",D31<README!$B$4),"Yes","No")
A32: POAM-009 | B32: M1 | C32: Expand SIEM report scope to all privileged principals incl. IAM users | D32: 46255 | E32: Done | F32: 46248 | G32: =IF(AND(E32<>"Done",D32<README!$B$4),"Yes","No")
A33: POAM-009 | B33: M2 | C33: Auto-create weekly review ticket with escalation to CISO at 5 business days | D33: 46262 | E33: Done | F33: 46262 | G33: =IF(AND(E33<>"Done",D33<README!$B$4),"Yes","No")
A34: POAM-009 | B34: M3 | C34: Execute MDR SOW change for backup reviewer | D34: 46276 | E34: Delayed | G34: =IF(AND(E34<>"Done",D34<README!$B$4),"Yes","No")
A35: POAM-009 | B35: M4 | C35: Assessor validation: W27–W37 reviews (EVID-072) | D35: 46280 | E35: Not Started | G35: =IF(AND(E35<>"Done",D35<README!$B$4),"Yes","No")
A36: POAM-010 | B36: M1 | C36: Submit VM-003 §7 exception for 2 notify-worker criticals with reachability analysis (CISO decision) | D36: 46255 | E36: Done | F36: 46254 | G36: =IF(AND(E36<>"Done",D36<README!$B$4),"Yes","No")
A37: POAM-010 | B37: M2 | C37: Upgrade notify-worker to supported Node.js LTS + current base image | D37: 46295 | E37: In Progress | G37: =IF(AND(E37<>"Done",D37<README!$B$4),"Yes","No")
A38: POAM-010 | B38: M3 | C38: SLA-breach dashboard reviewed in weekly engineering leads meeting | D38: 46280 | E38: Done | F38: 46274 | G38: =IF(AND(E38<>"Done",D38<README!$B$4),"Yes","No")
A39: POAM-010 | B39: M4 | C39: Tag-policy SCP denying untagged EC2/EKS launches (OBS-02) | D39: 46310 | E39: Not Started | G39: =IF(AND(E39<>"Done",D39<README!$B$4),"Yes","No")
A40: POAM-010 | B40: M5 | C40: Assessor validation: re-run SLA test on Q3 population | D40: 46331 | E40: Not Started | G40: =IF(AND(E40<>"Done",D40<README!$B$4),"Yes","No")
A41: POAM-011 | B41: M1 | C41: Stand up managed transfer service (IaC) and test with Quarrystone | D41: 46262 | E41: Done | F41: 46260 | G41: =IF(AND(E41<>"Done",D41<README!$B$4),"Yes","No")
A42: POAM-011 | B42: M2 | C42: Cut over Quarrystone + 4 customers; decommission wf-sftp-01 | D42: 46280 | E42: Delayed | G42: =IF(AND(E42<>"Done",D42<README!$B$4),"Yes","No")
A43: POAM-011 | B43: M3 | C43: Migrate legacy-reports to Aurora read replica; decommission EC2 host | D43: 46325 | E43: In Progress | G43: =IF(AND(E43<>"Done",D43<README!$B$4),"Yes","No")
A44: POAM-011 | B44: M4 | C44: Assessor validation: inventory shows 0 unsupported components; hosts terminated | D44: 46371 | E44: Not Started | G44: =IF(AND(E44<>"Done",D44<README!$B$4),"Yes","No")
A45: POAM-012 | B45: M1 | C45: Remove 3389 ingress rule; confirm SSM-only admin (CHG-2026-0521); review Windows 4624 type-10 logons | D45: 46206 | E45: Done | F45: 46206 | G45: =IF(AND(E45<>"Done",D45<README!$B$4),"Yes","No")
A46: POAM-012 | B46: M2 | C46: Route Security Hub High findings to SRE on-call queue | D46: 46211 | E46: Done | F46: 46210 | G46: =IF(AND(E46<>"Done",D46<README!$B$4),"Yes","No")
A47: POAM-012 | B47: M3 | C47: Deploy SCP guardrail for admin ports from 0.0.0.0/0 | D47: 46213 | E47: Done | F47: 46212 | G47: =IF(AND(E47<>"Done",D47<README!$B$4),"Yes","No")
A48: POAM-012 | B48: M4 | C48: Assessor validation: SG export, Security Hub PASSED, guardrail test | D48: 46213 | E48: Done | F48: 46213 | G48: =IF(AND(E48<>"Done",D48<README!$B$4),"Yes","No")
A49: POAM-013 | B49: M1 | C49: Write restore runbook and integrity-check queries | D49: 46255 | E49: Done | F49: 46253 | G49: =IF(AND(E49<>"Done",D49<README!$B$4),"Yes","No")
A50: POAM-013 | B50: M2 | C50: Perform restore test (assessor observes) | D50: 46262 | E50: Done | F50: 46261 | G50: =IF(AND(E50<>"Done",D50<README!$B$4),"Yes","No")
A51: POAM-013 | B51: M3 | C51: Add semi-annual restore test to BCP-003 calendar; assessor validation | D51: 46266 | E51: Done | F51: 46266 | G51: =IF(AND(E51<>"Done",D51<README!$B$4),"Yes","No")
A52: POAM-014 | B52: M1 | C52: Update IRP-005: SHCA 24h notification step + current roster (OBS-03) | D52: 46280 | E52: Done | F52: 46276 | G52: =IF(AND(E52<>"Done",D52<README!$B$4),"Yes","No")
A53: POAM-014 | B53: M2 | C53: Conduct ransomware tabletop (IR + CP) | D53: 46309 | E53: Not Started | G53: =IF(AND(E53<>"Done",D53<README!$B$4),"Yes","No")
A54: POAM-014 | B54: M3 | C54: Publish after-action report; add corrective actions to POA&M | D54: 46325 | E54: Not Started | G54: =IF(AND(E54<>"Done",D54<README!$B$4),"Yes","No")
A55: POAM-014 | B55: M4 | C55: Assessor validation | D55: 46341 | E55: Not Started | G55: =IF(AND(E55<>"Done",D55<README!$B$4),"Yes","No")
A56: POAM-015 | B56: M1 | C56: Assess Tier 1 overdue vendors (Pulsewire, Ironpeak) | D56: 46356 | E56: In Progress | G56: =IF(AND(E56<>"Done",D56<README!$B$4),"Yes","No")
A57: POAM-015 | B57: M2 | C57: Fourth-party inventory from updated questionnaires (all Tier 1) | D57: 46371 | E57: Not Started | G57: =IF(AND(E57<>"Done",D57<README!$B$4),"Yes","No")
A58: POAM-015 | B58: M3 | C58: Approve C-SCRM plan | D58: 46402 | E58: Not Started | G58: =IF(AND(E58<>"Done",D58<README!$B$4),"Yes","No")
A59: POAM-015 | B59: M4 | C59: Assess remaining Tier 2 overdue vendors; assessor validation | D59: 46421 | E59: Not Started | G59: =IF(AND(E59<>"Done",D59<README!$B$4),"Yes","No")
A60: POAM-016 | B60: M1 | C60: Interim: vendor suspends offshore access to Wrenfield data (letter) | D60: 46227 | E60: Done | F60: 46227 | G60: =IF(AND(E60<>"Done",D60<README!$B$4),"Yes","No")
A61: POAM-016 | B61: M2 | C61: Execute contract amendment (redline v3 in negotiation) | D61: 46295 | E61: In Progress | G61: =IF(AND(E61<>"Done",D61<README!$B$4),"Yes","No")
A62: POAM-016 | B62: M3 | C62: Deploy minimized, tokenized extract (drop address, phone, email, free text) | D62: 46311 | E62: In Progress | G62: =IF(AND(E62<>"Done",D62<README!$B$4),"Yes","No")
A63: POAM-016 | B63: M4 | C63: Receive current pentest report + retest letter (EVID-051) | D63: 46325 | E63: Not Started | G63: =IF(AND(E63<>"Done",D63<README!$B$4),"Yes","No")
A64: POAM-016 | B64: M5 | C64: Assessor validation + vendor risk re-score | D64: 46331 | E64: Not Started | G64: =IF(AND(E64<>"Done",D64<README!$B$4),"Yes","No")
A65: POAM-017 | B65: M1 | C65: SSP outline on SP 800-18r2 structure; boundary + data flows updated | D65: 46295 | E65: In Progress | G65: =IF(AND(E65<>"Done",D65<README!$B$4),"Yes","No")
A66: POAM-017 | B66: M2 | C66: Control implementation statements (61 controls) reviewed by owners | D66: 46356 | E66: Not Started | G66: =IF(AND(E66<>"Done",D66<README!$B$4),"Yes","No")
A67: POAM-017 | B67: M3 | C67: Approval by CTO (system owner); assessor validation | D67: 46371 | E67: Not Started | G67: =IF(AND(E67<>"Done",D67<README!$B$4),"Yes","No")
A68: POAM-018 | B68: M1 | C68: Retro-approval task automation for emergency changes | D68: 46262 | E68: Done | F68: 46262 | G68: =IF(AND(E68<>"Done",D68<README!$B$4),"Yes","No")
A69: POAM-018 | B69: M2 | C69: EventBridge alerts on console SG/IAM changes to on-call | D69: 46269 | E69: Not Started | G69: =IF(AND(E69<>"Done",D69<README!$B$4),"Yes","No")
A70: POAM-018 | B70: M3 | C70: Assessor validation: sample of emergency changes since M1 + alert test | D70: 46276 | E70: Not Started | G70: =IF(AND(E70<>"Done",D70<README!$B$4),"Yes","No")
A71: POAM-019 | B71: M1 | C71: Manager escalation at 14 days; enforcement group rule live | D71: 46255 | E71: Done | F71: 46254 | G71: =IF(AND(E71<>"Done",D71<README!$B$4),"Yes","No")
A72: POAM-019 | B72: M2 | C72: Reach >= 99% (documented leave exceptions) | D72: 46280 | E72: Done | F72: 46277 | G72: =IF(AND(E72<>"Done",D72<README!$B$4),"Yes","No")
A73: POAM-019 | B73: M3 | C73: Assessor validation of EVID-070 (leave records for 3 exceptions) | D73: 46295 | E73: In Progress | G73: =IF(AND(E73<>"Done",D73<README!$B$4),"Yes","No")

Sheet Evidence
A1: Evidence ID | B1: Control ID | C1: Evidence Request | D1: Artifact Description | E1: Evidence Owner | F1: Request Date | G1: Due Date | H1: Received Date | I1: Status | J1: Evidence Period | K1: File / Repository Location | L1: In Repo? | M1: Reviewer | N1: Review Result | O1: Evidence Level | P1: Sufficiency | Q1: Exception | R1: Follow-Up Required | S1: Days Late | T1: Notes
A2: EVID-001 | B2: AC-1 | C2: Current Access Control Policy with approval record and review history | D2: ACP-002 Access Control Policy v3.1 (PDF) + approval minutes 2025-01-15 | E2: Alicia Moreno | F2: 46183 | G2: 46192 | H2: 46185 | I2: Accepted | J2: Current version | K2: GRC-Vault:/WCP-2026/AC/EVID-001_ACP-002_v3.1.pdf | L2: No | M2: Lead assessor | N2: Content adequate; last approval 2025-01-15 exceeds the annual review cycle | O2: Design | P2: Sufficient | R2: No | S2: =IF(H2="",MAX(0,README!$B$4-G2),MAX(0,H2-G2)) | T2: Drives OBS-01. Policy existence alone did not satisfy AC-2 or AC-6
A3: EVID-002 | B3: AC-2; AC-2(3); PS-4; PS-5 | C3: Joiner/mover/leaver procedure | D3: SOP-IAM-02 Account Lifecycle v2.0 | E3: Nadia Rahman | F3: 46183 | G3: 46192 | H3: 46185 | I3: Accepted | J3: Current version | K3: GRC-Vault:/WCP-2026/AC/EVID-002_SOP-IAM-02_v2.0.pdf | L3: No | M3: Lead assessor | N3: Describes a manual HR-email to IT-ticket flow; no step for local accounts or transfers | O3: Design | P3: Sufficient | R3: No | S3: =IF(H3="",MAX(0,README!$B$4-G3),MAX(0,H3-G3)) | T3: Design gap is visible in the procedure itself
A4: EVID-003 | B4: AC-2(3); PS-4 | C4: System-generated list of ALL terminations 2026-01-01 to 2026-06-30 (worker ID, type, date, effective time) | D4: PeopleHub report 'Terminations by Effective Date' + final-pay reconciliation | E4: Denise Yamamoto | F4: 46183 | G4: 46192 | H4: 46190 | I4: Accepted | J4: 2026-01-01 to 2026-06-30 | K4: evidence/AC/EVID-003_peoplehub-terminations-2026H1.csv | L4: Yes | M4: Lead assessor | N4: IPE validated: 19 of 19 reconciled to final pay/invoice | O4: Operating Effectiveness | P4: Sufficient | R4: No | S4: =IF(H4="",MAX(0,README!$B$4-G4),MAX(0,H4-G4)) | T4: Assessor observed report generation over screen share
A5: EVID-004 | B5: AC-2(3) | C5: Okta System Log export of user.lifecycle.deactivate events for the period | D5: Okta System Log API export | E5: Nadia Rahman | F5: 46183 | G5: 46192 | H5: 46190 | I5: Accepted | J5: 2026-01-01 to 2026-06-30 | K5: evidence/AC/EVID-004_okta-deactivation-events-2026H1.csv | L5: Yes | M5: Lead assessor | N5: 17 events; matched to EVID-003 | O5: Operating Effectiveness | P5: Sufficient | R5: No | S5: =IF(H5="",MAX(0,README!$B$4-G5),MAX(0,H5-G5))
A6: EVID-005 | B6: AC-2; AC-2(1); IA-2; AC-6(2) | C6: Okta user export (all statuses) with MFA enrollment and group membership as of 2026-06-30 | D6: Okta Users API export | E6: Nadia Rahman | F6: 46183 | G6: 46192 | H6: 46204 | I6: Accepted | J6: As of 2026-06-30 | K6: access-review/source-exports/okta_users.csv | L6: Yes | M6: Lead assessor | N6: Complete for in-scope population; account types verified | O6: Implementation | P6: Sufficient | R6: No | S6: =IF(H6="",MAX(0,README!$B$4-G6),MAX(0,H6-G6))
A7: EVID-006 | B7: AC-2; AC-6; AC-6(5) | C7: Entitlement exports from each in-scope system as of 2026-06-30 | D7: Exports from AWS IAM Identity Center/IAM, GitHub, Aurora roles, wf-sftp-01, PeopleHub, Ledgerline, SIEM, EDR, Quarrystone portal | E7: System owners (9 systems) | F7: 46183 | G7: 46204 | H7: 46206 | I7: Accepted | J7: As of 2026-06-30 | K7: access-review/source-exports/entitlements.csv | L7: Yes | M7: Lead assessor | N7: 106 entitlements; 2 exports re-pulled after column omissions (Ledgerline, portal) | O7: Implementation | P7: Sufficient | R7: No | S7: =IF(H7="",MAX(0,README!$B$4-G7),MAX(0,H7-G7)) | T7: Ledgerline export first omitted role assignment dates; returned 2026-07-03
A8: EVID-007 | B8: AC-2; IA-2(1); IA-5 | C8: AWS IAM credential report for wcp-prod | D8: IAM credential report (CSV) | E8: Tomasz Wierzbicki | F8: 46183 | G8: 46192 | H8: 46204 | I8: Accepted | J8: As of 2026-06-30 | K8: evidence/IA/EVID-007_aws-iam-credential-report_2026-06-30.csv | L8: Yes | M8: Lead assessor | N8: Revealed mfeld-admin (no MFA) and svc-reporting-etl static key | O8: Implementation | P8: Sufficient | R8: No | S8: =IF(H8="",MAX(0,README!$B$4-G8),MAX(0,H8-G8))
A9: EVID-008 | B9: AC-6(7) | C9: Q1 2026 access certification campaign export (reviewer, item, decision, timestamp) | D9: Okta Access Certification campaign export Q1-2026 (412 decisions) | E9: Alicia Moreno | F9: 46183 | G9: 46192 | H9: 46197 | I9: Accepted | J9: 2026-03-02 to 2026-03-20 | K9: evidence/AC/EVID-008_q1-certification-summary.md | L9: Yes | M9: Lead assessor | N9: 100% approved; 17 of 23 reviewers finished in under 5 minutes; approved 2 items later found invalid | O9: Operating Effectiveness | P9: Sufficient | R9: No | S9: =IF(H9="",MAX(0,README!$B$4-G9),MAX(0,H9-G9))
A10: EVID-009 | B10: AC-6(7) | C10: Evidence that quarterly access reviews are performed | D10: Screenshot: 'Q1 Access Review, 100% complete' dashboard tile | E10: Alicia Moreno | F10: 46183 | G10: 46192 | H10: 46188 | I10: Insufficient | J10: Undated | K10: evidence/AC/EVID-009_insufficient-screenshot-example.md | L10: Yes | M10: Lead assessor | N10: No population, reviewers, decisions, or date; cannot show review quality | O10: Design | P10: Insufficient | Q10: Screenshot shows completion status only | R10: Yes: replaced by EVID-008 | S10: =IF(H10="",MAX(0,README!$B$4-G10),MAX(0,H10-G10)) | T10: Teaching example: completion does not prove effectiveness
A11: EVID-010 | B11: IA-2(1); IA-2(2); IA-2(8) | C11: Okta authentication and global session policy export | D11: Okta Policies API export | E11: Nadia Rahman | F11: 46183 | G11: 46192 | H11: 46203 | I11: Accepted | J11: As of 2026-06-30 | K11: evidence/IA/EVID-010_okta-authentication-policies_2026-06-30.json | L11: Yes | M11: Lead assessor | N11: Global policy excludes MFA-Exempt-Legacy group; admin apps accept non-phishing-resistant factors | O11: Implementation | P11: Sufficient | R11: No | S11: =IF(H11="",MAX(0,README!$B$4-G11),MAX(0,H11-G11))
A12: EVID-011 | B12: IA-2(1); IA-2(2) | C12: Membership of all MFA exemption groups with reason and approval | D12: Okta group membership export MFA-Exempt-Legacy | E12: Nadia Rahman | F12: 46183 | G12: 46192 | H12: 46203 | I12: Accepted | J12: As of 2026-06-30 | K12: evidence/IA/EVID-011_okta-mfa-exempt-group_2026-06-30.csv | L12: Yes | M12: Lead assessor | N12: 11 members (9 human, 2 service); 0 approvals or expiry dates | O12: Implementation | P12: Sufficient | R12: No | S12: =IF(H12="",MAX(0,README!$B$4-G12),MAX(0,H12-G12))
