Workbook

Sheet README
A1: Vendor Risk Assessment: Quarrystone Analytics (fictional) + Vendor Inventory
A2: Wrenfield Health (fictional) · simulated NIST SP 800-53 Rev. 5 (Release 5.2.0) assessment · synthetic data
A4: As-of (status) date | B4: 46283 | C4: <- input: all aging/overdue formulas reference this cell (use =TODAY() in a live workbook)
A6: Tiering | B6: Inherent score = sensitivity(0-3) + volume(0-3) + access(0-3) + criticality(0-3) + substitutability(0-2); Tier 1 >= 9, Tier 2 >= 5, else Tier 3. Formulas live in VendorInventory
A7: Reassessment | B7: Tier 1: Annual full assessment + continuous monitoring; Tier 2: Every 2 years + at renewal; Tier 3: At renewal (lightweight)
A8: Real platforms | B8: AWS, Okta, GitHub, Google Workspace appear only as inventory entries; no statement is made about their controls
A9: Decision | B9: Mitigate (conditional continuation) + partial Transfer, approved Elena Marsh (CEO) on recommendation of CISO and VP Clinical Analytics, 2026-07-22

Sheet VendorInventory
A1: Vendor ID | B1: Vendor | C1: Service | D1: Business Owner | E1: Data Sensitivity (0-3) | F1: Data Volume (0-3) | G1: Access / Integration (0-3) | H1: Business Criticality (0-3) | I1: Substitutability (0-2) | J1: Inherent Score | K1: Tier | L1: Last Assessed | M1: Reassess (months) | N1: Next Due | O1: Assessment Current? | P1: Assessment Method | Q1: Breach Notice Term | R1: Fourth Parties Mapped? | S1: Real Platform?
A2: VEN-001 | B2: AWS | C2: IaaS/PaaS hosting for WCP-PROD (BAA) | D2: Samir Haddad | E2: 3 | F2: 3 | G2: 3 | H2: 3 | I2: 2 | J2: =SUM(E2:I2) | K2: =IF(J2>=9,1,IF(J2>=5,2,3)) | L2: 46093 | M2: =IF(K2=1,12,IF(K2=2,24,36)) | N2: =IF(L2="","",DATE(YEAR(L2),MONTH(L2)+M2,MIN(DAY(L2),28))) | O2: =IF(L2="","No (never)",IF(N2<README!$B$4,"No (overdue)","Yes")) | P2: Review of provider's published compliance documentation (details out of scope) | Q2: Per provider BAA | R2: n/a | S2: Yes (no claims made about provider)
A3: VEN-002 | B3: Okta | C3: Workforce identity (SSO/MFA) | D3: Alicia Moreno | E3: 2 | F3: 2 | G3: 3 | H3: 3 | I3: 2 | J3: =SUM(E3:I3) | K3: =IF(J3>=9,1,IF(J3>=5,2,3)) | L3: 46073 | M3: =IF(K3=1,12,IF(K3=2,24,36)) | N3: =IF(L3="","",DATE(YEAR(L3),MONTH(L3)+M3,MIN(DAY(L3),28))) | O3: =IF(L3="","No (never)",IF(N3<README!$B$4,"No (overdue)","Yes")) | P3: Review of provider's published compliance documentation (details out of scope) | Q3: Per provider terms | R3: n/a | S3: Yes (no claims made about provider)
A4: VEN-003 | B4: GitHub | C4: Source code, CI/CD (Actions) | D4: Grace Lindqvist | E4: 2 | F4: 1 | G4: 3 | H4: 2 | I4: 1 | J4: =SUM(E4:I4) | K4: =IF(J4>=9,1,IF(J4>=5,2,3)) | L4: 46050 | M4: =IF(K4=1,12,IF(K4=2,24,36)) | N4: =IF(L4="","",DATE(YEAR(L4),MONTH(L4)+M4,MIN(DAY(L4),28))) | O4: =IF(L4="","No (never)",IF(N4<README!$B$4,"No (overdue)","Yes")) | P4: Review of provider's published compliance documentation (details out of scope) | Q4: Per provider terms | R4: n/a | S4: Yes (no claims made about provider)
A5: VEN-004 | B5: Quarrystone Analytics, LLC (fictional) | C5: Population-health analytics; nightly full-PHI extract (about 410k patients) | D5: Miriam Castell | E5: 3 | F5: 3 | G5: 2 | H5: 2 | I5: 2 | J5: =SUM(E5:I5) | K5: =IF(J5>=9,1,IF(J5>=5,2,3)) | L5: 46227 | M5: =IF(K5=1,12,IF(K5=2,24,36)) | N5: =IF(L5="","",DATE(YEAR(L5),MONTH(L5)+M5,MIN(DAY(L5),28))) | O5: =IF(L5="","No (never)",IF(N5<README!$B$4,"No (overdue)","Yes")) | P5: Deep assessment (this engagement): questionnaire, SOC 2 review, interviews | Q5: 30 days (BAA 2023) | R5: Yes (4 subprocessors identified during this assessment) | S5: No (fictional)
A6: VEN-005 | B6: Pulsewire Connect (fictional) | C6: RPM cellular hubs and device-data API | D6: Jorge Almeida | E6: 3 | F6: 3 | G6: 2 | H6: 3 | I6: 2 | J6: =SUM(E6:I6) | K6: =IF(J6>=9,1,IF(J6>=5,2,3)) | L6: 45518 | M6: =IF(K6=1,12,IF(K6=2,24,36)) | N6: =IF(L6="","",DATE(YEAR(L6),MONTH(L6)+M6,MIN(DAY(L6),28))) | O6: =IF(L6="","No (never)",IF(N6<README!$B$4,"No (overdue)","Yes")) | P6: Questionnaire + SOC 2 review | Q6: 10 days | R6: No | S6: No (fictional)
A7: VEN-006 | B7: Ironpeak MDR (fictional) | C7: 24x7 managed detection and response (SIEM/EDR access) | D7: Owen Castillo | E7: 2 | F7: 2 | G7: 3 | H7: 2 | I7: 1 | J7: =SUM(E7:I7) | K7: =IF(J7>=9,1,IF(J7>=5,2,3)) | L7: 45635 | M7: =IF(K7=1,12,IF(K7=2,24,36)) | N7: =IF(L7="","",DATE(YEAR(L7),MONTH(L7)+M7,MIN(DAY(L7),28))) | O7: =IF(L7="","No (never)",IF(N7<README!$B$4,"No (overdue)","Yes")) | P7: Onboarding due diligence only | Q7: 48 hours | R7: No | S7: No (fictional)
A8: VEN-007 | B8: Google Workspace | C8: Email and documents (BAA) | D8: Kevin Brandt | E8: 3 | F8: 2 | G8: 1 | H8: 2 | I8: 2 | J8: =SUM(E8:I8) | K8: =IF(J8>=9,1,IF(J8>=5,2,3)) | L8: 46121 | M8: =IF(K8=1,12,IF(K8=2,24,36)) | N8: =IF(L8="","",DATE(YEAR(L8),MONTH(L8)+M8,MIN(DAY(L8),28))) | O8: =IF(L8="","No (never)",IF(N8<README!$B$4,"No (overdue)","Yes")) | P8: Review of provider's published compliance documentation (details out of scope) | Q8: Per provider BAA | R8: n/a | S8: Yes (no claims made about provider)
A9: VEN-008 | B9: Brightdesk (fictional) | C9: Customer-support ticketing (limited PHI) | D9: Jorge Almeida | E9: 3 | F9: 1 | G9: 1 | H9: 1 | I9: 1 | J9: =SUM(E9:I9) | K9: =IF(J9>=9,1,IF(J9>=5,2,3)) | L9: 45797 | M9: =IF(K9=1,12,IF(K9=2,24,36)) | N9: =IF(L9="","",DATE(YEAR(L9),MONTH(L9)+M9,MIN(DAY(L9),28))) | O9: =IF(L9="","No (never)",IF(N9<README!$B$4,"No (overdue)","Yes")) | P9: Questionnaire + SOC 2 review | Q9: 5 business days | R9: No | S9: No (fictional)
A10: VEN-009 | B10: Clearpath Messaging (fictional) | C10: Patient SMS/voice reminders (name + phone + appointment time) | D10: Jorge Almeida | E10: 2 | F10: 3 | G10: 2 | H10: 1 | I10: 0 | J10: =SUM(E10:I10) | K10: =IF(J10>=9,1,IF(J10>=5,2,3)) | L10: 45418 | M10: =IF(K10=1,12,IF(K10=2,24,36)) | N10: =IF(L10="","",DATE(YEAR(L10),MONTH(L10)+M10,MIN(DAY(L10),28))) | O10: =IF(L10="","No (never)",IF(N10<README!$B$4,"No (overdue)","Yes")) | P10: Questionnaire | Q10: Without unreasonable delay (no fixed period) | R10: No | S10: No (fictional)
A11: VEN-010 | B11: PeopleHub (fictional) | C11: HRIS (authoritative source for JML) | D11: Denise Yamamoto | E11: 2 | F11: 1 | G11: 1 | H11: 2 | I11: 1 | J11: =SUM(E11:I11) | K11: =IF(J11>=9,1,IF(J11>=5,2,3)) | L11: 45734 | M11: =IF(K11=1,12,IF(K11=2,24,36)) | N11: =IF(L11="","",DATE(YEAR(L11),MONTH(L11)+M11,MIN(DAY(L11),28))) | O11: =IF(L11="","No (never)",IF(N11<README!$B$4,"No (overdue)","Yes")) | P11: Questionnaire + SOC 2 review | Q11: 72 hours | R11: No | S11: No (fictional)
A12: VEN-011 | B12: Ledgerline (fictional) | C12: ERP / finance | D12: Laura Brenneman | E12: 2 | F12: 1 | G12: 1 | H12: 2 | I12: 1 | J12: =SUM(E12:I12) | K12: =IF(J12>=9,1,IF(J12>=5,2,3)) | L12: 45902 | M12: =IF(K12=1,12,IF(K12=2,24,36)) | N12: =IF(L12="","",DATE(YEAR(L12),MONTH(L12)+M12,MIN(DAY(L12),28))) | O12: =IF(L12="","No (never)",IF(N12<README!$B$4,"No (overdue)","Yes")) | P12: Questionnaire + SOC 1/SOC 2 review | Q12: 72 hours | R12: No | S12: No (fictional)
A13: VEN-012 | B13: Northgate Talent Partners (fictional) | C13: Contract engineering staff (contractors receive privileged access) | D13: Sofia Ricci | E13: 1 | F13: 0 | G13: 3 | H13: 1 | I13: 0 | J13: =SUM(E13:I13) | K13: =IF(J13>=9,1,IF(J13>=5,2,3)) | M13: =IF(K13=1,12,IF(K13=2,24,36)) | N13: =IF(L13="","",DATE(YEAR(L13),MONTH(L13)+M13,MIN(DAY(L13),28))) | O13: =IF(L13="","No (never)",IF(N13<README!$B$4,"No (overdue)","Yes")) | P13: Never assessed (treated as staffing, not a data vendor) | Q13: None in MSA | R13: No | S13: No (fictional)
A14: VEN-013 | B14: Beaconline SIEM (fictional) | C14: Cloud SIEM | D14: Owen Castillo | E14: 2 | F14: 2 | G14: 1 | H14: 2 | I14: 1 | J14: =SUM(E14:I14) | K14: =IF(J14>=9,1,IF(J14>=5,2,3)) | L14: 45699 | M14: =IF(K14=1,12,IF(K14=2,24,36)) | N14: =IF(L14="","",DATE(YEAR(L14),MONTH(L14)+M14,MIN(DAY(L14),28))) | O14: =IF(L14="","No (never)",IF(N14<README!$B$4,"No (overdue)","Yes")) | P14: Questionnaire + SOC 2 review | Q14: 72 hours | R14: No | S14: No (fictional)
A15: VEN-014 | B15: Coldwater Secure Destruction (fictional) | C15: IT asset disposition | D15: Kevin Brandt | E15: 1 | F15: 1 | G15: 0 | H15: 0 | I15: 0 | J15: =SUM(E15:I15) | K15: =IF(J15>=9,1,IF(J15>=5,2,3)) | L15: 45931 | M15: =IF(K15=1,12,IF(K15=2,24,36)) | N15: =IF(L15="","",DATE(YEAR(L15),MONTH(L15)+M15,MIN(DAY(L15),28))) | O15: =IF(L15="","No (never)",IF(N15<README!$B$4,"No (overdue)","Yes")) | P15: Certificate + NAID-style attestation review | Q15: 5 business days | R15: n/a | S15: No (fictional)
A16: VEN-015 | B16: Lanternworks Security (fictional) | C16: Annual penetration testing | D16: Alicia Moreno | E16: 2 | F16: 0 | G16: 2 | H16: 0 | I16: 0 | J16: =SUM(E16:I16) | K16: =IF(J16>=9,1,IF(J16>=5,2,3)) | L16: 45976 | M16: =IF(K16=1,12,IF(K16=2,24,36)) | N16: =IF(L16="","",DATE(YEAR(L16),MONTH(L16)+M16,MIN(DAY(L16),28))) | O16: =IF(L16="","No (never)",IF(N16<README!$B$4,"No (overdue)","Yes")) | P16: Engagement due diligence | Q16: 24 hours | R16: n/a | S16: No (fictional)
A17: VEN-016 | B17: Tallis Print & Mail (fictional) | C17: Patient letters (names, addresses, program info) | D17: Jorge Almeida | E17: 3 | F17: 2 | G17: 2 | H17: 1 | I17: 0 | J17: =SUM(E17:I17) | K17: =IF(J17>=9,1,IF(J17>=5,2,3)) | M17: =IF(K17=1,12,IF(K17=2,24,36)) | N17: =IF(L17="","",DATE(YEAR(L17),MONTH(L17)+M17,MIN(DAY(L17),28))) | O17: =IF(L17="","No (never)",IF(N17<README!$B$4,"No (overdue)","Yes")) | P17: Never assessed | Q17: BAA executed 2023; no timeline | R17: No | S17: No (fictional)

Sheet Profile
A1: Attribute | B1: Value
A2: Vendor | B2: VEN-004
A3: Name | B3: Quarrystone Analytics, LLC (fictional)
A4: Service | B4: Population-health risk stratification and care-gap analytics. Nightly scores rank patients for care-manager outreach.
A5: Business Owner | B5: Dr. Miriam Castell, VP Clinical Analytics
A6: Technical Owner | B6: Liam Porter, Data Engineering Manager
A7: Contract | B7: MSA + BAA signed 2023-02-15 on vendor paper; renewal 2027-01-31 (negotiation leverage); annual fee $410k
A8: Data Accessed | B8: Full PHI extract of about 410,000 patients: name, DOB, address, phone, email, MRN, member ID, ICD-10 diagnoses, medications, vitals and RPM readings, care-plan events, free-text care notes (58 fields)
A9: Data Sensitivity | B9: PHI (regulated). Adds Medicaid member data after SHCA go-live.
A10: Integration | B10: Outbound: nightly SFTP push from wf-sftp-01 (Windows 2012 R2, unsupported) to the vendor landing zone. Inbound: risk scores pulled over HTTPS by API key (svc-qs-api). Portal: 6 Wrenfield user accounts plus 1 API key, local authentication (no SSO).
A11: Criticality | B11: High. Scores drive outreach prioritization. WCP has a rules-based fallback, so an outage degrades quality but does not stop care. Integrity matters: bad scores could mis-rank patients.
A12: Geography | B12: Vendor HQ Denver, CO. Storage in US (cloud region us-east-1). Access includes an offshore subcontractor in Pune, India.
A13: Inherent Score | B13: 12
A14: Inherent Rating | B14: Tier 1, Critical inherent risk
A15: Assessment Window | B15: 2026-06-22 to 2026-07-24
A16: Assessor Contacts | B16: Quarrystone CISO (interview 2026-07-14), Head of Data Engineering

Sheet FourthParties
A1: Subcontractor (fourth party) | B1: Role | C1: Location | D1: In SOC 2 Report? | E1: Disclosed Initially?
A2: Glacierbase Data Cloud (fictional) | B2: Cloud data warehouse (stores all Wrenfield data) | C2: US region | D2: Carved out (subservice organization) | E2: Yes
A3: AWS (vendor's own hosting) | B3: Ingestion and model hosting | C3: US region | D3: Carved out | E3: Yes
A4: Meridian Offshore Data Services Pvt. Ltd. (fictional) | B4: Data-engineering support: pipeline troubleshooting with production access | C4: Pune, India | D4: Not listed | E4: No (found at interview 2026-07-14)
A5: Hollis Helpdesk (fictional) | B5: Support ticketing (tickets may contain PHI snippets) | C5: US | D5: Not listed | E5: No

Sheet VendorAssessment
A1: Question ID | B1: Security Domain | C1: Requirement | D1: Vendor Response | E1: Evidence | F1: Assessor Evaluation | G1: Risk Identified | H1: Severity | I1: Recommendation | J1: Owner | K1: Status | L1: Vendor Finding
A2: VQ-01 | B2: Security governance | C2: Named security leader, approved policy set reviewed annually, executive oversight | D2: CISO in place since 2022; ISO 27001-aligned policy set reviewed 2026-01; quarterly board security update | E2: Policy index; org chart | F2: Satisfactory | G2: None | K2: Closed (satisfactory)
A3: VQ-02 | B3: Risk management | C3: Annual risk assessment with tracked treatments | D3: Annual risk assessment (2026-02); risk register maintained | E3: Risk assessment summary (redacted) | F3: Satisfactory | G3: None | K3: Closed (satisfactory)
A4: VQ-03 | B4: Certifications and attestations | C4: Current SOC 2 Type II (or ISO 27001) covering services used | D4: SOC 2 Type II 2024-10-01 to 2025-09-30; bridge letter to 2026-03-31; next report expected 2026-12 | E4: EVID-050 | F4: Partially Satisfactory | G4: SOC 2 exceptions (access reviews, change approvals) | H4: Low | I4: Monitor: obtain next SOC 2 (expected 2026-12) and confirm exceptions resolved | J4: Beth Kowalski | K4: Monitor | L4: VR-006
A5: VQ-04 | B5: Access control | C5: Timely provisioning/deprovisioning and periodic reviews of staff with customer-data access | D5: Quarterly reviews; SOC 2 notes 1 of 4 quarters missed (management response: automation added) | E5: SOC 2 section 4 exception | F5: Partially Satisfactory | G5: SOC 2 exceptions (access reviews, change approvals) | H5: Low | I5: Monitor: obtain next SOC 2 (expected 2026-12) and confirm exceptions resolved | J5: Beth Kowalski | K5: Monitor | L5: VR-006
A6: VQ-05 | B6: Access control | C6: Least privilege for production customer data | D6: Role-based; 14 US staff plus the subcontractor team have production read access | E6: Role list (counts only) | F6: Partially Satisfactory | G6: Undisclosed offshore subcontractor with production access to Wrenfield PHI | H6: Critical | I6: Immediate suspension of offshore access to Wrenfield data; contract amendment requiring US-only access with technical enforcement (geo-restricted IdP policy, US-only support roster) and access-log attestation quarterly | J6: Quarrystone CISO / Miriam Castell | K6: Interim contained (offshore access suspended 2026-07-24); contractual fix open | L6: VR-001
A7: VQ-06 | B7: MFA | C7: MFA for all workforce and privileged access | D7: SSO with MFA for all staff; FIDO2 required for admins | E7: IdP policy screenshot (dated) + SOC 2 CC6.1 no exceptions | F7: Satisfactory | G7: None | K7: Closed (satisfactory)
A8: VQ-07 | B8: MFA | C8: Customer portal supports SSO/MFA | D8: Portal uses local accounts with optional TOTP; SAML SSO available on Enterprise tier only | E8: Product documentation | F8: Unsatisfactory | G8: Wrenfield not performing SOC 2 CUEC for portal user management; no SSO | H8: Moderate | I8: Add portal to quarterly certification and JML checklist (done); budget SAML SSO at renewal | J8: Liam Porter | K8: Partially remediated (review + JML done; SSO at 2027 renewal) | L8: VR-007
A9: VQ-08 | B9: Encryption | C9: Encryption in transit (TLS 1.2+ / SFTP) | D9: SFTP (SSH) inbound; TLS 1.2+ API | E9: TLS scan by assessor (API endpoint) | F9: Satisfactory | G9: None | K9: Closed (satisfactory)
A10: VQ-09 | B10: Encryption | C10: Encryption at rest with managed keys | D10: AES-256 at rest in warehouse and object storage; cloud KMS; annual rotation | E10: SOC 2 CC6.1/CC6.7 no exceptions | F10: Satisfactory | G10: None | K10: Closed (satisfactory)
A11: VQ-10 | B11: Encryption | C11: Customer data segregation | D11: Schema-per-client logical separation; shared keys | E11: Architecture diagram | F11: Partially Satisfactory | G11: None | K11: Closed (satisfactory)
A12: VQ-11 | B12: Vulnerability management | C12: Scanning with defined remediation SLAs | D12: Monthly authenticated scans; Critical 30 days, High 60 | E12: Vulnerability management standard | F12: Satisfactory | G12: None | K12: Closed (satisfactory)
A13: VQ-12 | B13: Penetration testing | C13: Annual independent penetration test with retest evidence | D13: Last external test 2025-03; 1 High finding 'remediated'; summary letter only | E13: Summary letter; full report requested (EVID-051) | F13: Unsatisfactory | G13: Penetration test evidence stale and incomplete | H13: Moderate | I13: Provide full report (under NDA) or detailed executive summary with finding list and retest letter; annual testing clause in amendment | J13: Quarrystone CISO | K13: Evidence requested (EVID-051, overdue) | L13: VR-004
A14: VQ-13 | B14: Secure development | C14: SAST, code review, dependency scanning | D14: SAST and dependency scanning in CI; 2-person review | E14: SDLC standard | F14: Satisfactory | G14: None | K14: Closed (satisfactory)
A15: VQ-14 | B15: Supply-chain risk | C15: SBOM and third-party component governance | D15: No SBOM produced; dependency scanning only | E15: Interview | F15: Partially Satisfactory | G15: No SBOM for vendor software | H15: Low | I15: Request SBOM availability on the roadmap; revisit at 2027 renewal | J15: Beth Kowalski | K15: Monitor | L15: VR-011
A16: VQ-15 | B16: Incident response | C16: Documented IR plan tested annually | D16: IR plan; tabletop 2026-02 | E16: After-action summary | F16: Satisfactory | G16: None | K16: Closed (satisfactory)
A17: VQ-16 | B17: Breach notification | C17: Notify Wrenfield of security incidents affecting its data within 24 hours of discovery | D17: BAA: 'without unreasonable delay and no later than 30 days' | E17: BAA §4.2 | F17: Unsatisfactory | G17: Breach notification term of 30 days | H17: High | I17: Amend BAA to 24h notice of suspected or confirmed incidents affecting Wrenfield data, with defined content and updates | J17: Theo Anand (General Counsel) | K17: In negotiation (redline v3) | L17: VR-002
A18: VQ-17 | B18: Incident response | C18: Cooperate with customer investigations, including log provision | D18: 'Reasonable cooperation'; no commitment to provide logs | E18: MSA §9 | F18: Partially Satisfactory | G18: Access logs kept 90 days; no commitment to support investigations | H18: Moderate | I18: 12-month log retention for access to Wrenfield data; contractual log provision within 5 business days of request | J18: Theo Anand (General Counsel) | K18: In negotiation | L18: VR-009
A19: VQ-18 | B19: Business continuity | C19: BC/DR plan with RTO/RPO appropriate to the service | D19: RTO 72h / RPO 24h; tested 2026-01 | E19: BC/DR summary | F19: Satisfactory | G19: None (Acceptable: WCP has a rules-based fallback for scores) | K19: Closed (satisfactory)
A20: VQ-19 | B20: Backups | C20: Backups with immutability and restore testing | D20: Daily backups, 30-day retention, immutable; restore tested 2026-01 | E20: SOC 2 A1.2 no exceptions | F20: Satisfactory | G20: None | K20: Closed (satisfactory)
A21: VQ-20 | B21: Logging | C21: Log access to customer data; retain at least 12 months | D21: Access logs retained 90 days | E21: Interview | F21: Partially Satisfactory | G21: Access logs kept 90 days; no commitment to support investigations | H21: Moderate | I21: 12-month log retention for access to Wrenfield data; contractual log provision within 5 business days of request | J21: Theo Anand (General Counsel) | K21: In negotiation | L21: VR-009
A22: VQ-21 | B22: Privacy | C22: Receive only data needed for the service (minimum necessary) | D22: Model uses 31 of 58 fields; address, phone, email, free-text notes unused but received | E22: Feature list from Head of Data Engineering | F22: Unsatisfactory | G22: Extract exceeds minimum necessary (27 of 58 fields unused) | H22: High | I22: Redesign extract to 31 required fields; replace direct identifiers with tokenized IDs; re-validate model on minimized data | J22: Liam Porter (Data Engineering) | K22: In progress (target 2026-10-16) | L22: VR-003
A23: VQ-22 | B23: Privacy | C23: No secondary use of Wrenfield data without written permission | D23: De-identified (Safe Harbor) pooled data used to improve cross-client models, per vendor MSA §12 | E23: MSA §12; de-identification procedure | F23: Partially Satisfactory | G23: Secondary use of pooled de-identified data | H23: Moderate | I23: General Counsel opinion; either opt Wrenfield data out of pooling or confirm customer BAAs permit it and disclose | J23: Theo Anand (General Counsel) | K23: Legal review in progress | L23: VR-010
A24: VQ-23 | B24: Data location | C24: US-only storage AND access (SHCA CSA §6.1; 2 customer BAAs) | D24: Storage in US region. Initially answered 'US staff only'; interview revealed offshore subcontractor production access | E24: Interview 2026-07-14; subcontractor agreement | F24: Unsatisfactory | G24: Undisclosed offshore subcontractor with production access to Wrenfield PHI | H24: Critical | I24: Immediate suspension of offshore access to Wrenfield data; contract amendment requiring US-only access with technical enforcement (geo-restricted IdP policy, US-only support roster) and access-log attestation quarterly | J24: Quarrystone CISO / Miriam Castell | K24: Interim contained (offshore access suspended 2026-07-24); contractual fix open | L24: VR-001
A25: VQ-24 | B25: Privacy | C25: Documented de-identification method | D25: HIPAA Safe Harbor procedure, annual review | E25: Procedure document | F25: Satisfactory | G25: None | K25: Closed (satisfactory)
A26: VQ-25 | B26: Data retention | C26: Defined retention for raw and derived data | D26: Raw extracts 90 days; derived features and models retained indefinitely | E26: Retention schedule | F26: Partially Satisfactory | G26: Data retention and return/destruction undefined | H26: Moderate | I26: Return/destroy within 30 days of termination with certificate; derived features deleted or contractually de-identified; retention schedule appended to MSA | J26: Theo Anand (General Counsel) | K26: In negotiation | L26: VR-005
A27: VQ-26 | B27: Termination and data return | C27: Return and destroy data within 30 days of termination with certificate | D27: 'Upon request'; no timeframe or certificate | E27: MSA §15 | F27: Unsatisfactory | G27: Data retention and return/destruction undefined | H27: Moderate | I27: Return/destroy within 30 days of termination with certificate; derived features deleted or contractually de-identified; retention schedule appended to MSA | J27: Theo Anand (General Counsel) | K27: In negotiation | L27: VR-005
A28: VQ-27 | B28: Subcontractors | C28: Complete list of subcontractors with access to Wrenfield data | D28: Initially listed 2 (cloud warehouse, cloud host); 4 identified after SOC 2 review and interview | E28: Questionnaire v1 vs interview notes | F28: Unsatisfactory | G28: Incomplete subcontractor disclosure; no notice of new subcontractors | H28: Moderate | I28: Complete subcontractor schedule in amendment; 30-day advance notice and right to object; SHCA approval workflow | J28: Theo Anand (General Counsel) | K28: In negotiation | L28: VR-008
A29: VQ-28 | B29: Subcontractors | C29: BAA and security flow-down to every subcontractor | D29: BAAs with warehouse and offshore firm; offshore agreement lacks data-location restriction | E29: Subcontractor agreement excerpts | F29: Partially Satisfactory | G29: Undisclosed offshore subcontractor with production access to Wrenfield PHI | H29: Critical | I29: Immediate suspension of offshore access to Wrenfield data; contract amendment requiring US-only access with technical enforcement (geo-restricted IdP policy, US-only support roster) and access-log attestation quarterly | J29: Quarrystone CISO / Miriam Castell | K29: Interim contained (offshore access suspended 2026-07-24); contractual fix open | L29: VR-001
A30: VQ-29 | B30: Subcontractors | C30: Advance notice and right to object to new subcontractors | D30: No notice provision | E30: MSA | F30: Unsatisfactory | G30: Incomplete subcontractor disclosure; no notice of new subcontractors | H30: Moderate | I30: Complete subcontractor schedule in amendment; 30-day advance notice and right to object; SHCA approval workflow | J30: Theo Anand (General Counsel) | K30: In negotiation | L30: VR-008
A31: VQ-30 | B31: Personnel security | C31: Background checks for staff with data access | D31: US staff screened; subcontractor staff screened by subcontractor under local law | E31: HR policy; subcontractor attestation | F31: Partially Satisfactory | G31: Undisclosed offshore subcontractor with production access to Wrenfield PHI | H31: Critical | I31: Immediate suspension of offshore access to Wrenfield data; contract amendment requiring US-only access with technical enforcement (geo-restricted IdP policy, US-only support roster) and access-log attestation quarterly | J31: Quarrystone CISO / Miriam Castell | K31: Interim contained (offshore access suspended 2026-07-24); contractual fix open | L31: VR-001
A32: VQ-31 | B32: Personnel security | C32: Annual security and HIPAA training | D32: Annual training; 98% completion | E32: LMS summary | F32: Satisfactory | G32: None | K32: Closed (satisfactory)
A33: VQ-32 | B33: Risk transfer | C33: Cyber liability insurance adequate to data volume | D33: $5M cyber policy | E33: Certificate of insurance | F33: Satisfactory | G33: None ($5M may be light for about 410k records; considered in the Transfer decision) | K33: Closed (satisfactory)
A34: VQ-33 | B34: Change management | C34: Changes approved and tested before production | D34: SOC 2 notes 2 of 40 changes lacked approval (remediated) | E34: SOC 2 CC8.1 exception | F34: Partially Satisfactory | G34: SOC 2 exceptions (access reviews, change approvals) | H34: Low | I34: Monitor: obtain next SOC 2 (expected 2026-12) and confirm exceptions resolved | J34: Beth Kowalski | K34: Monitor | L34: VR-006
A35: VQ-34 | B35: Physical security | C35: Physical security of facilities hosting data | D35: Inherited from cloud providers (SOC 2 carve-out) | E35: SOC 2 subservice section | F35: Satisfactory | G35: None (Reliance on subservice organizations noted) | K35: Closed (satisfactory)
A36: VQ-35 | B36: Data transfer | C36: Secure, supported transfer mechanism from Wrenfield | D36: Vendor receives via SFTP from Wrenfield's wf-sftp-01 (Wrenfield-side, unsupported OS) | E36: Data Sharing Spec v2 | F36: Unsatisfactory | G36: Extract transferred from an unsupported Wrenfield host | H36: Moderate | I36: Managed transfer service (POAM-011) with PGP-encrypted files | J36: Tomasz Wierzbicki | K36: In progress (delayed; POAM-011) | L36: VR-012
A37: VQ-36 | B37: Assurance cooperation | C37: Right to assess; annual questionnaire; evidence on request | D37: Annual questionnaire; on-site with 30 days notice | E37: MSA §10 | F37: Satisfactory | G37: None | K37: Closed (satisfactory)

Sheet VendorFindings
A1: VR ID | B1: Title | C1: Severity | D1: Party Responsible | E1: Questions | F1: Description | G1: Recommendation | H1: Owner | I1: Status | J1: Related Finding | K1: Escalation
A2: VR-001 | B2: Undisclosed offshore subcontractor with production access to Wrenfield PHI | C2: Critical | D2: Vendor | E2: VQ-05, VQ-23, VQ-28, VQ-30 | F2: Meridian Offshore Data Services (Pune) performs pipeline troubleshooting with production read access to Wrenfield's full PHI dataset. Conflicts with SHCA CSA §6.1 (for SHCA data) and 2 current customer BAAs (incl. Lakemont) that prohibit offshore access. | G2: Immediate suspension of offshore access to Wrenfield data; contract amendment requiring US-only access with technical enforcement (geo-restricted IdP policy, US-only support roster) and access-log attestation quarterly | H2: Quarrystone CISO / Miriam Castell | I2: Interim contained (offshore access suspended 2026-07-24); contractual fix open | J2: FIND-016 | K2: CEO notified 2026-07-17 (Critical = outside appetite; 5-business-day rule met)
A3: VR-002 | B3: Breach notification term of 30 days | C3: High | D3: Vendor | E3: VQ-16 | F3: BAA allows up to 30 days. Wrenfield must notify SHCA within 24h and customers within 5 business days, so a 30-day upstream delay makes compliance impossible. | G3: Amend BAA to 24h notice of suspected or confirmed incidents affecting Wrenfield data, with defined content and updates | H3: Theo Anand (General Counsel) | I3: In negotiation (redline v3) | J3: FIND-016
A4: VR-003 | B4: Extract exceeds minimum necessary (27 of 58 fields unused) | C4: High | D4: Wrenfield | E4: VQ-21 | F4: Wrenfield sends address, phone, email, and free-text notes that the model does not use. Increases breach impact and conflicts with HIPAA minimum necessary (164.502(b)). | G4: Redesign extract to 31 required fields; replace direct identifiers with tokenized IDs; re-validate model on minimized data | H4: Liam Porter (Data Engineering) | I4: In progress (target 2026-10-16) | J4: FIND-016
A5: VR-004 | B5: Penetration test evidence stale and incomplete | C5: Moderate | D5: Vendor | E5: VQ-12 | F5: Last external test 2025-03 (18 months). Summary letter only. Retest of the High finding not evidenced. | G5: Provide full report (under NDA) or detailed executive summary with finding list and retest letter; annual testing clause in amendment | H5: Quarrystone CISO | I5: Evidence requested (EVID-051, overdue) | J5: FIND-016
A6: VR-005 | B6: Data retention and return/destruction undefined | C6: Moderate | D6: Vendor | E6: VQ-25, VQ-26 | F6: Return 'upon request' with no timeframe or certificate. Derived data kept indefinitely. | G6: Return/destroy within 30 days of termination with certificate; derived features deleted or contractually de-identified; retention schedule appended to MSA | H6: Theo Anand (General Counsel) | I6: In negotiation | J6: FIND-016
A7: VR-006 | B7: SOC 2 exceptions (access reviews, change approvals) | C7: Low | D7: Vendor | E7: VQ-03, VQ-04, VQ-33 | F7: 2 exceptions with adequate management responses. Report period ended 2025-09-30. Bridge letter covers to 2026-03-31. | G7: Monitor: obtain next SOC 2 (expected 2026-12) and confirm exceptions resolved | H7: Beth Kowalski | I7: Monitor
A8: VR-007 | B8: Wrenfield not performing SOC 2 CUEC for portal user management; no SSO | C8: Moderate | D8: Wrenfield | E8: VQ-07 | F8: The SOC 2 lists 'user entities are responsible for managing and reviewing their users' portal access' as a complementary user-entity control. Wrenfield had never reviewed its 6 portal user accounts; 1 former employee was active (AR-EX-04). | G8: Add portal to quarterly certification and JML checklist (done); budget SAML SSO at renewal | H8: Liam Porter | I8: Partially remediated (review + JML done; SSO at 2027 renewal) | J8: FIND-001
A9: VR-008 | B9: Incomplete subcontractor disclosure; no notice of new subcontractors | C9: Moderate | D9: Vendor | E9: VQ-27, VQ-29 | F9: Questionnaire listed 2 subcontractors; 4 exist. No contractual notice or approval for new subcontractors. SHCA CSA §6.3 requires approval before a subcontractor accesses agency data. | G9: Complete subcontractor schedule in amendment; 30-day advance notice and right to object; SHCA approval workflow | H9: Theo Anand (General Counsel) | I9: In negotiation | J9: FIND-016
A10: VR-009 | B10: Access logs kept 90 days; no commitment to support investigations | C10: Moderate | D10: Vendor | E10: VQ-17, VQ-20 | F10: Wrenfield could not scope a breach at the vendor older than 90 days. | G10: 12-month log retention for access to Wrenfield data; contractual log provision within 5 business days of request | H10: Theo Anand (General Counsel) | I10: In negotiation | J10: FIND-016
A11: VR-010 | B11: Secondary use of pooled de-identified data | C11: Moderate | D11: Both (legal review) | E11: VQ-22 | F11: Vendor de-identifies Wrenfield-supplied PHI and pools it for cross-client model training. Whether Wrenfield's customer BAAs permit its subcontractor to de-identify for this purpose is unresolved. Safe Harbor output is not PHI, but the act of de-identifying is a use of PHI that must be permitted. | G11: General Counsel opinion; either opt Wrenfield data out of pooling or confirm customer BAAs permit it and disclose | H11: Theo Anand (General Counsel) | I11: Legal review in progress | J11: FIND-016
A12: VR-011 | B12: No SBOM for vendor software | C12: Low | D12: Vendor | E12: VQ-14 | F12: Limits Wrenfield's ability to assess exposure to newly disclosed component vulnerabilities. | G12: Request SBOM availability on the roadmap; revisit at 2027 renewal | H12: Beth Kowalski | I12: Monitor
A13: VR-012 | B13: Extract transferred from an unsupported Wrenfield host | C13: Moderate | D13: Wrenfield | E13: VQ-35 | F13: The full-PHI extract leaves via wf-sftp-01 (Windows Server 2012 R2). | G13: Managed transfer service (POAM-011) with PGP-encrypted files | H13: Tomasz Wierzbicki | I13: In progress (delayed; POAM-011) | J13: FIND-011

Sheet RiskDecision
A1: Element | B1: Decision
A2: Inherent vendor risk | B2: Critical (Tier 1 score 12/14): full PHI of about 410k patients, external processing, undisclosed offshore access, weak notification terms
A3: Material findings | B3: VR-001, VR-002, VR-003
A4: Mitigating controls | B4: SOC 2 Type II (unqualified), strong encryption and MFA, immutable backups, US storage, $5M cyber insurance, WCP rules-based fallback for scores, interim suspension of offshore access (2026-07-24)
A5: Residual risk | B5: Moderate after conditions (RISK-010 residual L2 x I4 = 8); High until conditions are met
A6: Recommended treatment | B6: Mitigate (conditional continuation) + partial Transfer
A7: Rationale | B7: Avoid (replace the vendor) was rejected: replacement takes 9 to 12 months, the rules-based fallback is materially less accurate, and the vendor's core controls are mature. The problems are contractual and in data design, not a weak security program. Accept was rejected: VR-001 is Critical and VR-002/VR-003 are High, all outside appetite (RSK-MTH-001 §7). Transfer alone is insufficient: insurance and indemnity move money, not accountability or contractual compliance. Mitigate works because the 2027-01-31 renewal gives leverage and the fixes are well-defined. SHCA data will not flow to Quarrystone until the conditions precedent are met.
A8: Approved by | B8: Elena Marsh (CEO) on recommendation of CISO and VP Clinical Analytics, 2026-07-22
A9: Conditions precedent (SHCA data) | B9: Executed amendment: US-only storage and access with technical enforcement; subcontractor schedule and approval rights (VR-001, VR-008) | 24-hour breach notification (VR-002) | Minimized, tokenized extract live (VR-003)
A10: Contract / security requirements | B10: 24h incident notification with defined content and updates | US-only data storage and access, including subcontractors; quarterly access-log attestation | Subcontractor schedule; 30-day advance notice; right to object; SHCA approval for agency data | Data return/destruction within 30 days of termination with certificate; retention schedule | 12-month access-log retention; log provision within 5 business days | Annual independent penetration test with retest evidence | No secondary use of Wrenfield data without written consent (pending legal opinion, VR-010) | Cyber insurance of at least $10M (raise from $5M) naming Wrenfield as additional insured; indemnity for breach costs | SAML SSO for portal (Enterprise tier) at renewal
A11: Monitoring requirements | B11: Quarterly: US-only access attestation with access-log sample; subcontractor change notice check | Semi-annual: SOC 2 report or bridge letter; open-issue review with vendor CISO | Continuous: external attack-surface and breach-news monitoring; contract-renewal trigger | Event-driven: reassess on incident, subcontractor change, or material service change
A12: Reassessment frequency | B12: Focused reassessment 2027-01 (before SHCA data flows), then annual full assessment (Tier 1)
